Workbook

Sheet Dashboard
A1: AstroMarket Dashboard — first trading day Tuesday 27 Oct 2026
A2: Today = that session · Short = next 5 sessions (averaged) · Long = next 40 sessions (averaged)
A4: Sky | B4: Candra Meṣa 24°40′ · Bharaṇī · opening lagna Vṛścika 14°14′
A5: Business cycle | B5: Over-expansion & boom [ACTIVE] — Śani Mīna 15°22′ R, Guru Karkaṭa 29°29′
A6: Book guidance | B6: Śani in watery rāśi aspected by Guru – euphoria; book advises booking profits and holding cash.
G7: Confidence = shrunk historical hit-rate of comparable calls (same target, horizon, strength). ~50% means no demonstrated edge.
A8: Target | B8: Intraday | C8: Short | D8: Long | E8: Composite | F8: Call | G8: Intraday conf. | H8: Short conf. | I8: Long conf.
A9: Nifty 50 (market) | B9: -0.493 | C9: 0.203 | D9: 0.065 | E9: =Settings!$C$5*B9+Settings!$C$6*C9+Settings!$C$7*D9 -> -0.1726 | F9: =IF(E9>Settings!$C$4,"Bullish",IF(E9<-Settings!$C$4,"Bearish","Neutral")) -> Bearish | G9: 0.529 | H9: 0.495
A10: Agriculture & agro industries | B10: -0.515 | C10: 0.142 | D10: -0.008 | E10: =Settings!$C$5*B10+Settings!$C$6*C10+Settings!$C$7*D10 -> -0.2165 | F10: =IF(E10>Settings!$C$4,"Bullish",IF(E10<-Settings!$C$4,"Bearish","Neutral")) -> Bearish | G10: 0.485
A11: Automobile | B11: 0.003 | C11: 0.032 | D11: 0.002 | E11: =Settings!$C$5*B11+Settings!$C$6*C11+Settings!$C$7*D11 -> 0.0115 | F11: =IF(E11>Settings!$C$4,"Bullish",IF(E11<-Settings!$C$4,"Bearish","Neutral")) -> Neutral
A12: Aviation | B12: 0.07 | C12: 0.032 | D12: 0.088 | E12: =Settings!$C$5*B12+Settings!$C$6*C12+Settings!$C$7*D12 -> 0.0622 | F12: =IF(E12>Settings!$C$4,"Bullish",IF(E12<-Settings!$C$4,"Bearish","Neutral")) -> Neutral
A13: Banking & financial | B13: -0.711 | C13: 0.146 | D13: 0.112 | E13: =Settings!$C$5*B13+Settings!$C$6*C13+Settings!$C$7*D13 -> -0.2893 | F13: =IF(E13>Settings!$C$4,"Bullish",IF(E13<-Settings!$C$4,"Bearish","Neutral")) -> Bearish | G13: 0.488
A14: Capital goods | B14: 0.069 | C14: 0.032 | D14: 0.049 | E14: =Settings!$C$5*B14+Settings!$C$6*C14+Settings!$C$7*D14 -> 0.0539 | F14: =IF(E14>Settings!$C$4,"Bullish",IF(E14<-Settings!$C$4,"Bearish","Neutral")) -> Neutral
A15: Cement | B15: 0.026 | C15: 0.097 | D15: -0.054 | E15: =Settings!$C$5*B15+Settings!$C$6*C15+Settings!$C$7*D15 -> 0.0313 | F15: =IF(E15>Settings!$C$4,"Bullish",IF(E15<-Settings!$C$4,"Bearish","Neutral")) -> Neutral
A16: Crude oil & gas | B16: 0.059 | C16: 0.233 | D16: -0.159 | E16: =Settings!$C$5*B16+Settings!$C$6*C16+Settings!$C$7*D16 -> 0.0676 | F16: =IF(E16>Settings!$C$4,"Bullish",IF(E16<-Settings!$C$4,"Bearish","Neutral")) -> Neutral | H16: 0.523 | I16: 0.448
A17: Eatable oil | B17: 0.129 | C17: 0.032 | D17: -0.005 | E17: =Settings!$C$5*B17+Settings!$C$6*C17+Settings!$C$7*D17 -> 0.0731 | F17: =IF(E17>Settings!$C$4,"Bullish",IF(E17<-Settings!$C$4,"Bearish","Neutral")) -> Neutral
A18: Educational | B18: -0.402 | C18: 0.032 | D18: 0.101 | E18: =Settings!$C$5*B18+Settings!$C$6*C18+Settings!$C$7*D18 -> -0.1712 | F18: =IF(E18>Settings!$C$4,"Bullish",IF(E18<-Settings!$C$4,"Bearish","Neutral")) -> Bearish | G18: 0.516
A19: Essential oils & perfumeries | B19: -0.778 | C19: -0.047 | D19: 0.128 | E19: =Settings!$C$5*B19+Settings!$C$6*C19+Settings!$C$7*D19 -> -0.3775 | F19: =IF(E19>Settings!$C$4,"Bullish",IF(E19<-Settings!$C$4,"Bearish","Neutral")) -> Bearish | G19: 0.506
A20: Exports | B20: -0.252 | C20: 0.032 | D20: -0.005 | E20: =Settings!$C$5*B20+Settings!$C$6*C20+Settings!$C$7*D20 -> -0.1174 | F20: =IF(E20>Settings!$C$4,"Bullish",IF(E20<-Settings!$C$4,"Bearish","Neutral")) -> Neutral | G20: 0.518
A21: FMCG | B21: -0.459 | C21: 0.284 | D21: 0.092 | E21: =Settings!$C$5*B21+Settings!$C$6*C21+Settings!$C$7*D21 -> -0.1259 | F21: =IF(E21>Settings!$C$4,"Bullish",IF(E21<-Settings!$C$4,"Bearish","Neutral")) -> Neutral | G21: 0.482 | H21: 0.531
A22: Gems & jewelry | B22: -0.439 | C22: 0.127 | D22: 0.468 | E22: =Settings!$C$5*B22+Settings!$C$6*C22+Settings!$C$7*D22 -> -0.0878 | F22: =IF(E22>Settings!$C$4,"Bullish",IF(E22<-Settings!$C$4,"Bearish","Neutral")) -> Neutral | G22: 0.478 | I22: 0.578
A23: Health care | B23: -0.544 | C23: -0.182 | D23: 0.002 | E23: =Settings!$C$5*B23+Settings!$C$6*C23+Settings!$C$7*D23 -> -0.3262 | F23: =IF(E23>Settings!$C$4,"Bullish",IF(E23<-Settings!$C$4,"Bearish","Neutral")) -> Bearish | G23: 0.517 | H23: 0.536
A24: Hospitality | B24: -0.691 | C24: -0.202 | D24: 0.132 | E24: =Settings!$C$5*B24+Settings!$C$6*C24+Settings!$C$7*D24 -> -0.3797 | F24: =IF(E24>Settings!$C$4,"Bullish",IF(E24<-Settings!$C$4,"Bearish","Neutral")) -> Bearish | G24: 0.504 | H24: 0.484
A25: Infrastructure | B25: 0.02 | C25: 0.052 | D25: -0.145 | E25: =Settings!$C$5*B25+Settings!$C$6*C25+Settings!$C$7*D25 -> -0.0034 | F25: =IF(E25>Settings!$C$4,"Bullish",IF(E25<-Settings!$C$4,"Bearish","Neutral")) -> Neutral
A26: IT | B26: 0.038 | C26: 0.032 | D26: 0.073 | E26: =Settings!$C$5*B26+Settings!$C$6*C26+Settings!$C$7*D26 -> 0.0432 | F26: =IF(E26>Settings!$C$4,"Bullish",IF(E26<-Settings!$C$4,"Bearish","Neutral")) -> Neutral
A27: Leather & footwear | B27: 0.181 | C27: 0.032 | D27: -0.339 | E27: =Settings!$C$5*B27+Settings!$C$6*C27+Settings!$C$7*D27 -> 0.0323 | F27: =IF(E27>Settings!$C$4,"Bullish",IF(E27<-Settings!$C$4,"Bearish","Neutral")) -> Neutral | G27: 0.457 | I27: 0.334
A28: Media & entertainment | B28: -0.781 | C28: -0.121 | D28: 0.363 | E28: =Settings!$C$5*B28+Settings!$C$6*C28+Settings!$C$7*D28 -> -0.3542 | F28: =IF(E28>Settings!$C$4,"Bullish",IF(E28<-Settings!$C$4,"Bearish","Neutral")) -> Bearish | G28: 0.52 | I28: 0.431
A29: Metal | B29: 0.104 | C29: 0.097 | D29: -0.048 | E29: =Settings!$C$5*B29+Settings!$C$6*C29+Settings!$C$7*D29 -> 0.0715 | F29: =IF(E29>Settings!$C$4,"Bullish",IF(E29<-Settings!$C$4,"Bearish","Neutral")) -> Neutral
A30: Paints | B30: -0.468 | C30: -0.202 | D30: 0.132 | E30: =Settings!$C$5*B30+Settings!$C$6*C30+Settings!$C$7*D30 -> -0.2682 | F30: =IF(E30>Settings!$C$4,"Bullish",IF(E30<-Settings!$C$4,"Bearish","Neutral")) -> Bearish | G30: 0.527 | H30: 0.513
A31: Pharmaceutical | B31: -0.261 | C31: 0.032 | D31: -0.126 | E31: =Settings!$C$5*B31+Settings!$C$6*C31+Settings!$C$7*D31 -> -0.1461 | F31: =IF(E31>Settings!$C$4,"Bullish",IF(E31<-Settings!$C$4,"Bearish","Neutral")) -> Neutral | G31: 0.527
A32: Power | B32: -0.151 | C32: 0.021 | D32: 0.094 | E32: =Settings!$C$5*B32+Settings!$C$6*C32+Settings!$C$7*D32 -> -0.0504 | F32: =IF(E32>Settings!$C$4,"Bullish",IF(E32<-Settings!$C$4,"Bearish","Neutral")) -> Neutral | G32: 0.493
A33: Publication | B33: 0.038 | C33: 0.032 | D33: 0.101 | E33: =Settings!$C$5*B33+Settings!$C$6*C33+Settings!$C$7*D33 -> 0.0488 | F33: =IF(E33>Settings!$C$4,"Bullish",IF(E33<-Settings!$C$4,"Bearish","Neutral")) -> Neutral
A34: Realty | B34: 0.217 | C34: 0.052 | D34: -0.145 | E34: =Settings!$C$5*B34+Settings!$C$6*C34+Settings!$C$7*D34 -> 0.0951 | F34: =IF(E34>Settings!$C$4,"Bullish",IF(E34<-Settings!$C$4,"Bearish","Neutral")) -> Neutral | G34: 0.468
A35: Shipping | B35: 0.161 | C35: 0.184 | D35: -0.015 | E35: =Settings!$C$5*B35+Settings!$C$6*C35+Settings!$C$7*D35 -> 0.1327 | F35: =IF(E35>Settings!$C$4,"Bullish",IF(E35<-Settings!$C$4,"Bearish","Neutral")) -> Neutral | G35: 0.5 | H35: 0.439
A36: Sugar | B36: -0.789 | C36: -0.202 | D36: 0.08 | E36: =Settings!$C$5*B36+Settings!$C$6*C36+Settings!$C$7*D36 -> -0.4391 | F36: =IF(E36>Settings!$C$4,"Bullish",IF(E36<-Settings!$C$4,"Bearish","Neutral")) -> Bearish | G36: 0.498 | H36: 0.515
A37: Telecommunication | B37: -0.161 | C37: 0.424 | D37: 0.077 | E37: =Settings!$C$5*B37+Settings!$C$6*C37+Settings!$C$7*D37 -> 0.0621 | F37: =IF(E37>Settings!$C$4,"Bullish",IF(E37<-Settings!$C$4,"Bearish","Neutral")) -> Neutral | G37: 0.483 | H37: 0.528
A38: Textile | B38: -0.456 | C38: 0.146 | D38: 0.112 | E38: =Settings!$C$5*B38+Settings!$C$6*C38+Settings!$C$7*D38 -> -0.1618 | F38: =IF(E38>Settings!$C$4,"Bullish",IF(E38<-Settings!$C$4,"Bearish","Neutral")) -> Bearish | G38: 0.511
A39: Travel & tourism | B39: -0.642 | C39: 0.152 | D39: 0.157 | E39: =Settings!$C$5*B39+Settings!$C$6*C39+Settings!$C$7*D39 -> -0.244 | F39: =IF(E39>Settings!$C$4,"Bullish",IF(E39<-Settings!$C$4,"Bearish","Neutral")) -> Bearish | G39: 0.444 | H39: 0.466 | I39: 0.463
A40: Gov. public sector units (PSU) | B40: -0.23 | C40: 0.032 | D40: -0.054 | E40: =Settings!$C$5*B40+Settings!$C$6*C40+Settings!$C$7*D40 -> -0.1162 | F40: =IF(E40>Settings!$C$4,"Bullish",IF(E40<-Settings!$C$4,"Bearish","Neutral")) -> Neutral | G40: 0.478
A41: Gold | B41: 0.059 | C41: 0.642 | D41: 0.752 | E41: =Settings!$C$5*B41+Settings!$C$6*C41+Settings!$C$7*D41 -> 0.3725 | F41: =IF(E41>Settings!$C$4,"Bullish",IF(E41<-Settings!$C$4,"Bearish","Neutral")) -> Bullish | H41: 0.442 | I41: 0.522
A42: Silver | B42: -0.463 | C42: -0.056 | D42: 0.085 | E42: =Settings!$C$5*B42+Settings!$C$6*C42+Settings!$C$7*D42 -> -0.2313 | F42: =IF(E42>Settings!$C$4,"Bullish",IF(E42<-Settings!$C$4,"Bearish","Neutral")) -> Bearish | G42: 0.494
A43: Crude oil | B43: 0.062 | C43: 0.134 | D43: -0.272 | E43: =Settings!$C$5*B43+Settings!$C$6*C43+Settings!$C$7*D43 -> 0.0168 | F43: =IF(E43>Settings!$C$4,"Bullish",IF(E43<-Settings!$C$4,"Bearish","Neutral")) -> Neutral | I43: 0.364
A44: Natural gas | B44: 0.257 | C44: 0.142 | D44: -0.223 | E44: =Settings!$C$5*B44+Settings!$C$6*C44+Settings!$C$7*D44 -> 0.1265 | F44: =IF(E44>Settings!$C$4,"Bullish",IF(E44<-Settings!$C$4,"Bearish","Neutral")) -> Neutral | G44: 0.516 | I44: 0.508
A45: Copper | B45: -0.648 | C45: -0.213 | D45: 0.155 | E45: =Settings!$C$5*B45+Settings!$C$6*C45+Settings!$C$7*D45 -> -0.3569 | F45: =IF(E45>Settings!$C$4,"Bullish",IF(E45<-Settings!$C$4,"Bearish","Neutral")) -> Bearish | G45: 0.503 | H45: 0.485 | I45: 0.462
A46: Aluminium | B46: 0.06 | C46: 0.154 | D46: 0.003 | E46: =Settings!$C$5*B46+Settings!$C$6*C46+Settings!$C$7*D46 -> 0.0768 | F46: =IF(E46>Settings!$C$4,"Bullish",IF(E46<-Settings!$C$4,"Bearish","Neutral")) -> Neutral | H46: 0.441
A47: Iron & steel | B47: 0.002 | C47: 0 | D47: -0.102 | E47: =Settings!$C$5*B47+Settings!$C$6*C47+Settings!$C$7*D47 -> -0.0194 | F47: =IF(E47>Settings!$C$4,"Bullish",IF(E47<-Settings!$C$4,"Bearish","Neutral")) -> Neutral
A48: Wheat / food grains | B48: 0.038 | C48: 0 | D48: 0.048 | E48: =Settings!$C$5*B48+Settings!$C$6*C48+Settings!$C$7*D48 -> 0.0286 | F48: =IF(E48>Settings!$C$4,"Bullish",IF(E48<-Settings!$C$4,"Bearish","Neutral")) -> Neutral
A49: Cotton | B49: -0.032 | C49: 0 | D49: 0 | E49: =Settings!$C$5*B49+Settings!$C$6*C49+Settings!$C$7*D49 -> -0.016 | F49: =IF(E49>Settings!$C$4,"Bullish",IF(E49<-Settings!$C$4,"Bearish","Neutral")) -> Neutral
A50: Sugar (commodity) | B50: -0.509 | C50: -0.213 | D50: 0.085 | E50: =Settings!$C$5*B50+Settings!$C$6*C50+Settings!$C$7*D50 -> -0.3014 | F50: =IF(E50>Settings!$C$4,"Bullish",IF(E50<-Settings!$C$4,"Bearish","Neutral")) -> Bearish | G50: 0.5 | H50: 0.502
A52: Intraday timing (horā, Ch.10)
A53: 09:15–09:37 Śukra horā: SELL during — silver, copper, diamond, peppermint oil, essential oils, diamond cutting, jewelry, hospitality, hotels, tourism, media & entertainment, FMCG, finance, banking, garments, sugar and agricultural sector stocks
A54: 09:37–10:37 Budha horā: SELL during — telecommunication, FMCG, food grains, cotton, paper, newsprint, peppermint, agro products, insurance, textile, exports, aviation, IT, banking and financial, media, advertising, educational and publication sector stocks
A55: 10:37–11:37 Candra horā: BUY before / during — crude, silver, aluminum, peppermint, eatable oils, oil & gas, petroleum and shipping sector stocks
A56: 11:37–12:37 Śani horā: SELL during — oil & gas, cement, realty, infrastructure, iron & steel, metal, mining, coal, agricultural products, leather & footwear sector stocks
A57: 12:37–13:37 Guru horā: BUY before / during — gold, bronze, food grains, mustard, FMCG, banking & financial, insurance, eatable oils, textile, shipping, exports, gems and jewelry sector stocks
A58: 13:37–14:37 Maṅgala horā: BUY before / during — copper, steel, metal, spices, pharmaceutical, health care, automobile, crude oil, capital goods, cement and infrastructure sector stocks
A59: 14:37–15:30 Sūrya horā: SELL during — gold, copper, bronze as well as power and media sector stocks
A61: Micro-daśā windows (Ch.12)
A62: 09:15–09:38 Śukra daśā: negative momentum (Gems & jewelry, Textile, Media & entertainment, Essential oils & perfumeries, Health care)
A63: 09:38–10:02 Sūrya daśā: negative momentum (Power, Media & entertainment, Gov. public sector units (PSU), Gold, Copper)
A64: 10:02–10:42 Candra daśā: positive momentum (Crude oil & gas, Crude oil, Natural gas, Shipping, Silver)
... A72: Business-cycle regime: Over-expansion & boom [ACTIVE]. Śani in watery rāśi aspected by Guru – euphoria; book advises booking profits and holding cash.

Sheet Settings
A1: Settings & legend
A2: Yellow cells are inputs. Change them and every call, colour and tracker statistic in the workbook updates.
B3: Parameter | C3: Value | D3: Note
B4: Green / Red threshold (|score| above which a call is Bullish / Bearish) | C4: 0.15 | D4: Engine default 0.15. Scores run −1 … +1.
B5: Overall-view weight — today | C5: 0.5 | D5: Overall = w·today + w·next week + w·next 2 months (pre-computed in Daily_Composite with these defaults).
B6: Overall-view weight — next week | C6: 0.3
B7: Overall-view weight — next 2 months | C7: 0.2
B8: Workbook generated | C8: 2026-10-26 16:31 | D8: Re-run build_excel.py to roll forward.
B9: Market location / opening bell | C9: NSE/BSE Mumbai 09:15 | D9: Opening-bell chart & horā computed for this place.
B12: Legend
C13: Bullish (score > threshold)
C14: Neutral (|score| ≤ threshold)
C15: Bearish (score < −threshold)
C16: Input cell (blue text) — edit me
B18: Important
B19: Backtest 2012-02-21 → 2026-10-23 on NSE indices: intraday directional hit-rate 50.5% (95% CI 50.0–51.0%), short-term 50.5%, long-term 46.1% vs ~60% for a naive "always up" call. Treat outputs as an implementation of the book, not as a validated trading signal.

Sheet Grid_12M
A1: Day-box grid — 12 months × all sectors & commodities (daily composite)
A2: Each box links to Daily_Composite; green = Bullish, amber = Neutral, red = Bearish. Weekend columns shaded headers.
B3: Oct-26 | G3: Nov-26 | AK3: Dec-26 | BP3: Jan-27 | CU3: Feb-27 | DW3: Mar-27 | FB3: Apr-27 | GF3: May-27 | HK3: Jun-27 | IO3: Jul-27 | JT3: Aug-27 | KY3: Sep-27 | MC3: Oct-27
A4: Target | B4: 27 | C4: 28 | D4: 29 | E4: 30 | F4: 31 | G4: 1 | H4: 2 | I4: 3 | J4: 4 | K4: 5 | L4: 6 | M4: 7 | N4: 8 | O4: 9 | P4: 10 | Q4: 11 | R4: 12 | S4: 13 | T4: 14 | U4: 15 | V4: 16 | W4: 17 | X4: 18 | Y4: 19 | Z4: 20 | AA4: 21 | AB4: 22 | AC4: 23 | AD4: 24 | AE4: 25 | AF4: 26 | AG4: 27 | AH4: 28 | AI4: 29 | AJ4: 30 | AK4: 1 | AL4: 2 | AM4: 3 | AN4: 4 | AO4: 5 | AP4: 6 | AQ4: 7 | AR4: 8 | AS4: 9 | AT4: 10 | AU4: 11 | AV4: 12 | AW4: 13 | AX4: 14 | AY4: 15 | AZ4: 16 | BA4: 17 | BB4: 18 | BC4: 19 | BD4: 20 | BE4: 21 | BF4: 22 | BG4: 23 | BH4: 24 | BI4: 25 | BJ4: 26 | BK4: 27 | BL4: 28 | BM4: 29 | BN4: 30 | BO4: 31 | BP4: 1 | BQ4: 2 | BR4: 3 | BS4: 4 | BT4: 5 | BU4: 6 | BV4: 7 | BW4: 8 | BX4: 9 | BY4: 10 | BZ4: 11 | CA4: 12 | CB4: 13 | CC4: 14 | CD4: 15 | CE4: 16 | CF4: 17 | CG4: 18 | CH4: 19 | CI4: 20 | CJ4: 21 | CK4: 22 | CL4: 23 | CM4: 24 | CN4: 25 | CO4: 26 | CP4: 27 | CQ4: 28 | CR4: 29 | CS4: 30 | CT4: 31 | CU4: 1 | CV4: 2 | CW4: 3 | CX4: 4 | CY4: 5 | CZ4: 6 | DA4: 7 | DB4: 8 | DC4: 9 | DD4: 10 | DE4: 11 | DF4: 12 | DG4: 13 | DH4: 14 | DI4: 15 | DJ4: 16 | DK4: 17 | DL4: 18 | DM4: 19 | DN4: 20 | DO4: 21 | DP4: 22 | DQ4: 23 | DR4: 24 | DS4: 25 | DT4: 26 | DU4: 27 | DV4: 28 | DW4: 1 | DX4: 2 | DY4: 3 | DZ4: 4 | EA4: 5 | EB4: 6 | EC4: 7 | ED4: 8 | EE4: 9 | EF4: 10 | EG4: 11 | EH4: 12 | EI4: 13 | EJ4: 14 | EK4: 15 | EL4: 16 | EM4: 17 | EN4: 18 | EO4: 19 | EP4: 20 | EQ4: 21 | ER4: 22 | ES4: 23 | ET4: 24 | EU4: 25 | EV4: 26 | EW4: 27 | EX4: 28 | EY4: 29 | EZ4: 30 | FA4: 31 | FB4: 1 | FC4: 2 | FD4: 3 | FE4: 4 | FF4: 5 | FG4: 6 | FH4: 7 | FI4: 8 | FJ4: 9 | FK4: 10 | FL4: 11 | FM4: 12 | FN4: 13 | FO4: 14 | FP4: 15 | FQ4: 16 | FR4: 17 | FS4: 18 | FT4: 19 | FU4: 20 | FV4: 21 | FW4: 22 | FX4: 23 | FY4: 24 | FZ4: 25 | GA4: 26 | GB4: 27 | GC4: 28 | GD4: 29 | GE4: 30 | GF4: 1 | GG4: 2 | GH4: 3 | GI4: 4 | GJ4: 5 | GK4: 6 | GL4: 7 | GM4: 8 | GN4: 9 | GO4: 10 | GP4: 11 | GQ4: 12 | GR4: 13 | GS4: 14 | GT4: 15 | GU4: 16 | GV4: 17 | GW4: 18 | GX4: 19 | GY4: 20 | GZ4: 21 | HA4: 22 | HB4: 23 | HC4: 24 | HD4: 25 | HE4: 26 | HF4: 27 | HG4: 28 | HH4: 29 | HI4: 30 | HJ4: 31 | HK4: 1 | HL4: 2 | HM4: 3 | HN4: 4 | HO4: 5 | HP4: 6 | HQ4: 7 | HR4: 8 | HS4: 9 | HT4: 10 | HU4: 11 | HV4: 12 | HW4: 13 | HX4: 14 | HY4: 15 | HZ4: 16 | IA4: 17 | IB4: 18 | IC4: 19 | ID4: 20 | IE4: 21 | IF4: 22 | IG4: 23 | IH4: 24 | II4: 25 | IJ4: 26 | IK4: 27 | IL4: 28 | IM4: 29 | IN4: 30 | IO4: 1 | IP4: 2 | IQ4: 3 | IR4: 4 | IS4: 5 | IT4: 6 | IU4: 7 | IV4: 8 | IW4: 9 | IX4: 10 | IY4: 11 | IZ4: 12 | JA4: 13 | JB4: 14 | JC4: 15 | JD4: 16 | JE4: 17 | JF4: 18 | JG4: 19 | JH4: 20 | JI4: 21 | JJ4: 22 | JK4: 23 | JL4: 24 | JM4: 25 | JN4: 26 | JO4: 27 | JP4: 28 | JQ4: 29 | JR4: 30 | JS4: 31 | JT4: 1 | JU4: 2 | JV4: 3 | JW4: 4 | JX4: 5 | JY4: 6 | JZ4: 7 | KA4: 8 | KB4: 9 | KC4: 10 | KD4: 11 | KE4: 12 | KF4: 13 | KG4: 14 | KH4: 15 | KI4: 16 | KJ4: 17 | KK4: 18 | KL4: 19 | KM4: 20 | KN4: 21 | KO4: 22 | KP4: 23 | KQ4: 24 | KR4: 25 | KS4: 26 | KT4: 27 | KU4: 28 | KV4: 29 | KW4: 30 | KX4: 31 | KY4: 1 | KZ4: 2 | LA4: 3 | LB4: 4 | LC4: 5 | LD4: 6 | LE4: 7 | LF4: 8 | LG4: 9 | LH4: 10 | LI4: 11 | LJ4: 12 | LK4: 13 | LL4: 14 | LM4: 15 | LN4: 16 | LO4: 17 | LP4: 18 | LQ4: 19 | LR4: 20 | LS4: 21 | LT4: 22 | LU4: 23 | LV4: 24 | LW4: 25 | LX4: 26 | LY4: 27 | LZ4: 28 | MA4: 29 | MB4: 30 | MC4: 1 | MD4: 2 | ME4: 3 | MF4: 4 | MG4: 5 | MH4: 6 | MI4: 7 | MJ4: 8 | MK4: 9 | ML4: 10 | MM4: 11 | MN4: 12 | MO4: 13 | MP4: 14 | MQ4: 15 | MR4: 16 | MS4: 17 | MT4: 18 | MU4: 19 | MV4: 20 | MW4: 21 | MX4: 22 | MY4: 23 | MZ4: 24 | NA4: 25 | NB4: 26
A5: Nifty 50 (market) | B5: =Daily_Composite!G5 -> -0.173 | C5: =Daily_Composite!G6 -> 0.04 | D5: =Daily_Composite!G7 -> 0.009 | E5: =Daily_Composite!G8 -> -0.07 | F5: =Daily_Composite!G9 -> -0.326 | G5: =Daily_Composite!G10 -> -0.215 | H5: =Daily_Composite!G11 -> 0.159 | I5: =Daily_Composite!G12 -> -0.356 | J5: =Daily_Composite!G13 -> 0.047 | K5: =Daily_Composite!G14 -> -0.028 | L5: =Daily_Composite!G15 -> -0.205 | M5: =Daily_Composite!G16 -> -0.179 | N5: =Daily_Composite!G17 -> -0.227 | O5: =Daily_Composite!G18 -> -0.235 | P5: =Daily_Composite!G19 -> 0.005 | Q5: =Daily_Composite!G20 -> -0.029 | R5: =Daily_Composite!G21 -> 0.507 | S5: =Daily_Composite!G22 -> -0.016 | T5: =Daily_Composite!G23 -> 0.461 | U5: =Daily_Composite!G24 -> 0.145 | V5: =Daily_Composite!G25 -> 0.186 | W5: =Daily_Composite!G26 -> -0.031 | X5: =Daily_Composite!G27 -> -0.146 | Y5: =Daily_Composite!G28 -> 0.28 | Z5: =Daily_Composite!G29 -> 0.082 | AA5: =Daily_Composite!G30 -> 0.337 | AB5: =Daily_Composite!G31 -> -0.141 | AC5: =Daily_Composite!G32 -> 0.168 | AD5: =Daily_Composite!G33 -> 0.307 | AE5: =Daily_Composite!G34 -> 0.259 | AF5: =Daily_Composite!G35 -> 0.531 | AG5: =Daily_Composite!G36 -> 0.473 | AH5: =Daily_Composite!G37 -> 0.485 | AI5: =Daily_Composite!G38 -> 0.52 | AJ5: =Daily_Composite!G39 -> 0.369 | AK5: =Daily_Composite!G40 -> 0.524 | AL5: =Daily_Composite!G41 -> 0.279 | AM5: =Daily_Composite!G42 -> 0.058 | AN5: =Daily_Composite!G43 -> 0.346 | AO5: =Daily_Composite!G44 -> -0.049 | AP5: =Daily_Composite!G45 -> 0.142 | AQ5: =Daily_Composite!G46 -> 0.508 | AR5: =Daily_Composite!G47 -> 0.04 | AS5: =Daily_Composite!G48 -> 0.07 | AT5: =Daily_Composite!G49 -> 0.086 | AU5: =Daily_Composite!G50 -> 0.348 | AV5: =Daily_Composite!G51 -> 0.161 | AW5: =Daily_Composite!G52 -> -0.064 | AX5: =Daily_Composite!G53 -> 0.135 | AY5: =Daily_Composite!G54 -> -0.088 | AZ5: =Daily_Composite!G55 -> -0.11 | BA5: =Daily_Composite!G56 -> 0.294 | BB5: =Daily_Composite!G57 -> -0.094 | BC5: =Daily_Composite!G58 -> -0.273 | BD5: =Daily_Composite!G59 -> 0.202 | BE5: =Daily_Composite!G60 -> -0.179 | BF5: =Daily_Composite!G61 -> 0.021 | BG5: =Daily_Composite!G62 -> 0.325 | BH5: =Daily_Composite!G63 -> -0.001 | BI5: =Daily_Composite!G64 -> 0.194 | BJ5: =Daily_Composite!G65 -> -0.157 | BK5: =Daily_Composite!G66 -> 0.088 | BL5: =Daily_Composite!G67 -> 0.08 | BM5: =Daily_Composite!G68 -> 0.202 | BN5: =Daily_Composite!G69 -> 0.062 | BO5: =Daily_Composite!G70 -> -0.094 | BP5: =Daily_Composite!G71 -> -0.01 | BQ5: =Daily_Composite!G72 -> -0.035 | BR5: =Daily_Composite!G73 -> 0.151 | BS5: =Daily_Composite!G74 -> -0.191 | BT5: =Daily_Composite!G75 -> 0.156 | BU5: =Daily_Composite!G76 -> -0.04 | BV5: =Daily_Composite!G77 -> -0.048 | BW5: =Daily_Composite!G78 -> 0.065 | BX5: =Daily_Composite!G79 -> -0.217 | BY5: =Daily_Composite!G80 -> -0.237 | BZ5: =Daily_Composite!G81 -> 0.188 | CA5: =Daily_Composite!G82 -> -0.01 | CB5: =Daily_Composite!G83 -> 0.251 | CC5: =Daily_Composite!G84 -> -0.2 | CD5: =Daily_Composite!G85 -> 0.367 | CE5: =Daily_Composite!G86 -> 0.179 | CF5: =Daily_Composite!G87 -> 0.47 | CG5: =Daily_Composite!G88 -> -0.224 | CH5: =Daily_Composite!G89 -> -0.249 | CI5: =Daily_Composite!G90 -> 0.285 | CJ5: =Daily_Composite!G91 -> 0.216 | CK5: =Daily_Composite!G92 -> -0.132 | CL5: =Daily_Composite!G93 -> -0.245 | CM5: =Daily_Composite!G94 -> 0.204 | CN5: =Daily_Composite!G95 -> -0.36 | CO5: =Daily_Composite!G96 -> -0.343 | CP5: =Daily_Composite!G97 -> -0.454 | CQ5: =Daily_Composite!G98 -> -0.631 | CR5: =Daily_Composite!G99 -> -0.64 | CS5: =Daily_Composite!G100 -> -0.617 | CT5: =Daily_Composite!G101 -> -0.535 | CU5: =Daily_Composite!G102 -> -0.648 | CV5: =Daily_Composite!G103 -> -0.663 | CW5: =Daily_Composite!G104 -> -0.676 | CX5: =Daily_Composite!G105 -> -0.655 | CY5: =Daily_Composite!G106 -> -0.553 | CZ5: =Daily_Composite!G107 -> -0.555 | DA5: =Daily_Composite!G108 -> -0.626 | DB5: =Daily_Composite!G109 -> -0.603 | DC5: =Daily_Composite!G110 -> -0.595 | DD5: =Daily_Composite!G111 -> -0.277 | DE5: =Daily_Composite!G112 -> -0.593 | DF5: =Daily_Composite!G113 -> -0.554 | DG5: =Daily_Composite!G114 -> -0.39 | DH5: =Daily_Composite!G115 -> -0.479 | DI5: =Daily_Composite!G116 -> -0.608 | DJ5: =Daily_Composite!G117 -> -0.69 | DK5: =Daily_Composite!G118 -> -0.685 | DL5: =Daily_Composite!G119 -> -0.592 | DM5: =Daily_Composite!G120 -> -0.33 | DN5: =Daily_Composite!G121 -> -0.554 | DO5: =Daily_Composite!G122 -> -0.427 | DP5: =Daily_Composite!G123 -> -0.271 | DQ5: =Daily_Composite!G124 -> -0.415 | DR5: =Daily_Composite!G125 -> -0.039 | DS5: =Daily_Composite!G126 -> -0.112 | DT5: =Daily_Composite!G127 -> -0.293 | DU5: =Daily_Composite!G128 -> 0.117 | DV5: =Daily_Composite!G129 -> -0.023 | DW5: =Daily_Composite!G130 -> 0.552 | DX5: =Daily_Composite!G131 -> 0.209 | DY5: =Daily_Composite!G132 -> 0.036 | DZ5: =Daily_Composite!G133 -> -0.076 | EA5: =Daily_Composite!G134 -> -0.196 | EB5: =Daily_Composite!G135 -> 0.095 | EC5: =Daily_Composite!G136 -> -0.054 | ED5: =Daily_Composite!G137 -> -0.366 | EE5: =Daily_Composite!G138 -> -0.117 | EF5: =Daily_Composite!G139 -> 0.136 | EG5: =Daily_Composite!G140 -> 0.238 | EH5: =Daily_Composite!G141 -> -0.143 | EI5: =Daily_Composite!G142 -> -0.019 | EJ5: =Daily_Composite!G143 -> -0.369 | EK5: =Daily_Composite!G144 -> -0.596 | EL5: =Daily_Composite!G145 -> -0.368 | EM5: =Daily_Composite!G146 -> -0.403 | EN5: =Daily_Composite!G147 -> -0.304 | EO5: =Daily_Composite!G148 -> -0.44 | EP5: =Daily_Composite!G149 -> 0.016 | EQ5: =Daily_Composite!G150 -> -0.206 | ER5: =Daily_Composite!G151 -> -0.161 | ES5: =Daily_Composite!G152 -> -0.244 | ET5: =Daily_Composite!G153 -> -0.423 | EU5: =Daily_Composite!G154 -> -0.339 | EV5: =Daily_Composite!G155 -> -0.091 | EW5: =Daily_Composite!G156 -> -0.039 | EX5: =Daily_Composite!G157 -> 0.228 | EY5: =Daily_Composite!G158 -> -0.301 | EZ5: =Daily_Composite!G159 -> 0.064 | FA5: =Daily_Composite!G160 -> -0.108 | FB5: =Daily_Composite!G161 -> -0.14 | FC5: =Daily_Composite!G162 -> 0.03 | FD5: =Daily_Composite!G163 -> -0.393 | FE5: =Daily_Composite!G164 -> -0.376 | FF5: =Daily_Composite!G165 -> 0.293 | FG5: =Daily_Composite!G166 -> -0.147 | FH5: =Daily_Composite!G167 -> 0.061 | FI5: =Daily_Composite!G168 -> -0.306 | FJ5: =Daily_Composite!G169 -> -0.023 | FK5: =Daily_Composite!G170 -> -0.076 | FL5: =Daily_Composite!G171 -> -0.194 | FM5: =Daily_Composite!G172 -> 0.034 | FN5: =Daily_Composite!G173 -> 0.05 | FO5: =Daily_Composite!G174 -> -0.203 | FP5: =Daily_Composite!G175 -> -0.076 | FQ5: =Daily_Composite!G176 -> -0.043 | FR5: =Daily_Composite!G177 -> 0.254 | FS5: =Daily_Composite!G178 -> -0.148 | FT5: =Daily_Composite!G179 -> -0.424 | FU5: =Daily_Composite!G180 -> -0.577 | FV5: =Daily_Composite!G181 -> -0.339 | FW5: =Daily_Composite!G182 -> -0.478 | FX5: =Daily_Composite!G183 -> -0.532 | FY5: =Daily_Composite!G184 -> -0.622 | FZ5: =Daily_Composite!G185 -> -0.4 | GA5: =Daily_Composite!G186 -> -0.119 | GB5: =Daily_Composite!G187 -> -0.224 | GC5: =Daily_Composite!G188 -> -0.556 | GD5: =Daily_Composite!G189 -> -0.287 | GE5: =Daily_Composite!G190 -> -0.168 | GF5: =Daily_Composite!G191 -> -0.496 | GG5: =Daily_Composite!G192 -> -0.595 | GH5: =Daily_Composite!G193 -> -0.422 | GI5: =Daily_Composite!G194 -> -0.284 | GJ5: =Daily_Composite!G195 -> 0.111 | GK5: =Daily_Composite!G196 -> 0.1 | GL5: =Daily_Composite!G197 -> -0.39 | GM5: =Daily_Composite!G198 -> -0.441 | GN5: =Daily_Composite!G199 -> -0.211 | GO5: =Daily_Composite!G200 -> -0.376 | GP5: =Daily_Composite!G201 -> -0.415 | GQ5: =Daily_Composite!G202 -> -0.384 | GR5: =Daily_Composite!G203 -> 0.121 | GS5: =Daily_Composite!G204 -> -0.401 | GT5: =Daily_Composite!G205 -> -0.222 | GU5: =Daily_Composite!G206 -> -0.417 | GV5: =Daily_Composite!G207 -> -0.357 | GW5: =Daily_Composite!G208 -> -0.369 | GX5: =Daily_Composite!G209 -> -0.446 | GY5: =Daily_Composite!G210 -> -0.386 | GZ5: =Daily_Composite!G211 -> -0.431 | HA5: =Daily_Composite!G212 -> -0.1 | HB5: =Daily_Composite!G213 -> -0.735 | HC5: =Daily_Composite!G214 -> -0.632 | HD5: =Daily_Composite!G215 -> -0.349 | HE5: =Daily_Composite!G216 -> -0.26 | HF5: =Daily_Composite!G217 -> -0.409 | HG5: =Daily_Composite!G218 -> -0.669 | HH5: =Daily_Composite!G219 -> -0.718 | HI5: =Daily_Composite!G220 -> -0.411 | HJ5: =Daily_Composite!G221 -> -0.41 | HK5: =Daily_Composite!G222 -> -0.46 | HL5: =Daily_Composite!G223 -> -0.663 | HM5: =Daily_Composite!G224 -> -0.631 | HN5: =Daily_Composite!G225 -> -0.727 | HO5: =Daily_Composite!G226 -> -0.711 | HP5: =Daily_Composite!G227 -> -0.75 | HQ5: =Daily_Composite!G228 -> -0.707 | HR5: =Daily_Composite!G229 -> -0.442 | HS5: =Daily_Composite!G230 -> -0.08 | HT5: =Daily_Composite!G231 -> -0.74 | HU5: =Daily_Composite!G232 -> -0.545 | HV5: =Daily_Composite!G233 -> -0.553 | HW5: =Daily_Composite!G234 -> -0.573 | HX5: =Daily_Composite!G235 -> -0.56 | HY5: =Daily_Composite!G236 -> -0.504 | HZ5: =Daily_Composite!G237 -> -0.347 | IA5: =Daily_Composite!G238 -> -0.29 | IB5: =Daily_Composite!G239 -> 0.147 | IC5: =Daily_Composite!G240 -> -0.202 | ID5: =Daily_Composite!G241 -> 0.025 | IE5: =Daily_Composite!G242 -> -0.263 | IF5: =Daily_Composite!G243 -> -0.21 | IG5: =Daily_Composite!G244 -> -0.196 | IH5: =Daily_Composite!G245 -> -0.083 | II5: =Daily_Composite!G246 -> -0.203 | IJ5: =Daily_Composite!G247 -> 0.304 | IK5: =Daily_Composite!G248 -> 0.295 | IL5: =Daily_Composite!G249 -> 0.515 | IM5: =Daily_Composite!G250 -> 0.196 | IN5: =Daily_Composite!G251 -> 0.512 | IO5: =Daily_Composite!G252 -> 0.104 | IP5: =Daily_Composite!G253 -> 0.131 | IQ5: =Daily_Composite!G254 -> 0.262 | IR5: =Daily_Composite!G255 -> 0.267 | IS5: =Daily_Composite!G256 -> -0.084 | IT5: =Daily_Composite!G257 -> 0.362 | IU5: =Daily_Composite!G258 -> 0.245 | IV5: =Daily_Composite!G259 -> 0.378 | IW5: =Daily_Composite!G260 -> 0.073 | IX5: =Daily_Composite!G261 -> 0.092 | IY5: =Daily_Composite!G262 -> -0.136 | IZ5: =Daily_Composite!G263 -> 0.055 | JA5: =Daily_Composite!G264 -> 0.074 | JB5: =Daily_Composite!G265 -> 0.019 | JC5: =Daily_Composite!G266 -> 0.223 | JD5: =Daily_Composite!G267 -> 0.154 | JE5: =Daily_Composite!G268 -> 0.225 | JF5: =Daily_Composite!G269 -> -0.021 | JG5: =Daily_Composite!G270 -> -0.118 | JH5: =Daily_Composite!G271 -> -0.212 | JI5: =Daily_Composite!G272 -> -0.301 | JJ5: =Daily_Composite!G273 -> -0.208 | JK5: =Daily_Composite!G274 -> -0.216 | JL5: =Daily_Composite!G275 -> -0.242 | JM5: =Daily_Composite!G276 -> 0.186 | JN5: =Daily_Composite!G277 -> -0.099 | JO5: =Daily_Composite!G278 -> -0.37 | JP5: =Daily_Composite!G279 -> -0.347 | JQ5: =Daily_Composite!G280 -> -0.418 | JR5: =Daily_Composite!G281 -> -0.411 | JS5: =Daily_Composite!G282 -> 0.181 | JT5: =Daily_Composite!G283 -> 0.11 | JU5: =Daily_Composite!G284 -> -0.248 | JV5: =Daily_Composite!G285 -> 0.294 | JW5: =Daily_Composite!G286 -> 0.32 | JX5: =Daily_Composite!G287 -> 0.054 | JY5: =Daily_Composite!G288 -> 0.138 | JZ5: =Daily_Composite!G289 -> 0.239 | KA5: =Daily_Composite!G290 -> 0.076 | KB5: =Daily_Composite!G291 -> 0.003 | KC5: =Daily_Composite!G292 -> -0.323 | KD5: =Daily_Composite!G293 -> 0.198 | KE5: =Daily_Composite!G294 -> 0.273 | KF5: =Daily_Composite!G295 -> 0.343 | KG5: =Daily_Composite!G296 -> -0.299 | KH5: =Daily_Composite!G297 -> -0.627 | KI5: =Daily_Composite!G298 -> -0.523 | KJ5: =Daily_Composite!G299 -> -0.447 | KK5: =Daily_Composite!G300 -> -0.401 | KL5: =Daily_Composite!G301 -> -0.416 | KM5: =Daily_Composite!G302 -> -0.253 | KN5: =Daily_Composite!G303 -> 0.257 | KO5: =Daily_Composite!G304 -> -0.294 | KP5: =Daily_Composite!G305 -> -0.322 | KQ5: =Daily_Composite!G306 -> -0.05 | KR5: =Daily_Composite!G307 -> -0.456 | KS5: =Daily_Composite!G308 -> -0.577 | KT5: =Daily_Composite!G309 -> -0.216 | KU5: =Daily_Composite!G310 -> -0.41 | KV5: =Daily_Composite!G311 -> -0.45 | KW5: =Daily_Composite!G312 -> -0.024 | KX5: =Daily_Composite!G313 -> -0.043 | KY5: =Daily_Composite!G314 -> -0.393 | KZ5: =Daily_Composite!G315 -> -0.284 | LA5: =Daily_Composite!G316 -> -0.32 | LB5: =Daily_Composite!G317 -> -0.247 | LC5: =Daily_Composite!G318 -> -0.136 | LD5: =Daily_Composite!G319 -> -0.066 | LE5: =Daily_Composite!G320 -> -0.1 | LF5: =Daily_Composite!G321 -> -0.042 | LG5: =Daily_Composite!G322 -> 0.068 | LH5: =Daily_Composite!G323 -> 0.469 | LI5: =Daily_Composite!G324 -> -0.005 | LJ5: =Daily_Composite!G325 -> -0.136 | LK5: =Daily_Composite!G326 -> -0.272 | LL5: =Daily_Composite!G327 -> 0.199 | LM5: =Daily_Composite!G328 -> 0.35 | LN5: =Daily_Composite!G329 -> 0.164 | LO5: =Daily_Composite!G330 -> -0.236 | LP5: =Daily_Composite!G331 -> 0.037 | LQ5: =Daily_Composite!G332 -> 0.049 | LR5: =Daily_Composite!G333 -> 0.27 | LS5: =Daily_Composite!G334 -> -0.303 | LT5: =Daily_Composite!G335 -> -0.501 | LU5: =Daily_Composite!G336 -> -0.718 | LV5: =Daily_Composite!G337 -> -0.302 | LW5: =Daily_Composite!G338 -> -0.323 | LX5: =Daily_Composite!G339 -> -0.382 | LY5: =Daily_Composite!G340 -> -0.319 | LZ5: =Daily_Composite!G341 -> -0.238 | MA5: =Daily_Composite!G342 -> -0.373 | MB5: =Daily_Composite!G343 -> -0.456 | MC5: =Daily_Composite!G344 -> -0.557 | MD5: =Daily_Composite!G345 -> -0.255 | ME5: =Daily_Composite!G346 -> -0.169 | MF5: =Daily_Composite!G347 -> 0.197 | MG5: =Daily_Composite!G348 -> 0.34 | MH5: =Daily_Composite!G349 -> 0.409 | MI5: =Daily_Composite!G350 -> 0.589 | MJ5: =Daily_Composite!G351 -> 0.664 | MK5: =Daily_Composite!G352 -> 0.385 | ML5: =Daily_Composite!G353 -> 0.412 | MM5: =Daily_Composite!G354 -> 0.429 | MN5: =Daily_Composite!G355 -> 0.136 | MO5: =Daily_Composite!G356 -> 0.442 | MP5: =Daily_Composite!G357 -> 0.646 | MQ5: =Daily_Composite!G358 -> 0.637 | MR5: =Daily_Composite!G359 -> 0.057 | MS5: =Daily_Composite!G360 -> 0.331 | MT5: =Daily_Composite!G361 -> 0.142 | MU5: =Daily_Composite!G362 -> 0.141 | MV5: =Daily_Composite!G363 -> -0.092 | MW5: =Daily_Composite!G364 -> -0.085 | MX5: =Daily_Composite!G365 -> -0.072 | MY5: =Daily_Composite!G366 -> 0.119 | MZ5: =Daily_Composite!G367 -> 0.307 | NA5: =Daily_Composite!G368 -> 0.035 | NB5: =Daily_Composite!G369 -> -0.003
A6: Agriculture & agro industries | B6: =Daily_Composite!H5 -> -0.217 | C6: =Daily_Composite!H6 -> 0.295 | D6: =Daily_Composite!H7 -> 0.125 | E6: =Daily_Composite!H8 -> 0.059 | F6: =Daily_Composite!H9 -> -0.315 | G6: =Daily_Composite!H10 -> 0.033 | H6: =Daily_Composite!H11 -> 0.451 | I6: =Daily_Composite!H12 -> 0.22 | J6: =Daily_Composite!H13 -> 0.381 | K6: =Daily_Composite!H14 -> 0.275 | L6: =Daily_Composite!H15 -> -0.16 | M6: =Daily_Composite!H16 -> 0.323 | N6: =Daily_Composite!H17 -> 0.207 | O6: =Daily_Composite!H18 -> -0.156 | P6: =Daily_Composite!H19 -> 0.549 | Q6: =Daily_Composite!H20 -> 0.417 | R6: =Daily_Composite!H21 -> 0.554 | S6: =Daily_Composite!H22 -> 0.261 | T6: =Daily_Composite!H23 -> 0.479 | U6: =Daily_Composite!H24 -> 0.231 | V6: =Daily_Composite!H25 -> 0.253 | W6: =Daily_Composite!H26 -> 0.021 | X6: =Daily_Composite!H27 -> -0.128 | Y6: =Daily_Composite!H28 -> 0.346 | Z6: =Daily_Composite!H29 -> -0.259 | AA6: =Daily_Composite!H30 -> 0.121 | AB6: =Daily_Composite!H31 -> 0.098 | AC6: =Daily_Composite!H32 -> 0.11 | AD6: =Daily_Composite!H33 -> -0.044 | AE6: =Daily_Composite!H34 -> -0.015 | AF6: =Daily_Composite!H35 -> -0.107 | AG6: =Daily_Composite!H36 -> -0.036 | AH6: =Daily_Composite!H37 -> 0.322 | AI6: =Daily_Composite!H38 -> 0.195 | AJ6: =Daily_Composite!H39 -> -0.054 | AK6: =Daily_Composite!H40 -> 0.226 | AL6: =Daily_Composite!H41 -> -0.134 | AM6: =Daily_Composite!H42 -> -0.488 | AN6: =Daily_Composite!H43 -> -0.297 | AO6: =Daily_Composite!H44 -> -0.376 | AP6: =Daily_Composite!H45 -> -0.315 | AQ6: =Daily_Composite!H46 -> 0.381 | AR6: =Daily_Composite!H47 -> -0.462 | AS6: =Daily_Composite!H48 -> -0.359 | AT6: =Daily_Composite!H49 -> 0.075 | AU6: =Daily_Composite!H50 -> 0.079 | AV6: =Daily_Composite!H51 -> -0.059 | AW6: =Daily_Composite!H52 -> -0.361 | AX6: =Daily_Composite!H53 -> -0.213 | AY6: =Daily_Composite!H54 -> -0.388 | AZ6: =Daily_Composite!H55 -> -0.44 | BA6: =Daily_Composite!H56 -> 0.277 | BB6: =Daily_Composite!H57 -> -0.516 | BC6: =Daily_Composite!H58 -> -0.537 | BD6: =Daily_Composite!H59 -> -0.085 | BE6: =Daily_Composite!H60 -> -0.498 | BF6: =Daily_Composite!H61 -> -0.474 | BG6: =Daily_Composite!H62 -> -0.131 | BH6: =Daily_Composite!H63 -> -0.383 | BI6: =Daily_Composite!H64 -> -0.115 | BJ6: =Daily_Composite!H65 -> -0.567 | BK6: =Daily_Composite!H66 -> -0.369 | BL6: =Daily_Composite!H67 -> -0.24 | BM6: =Daily_Composite!H68 -> -0.205 | BN6: =Daily_Composite!H69 -> -0.397 | BO6: =Daily_Composite!H70 -> -0.575 | BP6: =Daily_Composite!H71 -> -0.371 | BQ6: =Daily_Composite!H72 -> -0.327 | BR6: =Daily_Composite!H73 -> -0.013 | BS6: =Daily_Composite!H74 -> -0.568 | BT6: =Daily_Composite!H75 -> -0.222 | BU6: =Daily_Composite!H76 -> -0.123 | BV6: =Daily_Composite!H77 -> -0.228 | BW6: =Daily_Composite!H78 -> -0.078 | BX6: =Daily_Composite!H79 -> -0.277 | BY6: =Daily_Composite!H80 -> -0.385 | BZ6: =Daily_Composite!H81 -> -0.312 | CA6: =Daily_Composite!H82 -> -0.324 | CB6: =Daily_Composite!H83 -> 0.106 | CC6: =Daily_Composite!H84 -> -0.513 | CD6: =Daily_Composite!H85 -> 0.187 | CE6: =Daily_Composite!H86 -> -0.257 | CF6: =Daily_Composite!H87 -> 0.233 | CG6: =Daily_Composite!H88 -> -0.426 | CH6: =Daily_Composite!H89 -> -0.535 | CI6: =Daily_Composite!H90 -> -0.169 | CJ6: =Daily_Composite!H91 -> -0.141 | CK6: =Daily_Composite!H92 -> -0.512 | CL6: =Daily_Composite!H93 -> -0.626 | CM6: =Daily_Composite!H94 -> -0.514 | CN6: =Daily_Composite!H95 -> -0.602 | CO6: =Daily_Composite!H96 -> -0.685 | CP6: =Daily_Composite!H97 -> -0.764 | CQ6: =Daily_Composite!H98 -> -0.768 | CR6: =Daily_Composite!H99 -> -0.749 | CS6: =Daily_Composite!H100 -> -0.775 | CT6: =Daily_Composite!H101 -> -0.798 | CU6: =Daily_Composite!H102 -> -0.786 | CV6: =Daily_Composite!H103 -> -0.665 | CW6: =Daily_Composite!H104 -> -0.68 | CX6: =Daily_Composite!H105 -> -0.807 | CY6: =Daily_Composite!H106 -> -0.778 | CZ6: =Daily_Composite!H107 -> -0.698 | DA6: =Daily_Composite!H108 -> -0.798 | DB6: =Daily_Composite!H109 -> -0.798 | DC6: =Daily_Composite!H110 -> -0.771 | DD6: =Daily_Composite!H111 -> -0.792 | DE6: =Daily_Composite!H112 -> -0.789 | DF6: =Daily_Composite!H113 -> -0.488 | DG6: =Daily_Composite!H114 -> -0.5 | DH6: =Daily_Composite!H115 -> -0.558 | DI6: =Daily_Composite!H116 -> -0.77 | DJ6: =Daily_Composite!H117 -> -0.688 | DK6: =Daily_Composite!H118 -> -0.624 | DL6: =Daily_Composite!H119 -> -0.757 | DM6: =Daily_Composite!H120 -> -0.653 | DN6: =Daily_Composite!H121 -> -0.544 | DO6: =Daily_Composite!H122 -> -0.339 | DP6: =Daily_Composite!H123 -> -0.328 | DQ6: =Daily_Composite!H124 -> -0.492 | DR6: =Daily_Composite!H125 -> -0.257 | DS6: =Daily_Composite!H126 -> -0.074 | DT6: =Daily_Composite!H127 -> -0.322 | DU6: =Daily_Composite!H128 -> -0.129 | DV6: =Daily_Composite!H129 -> -0.345 | DW6: =Daily_Composite!H130 -> 0.488 | DX6: =Daily_Composite!H131 -> -0.137 | DY6: =Daily_Composite!H132 -> 0.325 | DZ6: =Daily_Composite!H133 -> 0.008 | EA6: =Daily_Composite!H134 -> -0.302 | EB6: =Daily_Composite!H135 -> 0 | EC6: =Daily_Composite!H136 -> -0.174 | ED6: =Daily_Composite!H137 -> -0.478 | EE6: =Daily_Composite!H138 -> -0.438 | EF6: =Daily_Composite!H139 -> -0.018 | EG6: =Daily_Composite!H140 -> -0.342 | EH6: =Daily_Composite!H141 -> -0.342 | EI6: =Daily_Composite!H142 -> -0.334 | EJ6: =Daily_Composite!H143 -> -0.619 | EK6: =Daily_Composite!H144 -> -0.595 | EL6: =Daily_Composite!H145 -> -0.512 | EM6: =Daily_Composite!H146 -> -0.609 | EN6: =Daily_Composite!H147 -> -0.628 | EO6: =Daily_Composite!H148 -> -0.608 | EP6: =Daily_Composite!H149 -> -0.363 | EQ6: =Daily_Composite!H150 -> -0.503 | ER6: =Daily_Composite!H151 -> -0.528 | ES6: =Daily_Composite!H152 -> -0.593 | ET6: =Daily_Composite!H153 -> -0.529 | EU6: =Daily_Composite!H154 -> -0.543 | EV6: =Daily_Composite!H155 -> -0.442 | EW6: =Daily_Composite!H156 -> -0.602 | EX6: =Daily_Composite!H157 -> -0.38 | EY6: =Daily_Composite!H158 -> -0.332 | EZ6: =Daily_Composite!H159 -> -0.286 | FA6: =Daily_Composite!H160 -> -0.404 | FB6: =Daily_Composite!H161 -> -0.43 | FC6: =Daily_Composite!H162 -> -0.579 | FD6: =Daily_Composite!H163 -> -0.616 | FE6: =Daily_Composite!H164 -> -0.627 | FF6: =Daily_Composite!H165 -> 0.149 | FG6: =Daily_Composite!H166 -> -0.646 | FH6: =Daily_Composite!H167 -> -0.447 | FI6: =Daily_Composite!H168 -> -0.35 | FJ6: =Daily_Composite!H169 -> -0.374 | FK6: =Daily_Composite!H170 -> -0.319 | FL6: =Daily_Composite!H171 -> -0.643 | FM6: =Daily_Composite!H172 -> -0.342 | FN6: =Daily_Composite!H173 -> -0.313 | FO6: =Daily_Composite!H174 -> -0.606 | FP6: =Daily_Composite!H175 -> -0.374 | FQ6: =Daily_Composite!H176 -> -0.218 | FR6: =Daily_Composite!H177 -> 0.3 | FS6: =Daily_Composite!H178 -> -0.234 | FT6: =Daily_Composite!H179 -> -0.593 | FU6: =Daily_Composite!H180 -> -0.268 | FV6: =Daily_Composite!H181 -> -0.159 | FW6: =Daily_Composite!H182 -> -0.443 | FX6: =Daily_Composite!H183 -> -0.178 | FY6: =Daily_Composite!H184 -> -0.424 | FZ6: =Daily_Composite!H185 -> -0.071 | GA6: =Daily_Composite!H186 -> 0.233 | GB6: =Daily_Composite!H187 -> 0.178 | GC6: =Daily_Composite!H188 -> -0.288 | GD6: =Daily_Composite!H189 -> -0.116 | GE6: =Daily_Composite!H190 -> -0.157 | GF6: =Daily_Composite!H191 -> -0.147 | GG6: =Daily_Composite!H192 -> -0.453 | GH6: =Daily_Composite!H193 -> -0.146 | GI6: =Daily_Composite!H194 -> -0.051 | GJ6: =Daily_Composite!H195 -> -0.023 | GK6: =Daily_Composite!H196 -> 0.421 | GL6: =Daily_Composite!H197 -> -0.006 | GM6: =Daily_Composite!H198 -> -0.382 | GN6: =Daily_Composite!H199 -> 0.3 | GO6: =Daily_Composite!H200 -> 0.009 | GP6: =Daily_Composite!H201 -> -0.303 | GQ6: =Daily_Composite!H202 -> -0.328 | GR6: =Daily_Composite!H203 -> 0.254 | GS6: =Daily_Composite!H204 -> -0.111 | GT6: =Daily_Composite!H205 -> -0.074 | GU6: =Daily_Composite!H206 -> -0.445 | GV6: =Daily_Composite!H207 -> -0.247 | GW6: =Daily_Composite!H208 -> -0.088 | GX6: =Daily_Composite!H209 -> -0.47 | GY6: =Daily_Composite!H210 -> -0.459 | GZ6: =Daily_Composite!H211 -> -0.375 | HA6: =Daily_Composite!H212 -> -0.007 | HB6: =Daily_Composite!H213 -> -0.4 | HC6: =Daily_Composite!H214 -> -0.645 | HD6: =Daily_Composite!H215 -> -0.438 | HE6: =Daily_Composite!H216 -> -0.262 | HF6: =Daily_Composite!H217 -> -0.485 | HG6: =Daily_Composite!H218 -> -0.542 | HH6: =Daily_Composite!H219 -> -0.592 | HI6: =Daily_Composite!H220 -> -0.554 | HJ6: =Daily_Composite!H221 -> -0.569 | HK6: =Daily_Composite!H222 -> -0.499 | HL6: =Daily_Composite!H223 -> -0.579 | HM6: =Daily_Composite!H224 -> -0.283 | HN6: =Daily_Composite!H225 -> -0.617 | HO6: =Daily_Composite!H226 -> -0.533 | HP6: =Daily_Composite!H227 -> -0.416 | HQ6: =Daily_Composite!H228 -> -0.596 | HR6: =Daily_Composite!H229 -> -0.16 | HS6: =Daily_Composite!H230 -> 0.124 | HT6: =Daily_Composite!H231 -> -0.295 | HU6: =Daily_Composite!H232 -> -0.395 | HV6: =Daily_Composite!H233 -> -0.26 | HW6: =Daily_Composite!H234 -> -0.419 | HX6: =Daily_Composite!H235 -> -0.384 | HY6: =Daily_Composite!H236 -> -0.252 | HZ6: =Daily_Composite!H237 -> -0.257 | IA6: =Daily_Composite!H238 -> 0.166 | IB6: =Daily_Composite!H239 -> 0.438 | IC6: =Daily_Composite!H240 -> 0.06 | ID6: =Daily_Composite!H241 -> 0.333 | IE6: =Daily_Composite!H242 -> -0.026 | IF6: =Daily_Composite!H243 -> -0.302 | IG6: =Daily_Composite!H244 -> -0.172 | IH6: =Daily_Composite!H245 -> -0.119 | II6: =Daily_Composite!H246 -> 0.019 | IJ6: =Daily_Composite!H247 -> 0.466 | IK6: =Daily_Composite!H248 -> 0.306 | IL6: =Daily_Composite!H249 -> 0.557 | IM6: =Daily_Composite!H250 -> -0.019 | IN6: =Daily_Composite!H251 -> 0.549 | IO6: =Daily_Composite!H252 -> 0.227 | IP6: =Daily_Composite!H253 -> 0.044 | IQ6: =Daily_Composite!H254 -> 0.017 | IR6: =Daily_Composite!H255 -> 0.305 | IS6: =Daily_Composite!H256 -> -0.222 | IT6: =Daily_Composite!H257 -> 0.464 | IU6: =Daily_Composite!H258 -> 0.131 | IV6: =Daily_Composite!H259 -> 0.492 | IW6: =Daily_Composite!H260 -> 0.114 | IX6: =Daily_Composite!H261 -> 0.121 | IY6: =Daily_Composite!H262 -> 0.031 | IZ6: =Daily_Composite!H263 -> -0.125 | JA6: =Daily_Composite!H264 -> -0.111 | JB6: =Daily_Composite!H265 -> -0.104 | JC6: =Daily_Composite!H266 -> 0.391 | JD6: =Daily_Composite!H267 -> -0.05 | JE6: =Daily_Composite!H268 -> 0.243 | JF6: =Daily_Composite!H269 -> -0.129 | JG6: =Daily_Composite!H270 -> -0.237 | JH6: =Daily_Composite!H271 -> -0.48 | JI6: =Daily_Composite!H272 -> -0.177 | JJ6: =Daily_Composite!H273 -> -0.315 | JK6: =Daily_Composite!H274 -> -0.458 | JL6: =Daily_Composite!H275 -> -0.637 | JM6: =Daily_Composite!H276 -> 0.053 | JN6: =Daily_Composite!H277 -> -0.403 | JO6: =Daily_Composite!H278 -> -0.712 | JP6: =Daily_Composite!H279 -> -0.34 | JQ6: =Daily_Composite!H280 -> -0.46 | JR6: =Daily_Composite!H281 -> -0.271 | JS6: =Daily_Composite!H282 -> 0.114 | JT6: =Daily_Composite!H283 -> 0.108 | JU6: =Daily_Composite!H284 -> -0.377 | JV6: =Daily_Composite!H285 -> 0.331 | JW6: =Daily_Composite!H286 -> 0.243 | JX6: =Daily_Composite!H287 -> -0.038 | JY6: =Daily_Composite!H288 -> 0.143 | JZ6: =Daily_Composite!H289 -> 0.039 | KA6: =Daily_Composite!H290 -> -0.024 | KB6: =Daily_Composite!H291 -> -0.007 | KC6: =Daily_Composite!H292 -> -0.307 | KD6: =Daily_Composite!H293 -> 0.331 | KE6: =Daily_Composite!H294 -> -0.241 | KF6: =Daily_Composite!H295 -> -0.016 | KG6: =Daily_Composite!H296 -> -0.026 | KH6: =Daily_Composite!H297 -> -0.464 | KI6: =Daily_Composite!H298 -> -0.311 | KJ6: =Daily_Composite!H299 -> -0.267 | KK6: =Daily_Composite!H300 -> -0.455 | KL6: =Daily_Composite!H301 -> -0.441 | KM6: =Daily_Composite!H302 -> -0.265 | KN6: =Daily_Composite!H303 -> 0.322 | KO6: =Daily_Composite!H304 -> -0.371 | KP6: =Daily_Composite!H305 -> -0.355 | KQ6: =Daily_Composite!H306 -> -0.051 | KR6: =Daily_Composite!H307 -> -0.35 | KS6: =Daily_Composite!H308 -> -0.424 | KT6: =Daily_Composite!H309 -> -0.354 | KU6: =Daily_Composite!H310 -> -0.561 | KV6: =Daily_Composite!H311 -> -0.608 | KW6: =Daily_Composite!H312 -> -0.132 | KX6: =Daily_Composite!H313 -> -0.138 | KY6: =Daily_Composite!H314 -> -0.595 | KZ6: =Daily_Composite!H315 -> -0.357 | LA6: =Daily_Composite!H316 -> -0.487 | LB6: =Daily_Composite!H317 -> -0.435 | LC6: =Daily_Composite!H318 -> -0.407 | LD6: =Daily_Composite!H319 -> -0.055 | LE6: =Daily_Composite!H320 -> -0.361 | LF6: =Daily_Composite!H321 -> 0.208 | LG6: =Daily_Composite!H322 -> 0.257 | LH6: =Daily_Composite!H323 -> 0.598 | LI6: =Daily_Composite!H324 -> 0.006 | LJ6: =Daily_Composite!H325 -> -0.203 | LK6: =Daily_Composite!H326 -> 0.096 | LL6: =Daily_Composite!H327 -> 0.282 | LM6: =Daily_Composite!H328 -> 0.55 | LN6: =Daily_Composite!H329 -> 0.237 | LO6: =Daily_Composite!H330 -> -0.38 | LP6: =Daily_Composite!H331 -> 0.153 | LQ6: =Daily_Composite!H332 -> 0.019 | LR6: =Daily_Composite!H333 -> 0.164 | LS6: =Daily_Composite!H334 -> -0.113 | LT6: =Daily_Composite!H335 -> -0.415 | LU6: =Daily_Composite!H336 -> -0.144 | LV6: =Daily_Composite!H337 -> -0.147 | LW6: =Daily_Composite!H338 -> -0.17 | LX6: =Daily_Composite!H339 -> -0.174 | LY6: =Daily_Composite!H340 -> -0.016 | LZ6: =Daily_Composite!H341 -> -0.13 | MA6: =Daily_Composite!H342 -> -0.176 | MB6: =Daily_Composite!H343 -> -0.315 | MC6: =Daily_Composite!H344 -> -0.079 | MD6: =Daily_Composite!H345 -> -0.069 | ME6: =Daily_Composite!H346 -> -0.025 | MF6: =Daily_Composite!H347 -> 0.654 | MG6: =Daily_Composite!H348 -> 0.662 | MH6: =Daily_Composite!H349 -> 0.479 | MI6: =Daily_Composite!H350 -> 0.727 | MJ6: =Daily_Composite!H351 -> 0.683 | MK6: =Daily_Composite!H352 -> 0.47 | ML6: =Daily_Composite!H353 -> 0.574 | MM6: =Daily_Composite!H354 -> 0.687 | MN6: =Daily_Composite!H355 -> 0.596 | MO6: =Daily_Composite!H356 -> 0.71 | MP6: =Daily_Composite!H357 -> 0.69 | MQ6: =Daily_Composite!H358 -> 0.664 | MR6: =Daily_Composite!H359 -> 0.194 | MS6: =Daily_Composite!H360 -> 0.57 | MT6: =Daily_Composite!H361 -> 0.375 | MU6: =Daily_Composite!H362 -> 0.4 | MV6: =Daily_Composite!H363 -> 0.077 | MW6: =Daily_Composite!H364 -> 0.065 | MX6: =Daily_Composite!H365 -> 0.118 | MY6: =Daily_Composite!H366 -> 0.549 | MZ6: =Daily_Composite!H367 -> 0.476 | NA6: =Daily_Composite!H368 -> 0.142 | NB6: =Daily_Composite!H369 -> 0.132
A7: Automobile | B7: =Daily_Composite!I5 -> 0.011 | C7: =Daily_Composite!I6 -> -0.099 | D7: =Daily_Composite!I7 -> 0.084 | E7: =Daily_Composite!I8 -> 0.01 | F7: =Daily_Composite!I9 -> -0.026 | G7: =Daily_Composite!I10 -> -0.134 | H7: =Daily_Composite!I11 -> -0.126 | I7: =Daily_Composite!I12 -> -0.468 | J7: =Daily_Composite!I13 -> -0.089 | K7: =Daily_Composite!I14 -> -0.086 | L7: =Daily_Composite!I15 -> -0.084 | M7: =Daily_Composite!I16 -> -0.214 | N7: =Daily_Composite!I17 -> -0.081 | O7: =Daily_Composite!I18 -> -0.081 | P7: =Daily_Composite!I19 -> -0.213 | Q7: =Daily_Composite!I20 -> -0.207 | R7: =Daily_Composite!I21 -> 0.15 | S7: =Daily_Composite!I22 -> -0.424 | T7: =Daily_Composite!I23 -> 0.002 | U7: =Daily_Composite!I24 -> 0.002 | V7: =Daily_Composite!I25 -> 0.002 | W7: =Daily_Composite!I26 -> -0.227 | X7: =Daily_Composite!I27 -> 0.058 | Y7: =Daily_Composite!I28 -> 0.045 | Z7: =Daily_Composite!I29 -> 0.053 | AA7: =Daily_Composite!I30 -> 0.085 | AB7: =Daily_Composite!I31 -> -0.294 | AC7: =Daily_Composite!I32 -> -0.127 | AD7: =Daily_Composite!I33 -> 0.119 | AE7: =Daily_Composite!I34 -> 0.151 | AF7: =Daily_Composite!I35 -> 0.623 | AG7: =Daily_Composite!I36 -> 0.252 | AH7: =Daily_Composite!I37 -> 0.214 | AI7: =Daily_Composite!I38 -> 0.226 | AJ7: =Daily_Composite!I39 -> 0.48 | AK7: =Daily_Composite!I40 -> 0.209 | AL7: =Daily_Composite!I41 -> 0.179 | AM7: =Daily_Composite!I42 -> 0.118 | AN7: =Daily_Composite!I43 -> 0.445 | AO7: =Daily_Composite!I44 -> 0.107 | AP7: =Daily_Composite!I45 -> 0.116 | AQ7: =Daily_Composite!I46 -> 0.217 | AR7: =Daily_Composite!I47 -> 0.198 | AS7: =Daily_Composite!I48 -> 0.135 | AT7: =Daily_Composite!I49 -> -0.289 | AU7: =Daily_Composite!I50 -> 0.119 | AV7: =Daily_Composite!I51 -> 0.115 | AW7: =Daily_Composite!I52 -> 0.122 | AX7: =Daily_Composite!I53 -> 0.293 | AY7: =Daily_Composite!I54 -> 0.204 | AZ7: =Daily_Composite!I55 -> 0.113 | BA7: =Daily_Composite!I56 -> 0.128 | BB7: =Daily_Composite!I57 -> 0.178 | BC7: =Daily_Composite!I58 -> 0.205 | BD7: =Daily_Composite!I59 -> 0.54 | BE7: =Daily_Composite!I60 -> 0.289 | BF7: =Daily_Composite!I61 -> 0.148 | BG7: =Daily_Composite!I62 -> 0.608 | BH7: =Daily_Composite!I63 -> 0.08 | BI7: =Daily_Composite!I64 -> 0.085 | BJ7: =Daily_Composite!I65 -> 0.101 | BK7: =Daily_Composite!I66 -> 0.053 | BL7: =Daily_Composite!I67 -> 0.334 | BM7: =Daily_Composite!I68 -> 0.038 | BN7: =Daily_Composite!I69 -> 0.073 | BO7: =Daily_Composite!I70 -> 0.031 | BP7: =Daily_Composite!I71 -> 0.254 | BQ7: =Daily_Composite!I72 -> -0.019 | BR7: =Daily_Composite!I73 -> -0.016 | BS7: =Daily_Composite!I74 -> 0.164 | BT7: =Daily_Composite!I75 -> 0.136 | BU7: =Daily_Composite!I76 -> -0.13 | BV7: =Daily_Composite!I77 -> -0.08 | BW7: =Daily_Composite!I78 -> -0.061 | BX7: =Daily_Composite!I79 -> -0.07 | BY7: =Daily_Composite!I80 -> -0.07 | BZ7: =Daily_Composite!I81 -> 0.437 | CA7: =Daily_Composite!I82 -> -0.075 | CB7: =Daily_Composite!I83 -> 0.002 | CC7: =Daily_Composite!I84 -> -0.038 | CD7: =Daily_Composite!I85 -> -0.013 | CE7: =Daily_Composite!I86 -> 0.348 | CF7: =Daily_Composite!I87 -> 0.364 | CG7: =Daily_Composite!I88 -> -0.008 | CH7: =Daily_Composite!I89 -> 0.006 | CI7: =Daily_Composite!I90 -> 0.38 | CJ7: =Daily_Composite!I91 -> 0.007 | CK7: =Daily_Composite!I92 -> 0.04 | CL7: =Daily_Composite!I93 -> 0.048 | CM7: =Daily_Composite!I94 -> 0.5 | CN7: =Daily_Composite!I95 -> 0.055 | CO7: =Daily_Composite!I96 -> 0.023 | CP7: =Daily_Composite!I97 -> 0.027 | CQ7: =Daily_Composite!I98 -> -0.407 | CR7: =Daily_Composite!I99 -> 0.004 | CS7: =Daily_Composite!I100 -> 0.007 | CT7: =Daily_Composite!I101 -> -0.08 | CU7: =Daily_Composite!I102 -> -0.165 | CV7: =Daily_Composite!I103 -> -0.49 | CW7: =Daily_Composite!I104 -> -0.522 | CX7: =Daily_Composite!I105 -> -0.105 | CY7: =Daily_Composite!I106 -> -0.177 | CZ7: =Daily_Composite!I107 -> -0.221 | DA7: =Daily_Composite!I108 -> -0.396 | DB7: =Daily_Composite!I109 -> -0.14 | DC7: =Daily_Composite!I110 -> -0.117 | DD7: =Daily_Composite!I111 -> -0.115 | DE7: =Daily_Composite!I112 -> -0.056 | DF7: =Daily_Composite!I113 -> -0.504 | DG7: =Daily_Composite!I114 -> -0.13 | DH7: =Daily_Composite!I115 -> 0.019 | DI7: =Daily_Composite!I116 -> -0.102 | DJ7: =Daily_Composite!I117 -> -0.253 | DK7: =Daily_Composite!I118 -> 0.046 | DL7: =Daily_Composite!I119 -> 0.06 | DM7: =Daily_Composite!I120 -> 0.071 | DN7: =Daily_Composite!I121 -> 0.082 | DO7: =Daily_Composite!I122 -> 0.02 | DP7: =Daily_Composite!I123 -> 0.107 | DQ7: =Daily_Composite!I124 -> -0.005 | DR7: =Daily_Composite!I125 -> 0.458 | DS7: =Daily_Composite!I126 -> 0.098 | DT7: =Daily_Composite!I127 -> 0.115 | DU7: =Daily_Composite!I128 -> 0.427 | DV7: =Daily_Composite!I129 -> 0.406 | DW7: =Daily_Composite!I130 -> 0.43 | DX7: =Daily_Composite!I131 -> 0.514 | DY7: =Daily_Composite!I132 -> -0.072 | DZ7: =Daily_Composite!I133 -> -0.017 | EA7: =Daily_Composite!I134 -> -0.006 | EB7: =Daily_Composite!I135 -> 0.4 | EC7: =Daily_Composite!I136 -> 0.015 | ED7: =Daily_Composite!I137 -> 0.015 | EE7: =Daily_Composite!I138 -> -0.009 | EF7: =Daily_Composite!I139 -> -0.003 | EG7: =Daily_Composite!I140 -> 0.508 | EH7: =Daily_Composite!I141 -> 0.187 | EI7: =Daily_Composite!I142 -> 0.191 | EJ7: =Daily_Composite!I143 -> 0.036 | EK7: =Daily_Composite!I144 -> -0.299 | EL7: =Daily_Composite!I145 -> 0.045 | EM7: =Daily_Composite!I146 -> 0.038 | EN7: =Daily_Composite!I147 -> 0.041 | EO7: =Daily_Composite!I148 -> 0.053 | EP7: =Daily_Composite!I149 -> 0.285 | EQ7: =Daily_Composite!I150 -> 0.086 | ER7: =Daily_Composite!I151 -> 0.015 | ES7: =Daily_Composite!I152 -> 0.015 | ET7: =Daily_Composite!I153 -> -0.394 | EU7: =Daily_Composite!I154 -> -0.074 | EV7: =Daily_Composite!I155 -> -0.078 | EW7: =Daily_Composite!I156 -> 0.134 | EX7: =Daily_Composite!I157 -> 0.077 | EY7: =Daily_Composite!I158 -> -0.392 | EZ7: =Daily_Composite!I159 -> -0.085 | FA7: =Daily_Composite!I160 -> -0.066 | FB7: =Daily_Composite!I161 -> -0.037 | FC7: =Daily_Composite!I162 -> 0.258 | FD7: =Daily_Composite!I163 -> -0.29 | FE7: =Daily_Composite!I164 -> -0.061 | FF7: =Daily_Composite!I165 -> -0.06 | FG7: =Daily_Composite!I166 -> -0.057 | FH7: =Daily_Composite!I167 -> -0.028 | FI7: =Daily_Composite!I168 -> -0.386 | FJ7: =Daily_Composite!I169 -> -0.167 | FK7: =Daily_Composite!I170 -> -0.021 | FL7: =Daily_Composite!I171 -> -0.017 | FM7: =Daily_Composite!I172 -> -0.087 | FN7: =Daily_Composite!I173 -> -0.007 | FO7: =Daily_Composite!I174 -> 0.014 | FP7: =Daily_Composite!I175 -> 0.035 | FQ7: =Daily_Composite!I176 -> -0.142 | FR7: =Daily_Composite!I177 -> -0.109 | FS7: =Daily_Composite!I178 -> -0.134 | FT7: =Daily_Composite!I179 -> -0.138 | FU7: =Daily_Composite!I180 -> -0.525 | FV7: =Daily_Composite!I181 -> -0.255 | FW7: =Daily_Composite!I182 -> -0.293 | FX7: =Daily_Composite!I183 -> -0.449 | FY7: =Daily_Composite!I184 -> -0.425 | FZ7: =Daily_Composite!I185 -> -0.559 | GA7: =Daily_Composite!I186 -> -0.295 | GB7: =Daily_Composite!I187 -> -0.33 | GC7: =Daily_Composite!I188 -> -0.278 | GD7: =Daily_Composite!I189 -> -0.175 | GE7: =Daily_Composite!I190 -> 0.217 | GF7: =Daily_Composite!I191 -> -0.062 | GG7: =Daily_Composite!I192 -> -0.076 | GH7: =Daily_Composite!I193 -> -0.141 | GI7: =Daily_Composite!I194 -> -0.154 | GJ7: =Daily_Composite!I195 -> 0.255 | GK7: =Daily_Composite!I196 -> -0.168 | GL7: =Daily_Composite!I197 -> -0.185 | GM7: =Daily_Composite!I198 -> -0.215 | GN7: =Daily_Composite!I199 -> -0.454 | GO7: =Daily_Composite!I200 -> -0.224 | GP7: =Daily_Composite!I201 -> -0.201 | GQ7: =Daily_Composite!I202 -> -0.177 | GR7: =Daily_Composite!I203 -> -0.153 | GS7: =Daily_Composite!I204 -> -0.209 | GT7: =Daily_Composite!I205 -> -0.01 | GU7: =Daily_Composite!I206 -> -0.088 | GV7: =Daily_Composite!I207 -> -0.165 | GW7: =Daily_Composite!I208 -> -0.089 | GX7: =Daily_Composite!I209 -> -0.091 | GY7: =Daily_Composite!I210 -> -0.069 | GZ7: =Daily_Composite!I211 -> -0.205 | HA7: =Daily_Composite!I212 -> -0.233 | HB7: =Daily_Composite!I213 -> -0.461 | HC7: =Daily_Composite!I214 -> -0.097 | HD7: =Daily_Composite!I215 -> -0.102 | HE7: =Daily_Composite!I216 -> -0.107 | HF7: =Daily_Composite!I217 -> -0.365 | HG7: =Daily_Composite!I218 -> -0.03 | HH7: =Daily_Composite!I219 -> -0.066 | HI7: =Daily_Composite!I220 -> -0.142 | HJ7: =Daily_Composite!I221 -> -0.142 | HK7: =Daily_Composite!I222 -> -0.151 | HL7: =Daily_Composite!I223 -> -0.069 | HM7: =Daily_Composite!I224 -> -0.495 | HN7: =Daily_Composite!I225 -> -0.189 | HO7: =Daily_Composite!I226 -> -0.339 | HP7: =Daily_Composite!I227 -> -0.207 | HQ7: =Daily_Composite!I228 -> -0.207 | HR7: =Daily_Composite!I229 -> -0.23 | HS7: =Daily_Composite!I230 -> -0.254 | HT7: =Daily_Composite!I231 -> -0.501 | HU7: =Daily_Composite!I232 -> -0.139 | HV7: =Daily_Composite!I233 -> -0.297 | HW7: =Daily_Composite!I234 -> -0.281 | HX7: =Daily_Composite!I235 -> -0.405 | HY7: =Daily_Composite!I236 -> -0.276 | HZ7: =Daily_Composite!I237 -> -0.275 | IA7: =Daily_Composite!I238 -> -0.432 | IB7: =Daily_Composite!I239 -> -0.41 | IC7: =Daily_Composite!I240 -> -0.622 | ID7: =Daily_Composite!I241 -> -0.151 | IE7: =Daily_Composite!I242 -> -0.164 | IF7: =Daily_Composite!I243 -> -0.219 | IG7: =Daily_Composite!I244 -> -0.449 | IH7: =Daily_Composite!I245 -> 0.161 | II7: =Daily_Composite!I246 -> -0.084 | IJ7: =Daily_Composite!I247 -> -0.084 | IK7: =Daily_Composite!I248 -> -0.125 | IL7: =Daily_Composite!I249 -> -0.129 | IM7: =Daily_Composite!I250 -> 0.083 | IN7: =Daily_Composite!I251 -> 0.197 | IO7: =Daily_Composite!I252 -> -0.069 | IP7: =Daily_Composite!I253 -> -0.133 | IQ7: =Daily_Composite!I254 -> 0.137 | IR7: =Daily_Composite!I255 -> -0.135 | IS7: =Daily_Composite!I256 -> -0.23 | IT7: =Daily_Composite!I257 -> -0.233 | IU7: =Daily_Composite!I258 -> -0.317 | IV7: =Daily_Composite!I259 -> -0.232 | IW7: =Daily_Composite!I260 -> -0.091 | IX7: =Daily_Composite!I261 -> -0.124 | IY7: =Daily_Composite!I262 -> -0.525 | IZ7: =Daily_Composite!I263 -> -0.221 | JA7: =Daily_Composite!I264 -> -0.222 | JB7: =Daily_Composite!I265 -> -0.287 | JC7: =Daily_Composite!I266 -> -0.48 | JD7: =Daily_Composite!I267 -> -0.324 | JE7: =Daily_Composite!I268 -> -0.213 | JF7: =Daily_Composite!I269 -> -0.23 | JG7: =Daily_Composite!I270 -> -0.126 | JH7: =Daily_Composite!I271 -> -0.229 | JI7: =Daily_Composite!I272 -> -0.581 | JJ7: =Daily_Composite!I273 -> -0.228 | JK7: =Daily_Composite!I274 -> -0.227 | JL7: =Daily_Composite!I275 -> -0.096 | JM7: =Daily_Composite!I276 -> -0.1 | JN7: =Daily_Composite!I277 -> -0.135 | JO7: =Daily_Composite!I278 -> -0.09 | JP7: =Daily_Composite!I279 -> -0.215 | JQ7: =Daily_Composite!I280 -> -0.11 | JR7: =Daily_Composite!I281 -> -0.559 | JS7: =Daily_Composite!I282 -> -0.186 | JT7: =Daily_Composite!I283 -> -0.208 | JU7: =Daily_Composite!I284 -> -0.208 | JV7: =Daily_Composite!I285 -> -0.209 | JW7: =Daily_Composite!I286 -> -0.21 | JX7: =Daily_Composite!I287 -> -0.21 | JY7: =Daily_Composite!I288 -> -0.085 | JZ7: =Daily_Composite!I289 -> 0.085 | KA7: =Daily_Composite!I290 -> -0.211 | KB7: =Daily_Composite!I291 -> -0.211 | KC7: =Daily_Composite!I292 -> -0.288 | KD7: =Daily_Composite!I293 -> -0.355 | KE7: =Daily_Composite!I294 -> 0.179 | KF7: =Daily_Composite!I295 -> 0.19 | KG7: =Daily_Composite!I296 -> -0.225 | KH7: =Daily_Composite!I297 -> -0.245 | KI7: =Daily_Composite!I298 -> -0.226 | KJ7: =Daily_Composite!I299 -> -0.487 | KK7: =Daily_Composite!I300 -> -0.27 | KL7: =Daily_Composite!I301 -> -0.275 | KM7: =Daily_Composite!I302 -> -0.255 | KN7: =Daily_Composite!I303 -> -0.258 | KO7: =Daily_Composite!I304 -> -0.24 | KP7: =Daily_Composite!I305 -> -0.36 | KQ7: =Daily_Composite!I306 -> -0.197 | KR7: =Daily_Composite!I307 -> -0.287 | KS7: =Daily_Composite!I308 -> -0.513 | KT7: =Daily_Composite!I309 -> -0.162 | KU7: =Daily_Composite!I310 -> -0.195 | KV7: =Daily_Composite!I311 -> -0.225 | KW7: =Daily_Composite!I312 -> -0.224 | KX7: =Daily_Composite!I313 -> -0.346 | KY7: =Daily_Composite!I314 -> -0.198 | KZ7: =Daily_Composite!I315 -> -0.194 | LA7: =Daily_Composite!I316 -> -0.189 | LB7: =Daily_Composite!I317 -> -0.025 | LC7: =Daily_Composite!I318 -> -0.064 | LD7: =Daily_Composite!I319 -> -0.41 | LE7: =Daily_Composite!I320 -> -0.476 | LF7: =Daily_Composite!I321 -> -0.428 | LG7: =Daily_Composite!I322 -> -0.294 | LH7: =Daily_Composite!I323 -> -0.124 | LI7: =Daily_Composite!I324 -> -0.138 | LJ7: =Daily_Composite!I325 -> -0.163 | LK7: =Daily_Composite!I326 -> -0.583 | LL7: =Daily_Composite!I327 -> -0.137 | LM7: =Daily_Composite!I328 -> -0.133 | LN7: =Daily_Composite!I329 -> -0.15 | LO7: =Daily_Composite!I330 -> -0.146 | LP7: =Daily_Composite!I331 -> -0.119 | LQ7: =Daily_Composite!I332 -> 0.141 | LR7: =Daily_Composite!I333 -> 0.145 | LS7: =Daily_Composite!I334 -> -0.136 | LT7: =Daily_Composite!I335 -> -0.152 | LU7: =Daily_Composite!I336 -> -0.565 | LV7: =Daily_Composite!I337 -> -0.125 | LW7: =Daily_Composite!I338 -> -0.103 | LX7: =Daily_Composite!I339 -> -0.139 | LY7: =Daily_Composite!I340 -> -0.331 | LZ7: =Daily_Composite!I341 -> -0.135 | MA7: =Daily_Composite!I342 -> -0.13 | MB7: =Daily_Composite!I343 -> -0.126 | MC7: =Daily_Composite!I344 -> -0.537 | MD7: =Daily_Composite!I345 -> -0.067 | ME7: =Daily_Composite!I346 -> -0.073 | MF7: =Daily_Composite!I347 -> -0.409 | MG7: =Daily_Composite!I348 -> -0.388 | MH7: =Daily_Composite!I349 -> -0.261 | MI7: =Daily_Composite!I350 -> -0.044 | MJ7: =Daily_Composite!I351 -> 0.014 | MK7: =Daily_Composite!I352 -> -0.013 | ML7: =Daily_Composite!I353 -> -0.013 | MM7: =Daily_Composite!I354 -> -0.013 | MN7: =Daily_Composite!I355 -> -0.146 | MO7: =Daily_Composite!I356 -> -0.118 | MP7: =Daily_Composite!I357 -> -0.04 | MQ7: =Daily_Composite!I358 -> -0.018 | MR7: =Daily_Composite!I359 -> -0.164 | MS7: =Daily_Composite!I360 -> -0.128 | MT7: =Daily_Composite!I361 -> -0.098 | MU7: =Daily_Composite!I362 -> -0.139 | MV7: =Daily_Composite!I363 -> -0.131 | MW7: =Daily_Composite!I364 -> -0.13 | MX7: =Daily_Composite!I365 -> -0.156 | MY7: =Daily_Composite!I366 -> -0.237 | MZ7: =Daily_Composite!I367 -> -0.235 | NA7: =Daily_Composite!I368 -> -0.183 | NB7: =Daily_Composite!I369 -> -0.21
A8: Aviation | B8: =Daily_Composite!J5 -> 0.062 | C8: =Daily_Composite!J6 -> 0.099 | D8: =Daily_Composite!J7 -> 0.097 | E8: =Daily_Composite!J8 -> 0.23 | F8: =Daily_Composite!J9 -> 0.179 | G8: =Daily_Composite!J10 -> -0.083 | H8: =Daily_Composite!J11 -> 0.391 | I8: =Daily_Composite!J12 -> 0.115 | J8: =Daily_Composite!J13 -> 0.134 | K8: =Daily_Composite!J14 -> 0.404 | L8: =Daily_Composite!J15 -> 0.236 | M8: =Daily_Composite!J16 -> 0.31 | N8: =Daily_Composite!J17 -> 0.113 | O8: =Daily_Composite!J18 -> 0.101 | P8: =Daily_Composite!J19 -> 0.131 | Q8: =Daily_Composite!J20 -> 0.176 | R8: =Daily_Composite!J21 -> 0.288 | S8: =Daily_Composite!J22 -> 0.133 | T8: =Daily_Composite!J23 -> -0.102 | U8: =Daily_Composite!J24 -> -0.113 | V8: =Daily_Composite!J25 -> -0.102 | W8: =Daily_Composite!J26 -> -0.138 | X8: =Daily_Composite!J27 -> -0.352 | Y8: =Daily_Composite!J28 -> -0.295 | Z8: =Daily_Composite!J29 -> -0.176 | AA8: =Daily_Composite!J30 -> 0.146 | AB8: =Daily_Composite!J31 -> -0.201 | AC8: =Daily_Composite!J32 -> -0.195 | AD8: =Daily_Composite!J33 -> -0.16 | AE8: =Daily_Composite!J34 -> -0.161 | AF8: =Daily_Composite!J35 -> 0.093 | AG8: =Daily_Composite!J36 -> 0.092 | AH8: =Daily_Composite!J37 -> 0.095 | AI8: =Daily_Composite!J38 -> 0.394 | AJ8: =Daily_Composite!J39 -> 0.108 | AK8: =Daily_Composite!J40 -> 0.139 | AL8: =Daily_Composite!J41 -> 0.168 | AM8: =Daily_Composite!J42 -> 0.128 | AN8: =Daily_Composite!J43 -> 0.246 | AO8: =Daily_Composite!J44 -> 0.199 | AP8: =Daily_Composite!J45 -> 0.198 | AQ8: =Daily_Composite!J46 -> 0.184 | AR8: =Daily_Composite!J47 -> 0.187 | AS8: =Daily_Composite!J48 -> -0.047 | AT8: =Daily_Composite!J49 -> 0.182 | AU8: =Daily_Composite!J50 -> 0.155 | AV8: =Daily_Composite!J51 -> 0.147 | AW8: =Daily_Composite!J52 -> 0.148 | AX8: =Daily_Composite!J53 -> 0.151 | AY8: =Daily_Composite!J54 -> 0.037 | AZ8: =Daily_Composite!J55 -> -0.218 | BA8: =Daily_Composite!J56 -> -0.056 | BB8: =Daily_Composite!J57 -> -0.042 | BC8: =Daily_Composite!J58 -> -0.395 | BD8: =Daily_Composite!J59 -> -0.076 | BE8: =Daily_Composite!J60 -> -0.079 | BF8: =Daily_Composite!J61 -> -0.017 | BG8: =Daily_Composite!J62 -> -0.015 | BH8: =Daily_Composite!J63 -> 0.043 | BI8: =Daily_Composite!J64 -> 0.086 | BJ8: =Daily_Composite!J65 -> 0.036 | BK8: =Daily_Composite!J66 -> 0.323 | BL8: =Daily_Composite!J67 -> -0.055 | BM8: =Daily_Composite!J68 -> -0.028 | BN8: =Daily_Composite!J69 -> 0.018 | BO8: =Daily_Composite!J70 -> 0.112 | BP8: =Daily_Composite!J71 -> -0.034 | BQ8: =Daily_Composite!J72 -> -0.02 | BR8: =Daily_Composite!J73 -> -0.018 | BS8: =Daily_Composite!J74 -> 0.032 | BT8: =Daily_Composite!J75 -> 0.416 | BU8: =Daily_Composite!J76 -> -0.015 | BV8: =Daily_Composite!J77 -> -0.018 | BW8: =Daily_Composite!J78 -> -0.019 | BX8: =Daily_Composite!J79 -> 0.022 | BY8: =Daily_Composite!J80 -> -0.057 | BZ8: =Daily_Composite!J81 -> 0.208 | CA8: =Daily_Composite!J82 -> 0.232 | CB8: =Daily_Composite!J83 -> 0.25 | CC8: =Daily_Composite!J84 -> 0.073 | CD8: =Daily_Composite!J85 -> 0.546 | CE8: =Daily_Composite!J86 -> 0.126 | CF8: =Daily_Composite!J87 -> 0.133 | CG8: =Daily_Composite!J88 -> 0.095 | CH8: =Daily_Composite!J89 -> 0.087 | CI8: =Daily_Composite!J90 -> 0.448 | CJ8: =Daily_Composite!J91 -> 0.476 | CK8: =Daily_Composite!J92 -> 0.065 | CL8: =Daily_Composite!J93 -> 0.229 | CM8: =Daily_Composite!J94 -> -0.019 | CN8: =Daily_Composite!J95 -> -0.108 | CO8: =Daily_Composite!J96 -> 0.121 | CP8: =Daily_Composite!J97 -> 0.155 | CQ8: =Daily_Composite!J98 -> -0.246 | CR8: =Daily_Composite!J99 -> -0.25 | CS8: =Daily_Composite!J100 -> -0.273 | CT8: =Daily_Composite!J101 -> -0.219 | CU8: =Daily_Composite!J102 -> -0.5 | CV8: =Daily_Composite!J103 -> -0.23 | CW8: =Daily_Composite!J104 -> -0.235 | CX8: =Daily_Composite!J105 -> -0.239 | CY8: =Daily_Composite!J106 -> -0.218 | CZ8: =Daily_Composite!J107 -> -0.243 | DA8: =Daily_Composite!J108 -> -0.454 | DB8: =Daily_Composite!J109 -> -0.462 | DC8: =Daily_Composite!J110 -> -0.461 | DD8: =Daily_Composite!J111 -> -0.076 | DE8: =Daily_Composite!J112 -> -0.505 | DF8: =Daily_Composite!J113 -> -0.085 | DG8: =Daily_Composite!J114 -> -0.095 | DH8: =Daily_Composite!J115 -> -0.093 | DI8: =Daily_Composite!J116 -> -0.214 | DJ8: =Daily_Composite!J117 -> -0.202 | DK8: =Daily_Composite!J118 -> -0.214 | DL8: =Daily_Composite!J119 -> -0.009 | DM8: =Daily_Composite!J120 -> 0.006 | DN8: =Daily_Composite!J121 -> -0.302 | DO8: =Daily_Composite!J122 -> 0.038 | DP8: =Daily_Composite!J123 -> 0.041 | DQ8: =Daily_Composite!J124 -> -0.03 | DR8: =Daily_Composite!J125 -> 0.288 | DS8: =Daily_Composite!J126 -> 0.243 | DT8: =Daily_Composite!J127 -> 0.267 | DU8: =Daily_Composite!J128 -> 0.137 | DV8: =Daily_Composite!J129 -> 0.056 | DW8: =Daily_Composite!J130 -> 0.676 | DX8: =Daily_Composite!J131 -> 0.288 | DY8: =Daily_Composite!J132 -> 0.119 | DZ8: =Daily_Composite!J133 -> 0.186 | EA8: =Daily_Composite!J134 -> 0.148 | EB8: =Daily_Composite!J135 -> 0.07 | EC8: =Daily_Composite!J136 -> 0.235 | ED8: =Daily_Composite!J137 -> 0.184 | EE8: =Daily_Composite!J138 -> 0.079 | EF8: =Daily_Composite!J139 -> 0.412 | EG8: =Daily_Composite!J140 -> -0.001 | EH8: =Daily_Composite!J141 -> 0.002 | EI8: =Daily_Composite!J142 -> 0.033 | EJ8: =Daily_Composite!J143 -> 0.031 | EK8: =Daily_Composite!J144 -> -0.008 | EL8: =Daily_Composite!J145 -> 0.018 | EM8: =Daily_Composite!J146 -> 0.019 | EN8: =Daily_Composite!J147 -> 0.075 | EO8: =Daily_Composite!J148 -> -0.155 | EP8: =Daily_Composite!J149 -> 0.093 | EQ8: =Daily_Composite!J150 -> 0.119 | ER8: =Daily_Composite!J151 -> -0.012 | ES8: =Daily_Composite!J152 -> 0.094 | ET8: =Daily_Composite!J153 -> 0.142 | EU8: =Daily_Composite!J154 -> 0.11 | EV8: =Daily_Composite!J155 -> 0.143 | EW8: =Daily_Composite!J156 -> 0.151 | EX8: =Daily_Composite!J157 -> 0.256 | EY8: =Daily_Composite!J158 -> 0.242 | EZ8: =Daily_Composite!J159 -> 0.247 | FA8: =Daily_Composite!J160 -> 0.266 | FB8: =Daily_Composite!J161 -> 0.032 | FC8: =Daily_Composite!J162 -> 0.151 | FD8: =Daily_Composite!J163 -> 0.04 | FE8: =Daily_Composite!J164 -> -0.012 | FF8: =Daily_Composite!J165 -> 0.311 | FG8: =Daily_Composite!J166 -> 0.32 | FH8: =Daily_Composite!J167 -> 0.532 | FI8: =Daily_Composite!J168 -> 0.35 | FJ8: =Daily_Composite!J169 -> 0.31 | FK8: =Daily_Composite!J170 -> 0.13 | FL8: =Daily_Composite!J171 -> 0.13 | FM8: =Daily_Composite!J172 -> 0.544 | FN8: =Daily_Composite!J173 -> 0.49 | FO8: =Daily_Composite!J174 -> 0.223 | FP8: =Daily_Composite!J175 -> 0.353 | FQ8: =Daily_Composite!J176 -> 0.211 | FR8: =Daily_Composite!J177 -> 0.208 | FS8: =Daily_Composite!J178 -> 0.291 | FT8: =Daily_Composite!J179 -> 0.049 | FU8: =Daily_Composite!J180 -> 0.172 | FV8: =Daily_Composite!J181 -> 0.162 | FW8: =Daily_Composite!J182 -> 0.146 | FX8: =Daily_Composite!J183 -> 0.021 | FY8: =Daily_Composite!J184 -> -0.173 | FZ8: =Daily_Composite!J185 -> 0.166 | GA8: =Daily_Composite!J186 -> 0.174 | GB8: =Daily_Composite!J187 -> 0.134 | GC8: =Daily_Composite!J188 -> -0.057 | GD8: =Daily_Composite!J189 -> 0.116 | GE8: =Daily_Composite!J190 -> 0.059 | GF8: =Daily_Composite!J191 -> 0.042 | GG8: =Daily_Composite!J192 -> 0.074 | GH8: =Daily_Composite!J193 -> 0.109 | GI8: =Daily_Composite!J194 -> 0.313 | GJ8: =Daily_Composite!J195 -> 0.072 | GK8: =Daily_Composite!J196 -> 0.056 | GL8: =Daily_Composite!J197 -> 0.012 | GM8: =Daily_Composite!J198 -> 0.013 | GN8: =Daily_Composite!J199 -> 0.447 | GO8: =Daily_Composite!J200 -> 0.451 | GP8: =Daily_Composite!J201 -> 0.13 | GQ8: =Daily_Composite!J202 -> 0.031 | GR8: =Daily_Composite!J203 -> 0.507 | GS8: =Daily_Composite!J204 -> 0.018 | GT8: =Daily_Composite!J205 -> 0.066 | GU8: =Daily_Composite!J206 -> 0.132 | GV8: =Daily_Composite!J207 -> 0.26 | GW8: =Daily_Composite!J208 -> 0.098 | GX8: =Daily_Composite!J209 -> 0.099 | GY8: =Daily_Composite!J210 -> -0.001 | GZ8: =Daily_Composite!J211 -> -0.012 | HA8: =Daily_Composite!J212 -> 0.347 | HB8: =Daily_Composite!J213 -> -0.091 | HC8: =Daily_Composite!J214 -> -0.149 | HD8: =Daily_Composite!J215 -> 0.081 | HE8: =Daily_Composite!J216 -> 0.078 | HF8: =Daily_Composite!J217 -> -0.016 | HG8: =Daily_Composite!J218 -> -0.424 | HH8: =Daily_Composite!J219 -> -0.285 | HI8: =Daily_Composite!J220 -> 0.069 | HJ8: =Daily_Composite!J221 -> 0.069 | HK8: =Daily_Composite!J222 -> -0.217 | HL8: =Daily_Composite!J223 -> -0.172 | HM8: =Daily_Composite!J224 -> -0.031 | HN8: =Daily_Composite!J225 -> -0.033 | HO8: =Daily_Composite!J226 -> -0.034 | HP8: =Daily_Composite!J227 -> -0.142 | HQ8: =Daily_Composite!J228 -> -0.099 | HR8: =Daily_Composite!J229 -> 0.075 | HS8: =Daily_Composite!J230 -> 0.331 | HT8: =Daily_Composite!J231 -> -0.017 | HU8: =Daily_Composite!J232 -> 0.019 | HV8: =Daily_Composite!J233 -> 0.199 | HW8: =Daily_Composite!J234 -> 0.159 | HX8: =Daily_Composite!J235 -> 0.035 | HY8: =Daily_Composite!J236 -> 0.082 | HZ8: =Daily_Composite!J237 -> 0.177 | IA8: =Daily_Composite!J238 -> 0.302 | IB8: =Daily_Composite!J239 -> 0.586 | IC8: =Daily_Composite!J240 -> 0.139 | ID8: =Daily_Composite!J241 -> 0.14 | IE8: =Daily_Composite!J242 -> 0.177 | IF8: =Daily_Composite!J243 -> 0.164 | IG8: =Daily_Composite!J244 -> 0.173 | IH8: =Daily_Composite!J245 -> 0.156 | II8: =Daily_Composite!J246 -> 0.323 | IJ8: =Daily_Composite!J247 -> 0.318 | IK8: =Daily_Composite!J248 -> 0.243 | IL8: =Daily_Composite!J249 -> 0.612 | IM8: =Daily_Composite!J250 -> 0.18 | IN8: =Daily_Composite!J251 -> 0.183 | IO8: =Daily_Composite!J252 -> 0.179 | IP8: =Daily_Composite!J253 -> 0.174 | IQ8: =Daily_Composite!J254 -> 0.33 | IR8: =Daily_Composite!J255 -> 0.339 | IS8: =Daily_Composite!J256 -> 0.022 | IT8: =Daily_Composite!J257 -> 0.586 | IU8: =Daily_Composite!J258 -> 0.02 | IV8: =Daily_Composite!J259 -> 0.019 | IW8: =Daily_Composite!J260 -> 0.197 | IX8: =Daily_Composite!J261 -> 0.122 | IY8: =Daily_Composite!J262 -> -0.018 | IZ8: =Daily_Composite!J263 -> 0.018 | JA8: =Daily_Composite!J264 -> 0.008 | JB8: =Daily_Composite!J265 -> -0.009 | JC8: =Daily_Composite!J266 -> 0.515 | JD8: =Daily_Composite!J267 -> -0.057 | JE8: =Daily_Composite!J268 -> -0.12 | JF8: =Daily_Composite!J269 -> -0.115 | JG8: =Daily_Composite!J270 -> -0.086 | JH8: =Daily_Composite!J271 -> -0.117 | JI8: =Daily_Composite!J272 -> -0.262 | JJ8: =Daily_Composite!J273 -> -0.355 | JK8: =Daily_Composite!J274 -> -0.467 | JL8: =Daily_Composite!J275 -> -0.227 | JM8: =Daily_Composite!J276 -> 0.106 | JN8: =Daily_Composite!J277 -> -0.346 | JO8: =Daily_Composite!J278 -> -0.333 | JP8: =Daily_Composite!J279 -> -0.313 | JQ8: =Daily_Composite!J280 -> -0.21 | JR8: =Daily_Composite!J281 -> -0.18 | JS8: =Daily_Composite!J282 -> 0.092 | JT8: =Daily_Composite!J283 -> 0.088 | JU8: =Daily_Composite!J284 -> -0.12 | JV8: =Daily_Composite!J285 -> 0.464 | JW8: =Daily_Composite!J286 -> -0.02 | JX8: =Daily_Composite!J287 -> -0.009 | JY8: =Daily_Composite!J288 -> 0.067 | JZ8: =Daily_Composite!J289 -> 0.132 | KA8: =Daily_Composite!J290 -> -0.158 | KB8: =Daily_Composite!J291 -> -0.131 | KC8: =Daily_Composite!J292 -> -0.159 | KD8: =Daily_Composite!J293 -> 0.479 | KE8: =Daily_Composite!J294 -> -0.198 | KF8: =Daily_Composite!J295 -> -0.253 | KG8: =Daily_Composite!J296 -> -0.336 | KH8: =Daily_Composite!J297 -> -0.284 | KI8: =Daily_Composite!J298 -> -0.253 | KJ8: =Daily_Composite!J299 -> -0.283 | KK8: =Daily_Composite!J300 -> -0.469 | KL8: =Daily_Composite!J301 -> -0.458 | KM8: =Daily_Composite!J302 -> -0.393 | KN8: =Daily_Composite!J303 -> 0.235 | KO8: =Daily_Composite!J304 -> -0.412 | KP8: =Daily_Composite!J305 -> -0.349 | KQ8: =Daily_Composite!J306 -> -0.341 | KR8: =Daily_Composite!J307 -> -0.389 | KS8: =Daily_Composite!J308 -> -0.388 | KT8: =Daily_Composite!J309 -> -0.236 | KU8: =Daily_Composite!J310 -> -0.144 | KV8: =Daily_Composite!J311 -> -0.274 | KW8: =Daily_Composite!J312 -> 0.163 | KX8: =Daily_Composite!J313 -> -0.103 | KY8: =Daily_Composite!J314 -> -0.097 | KZ8: =Daily_Composite!J315 -> -0.369 | LA8: =Daily_Composite!J316 -> -0.366 | LB8: =Daily_Composite!J317 -> -0.062 | LC8: =Daily_Composite!J318 -> -0.058 | LD8: =Daily_Composite!J319 -> -0.074 | LE8: =Daily_Composite!J320 -> -0.054 | LF8: =Daily_Composite!J321 -> 0.202 | LG8: =Daily_Composite!J322 -> 0.028 | LH8: =Daily_Composite!J323 -> 0.116 | LI8: =Daily_Composite!J324 -> 0.074 | LJ8: =Daily_Composite!J325 -> 0.046 | LK8: =Daily_Composite!J326 -> 0.054 | LL8: =Daily_Composite!J327 -> 0.016 | LM8: =Daily_Composite!J328 -> -0.033 | LN8: =Daily_Composite!J329 -> 0.049 | LO8: =Daily_Composite!J330 -> 0.003 | LP8: =Daily_Composite!J331 -> 0.209 | LQ8: =Daily_Composite!J332 -> -0.022 | LR8: =Daily_Composite!J333 -> 0.013 | LS8: =Daily_Composite!J334 -> -0.051 | LT8: =Daily_Composite!J335 -> -0.143 | LU8: =Daily_Composite!J336 -> -0.456 | LV8: =Daily_Composite!J337 -> -0.44 | LW8: =Daily_Composite!J338 -> -0.187 | LX8: =Daily_Composite!J339 -> -0.17 | LY8: =Daily_Composite!J340 -> -0.194 | LZ8: =Daily_Composite!J341 -> -0.177 | MA8: =Daily_Composite!J342 -> -0.473 | MB8: =Daily_Composite!J343 -> -0.523 | MC8: =Daily_Composite!J344 -> -0.426 | MD8: =Daily_Composite!J345 -> -0.144 | ME8: =Daily_Composite!J346 -> -0.111 | MF8: =Daily_Composite!J347 -> -0.018 | MG8: =Daily_Composite!J348 -> 0.127 | MH8: =Daily_Composite!J349 -> 0.032 | MI8: =Daily_Composite!J350 -> 0.092 | MJ8: =Daily_Composite!J351 -> 0.249 | MK8: =Daily_Composite!J352 -> 0.24 | ML8: =Daily_Composite!J353 -> 0.218 | MM8: =Daily_Composite!J354 -> -0.131 | MN8: =Daily_Composite!J355 -> -0.177 | MO8: =Daily_Composite!J356 -> 0.015 | MP8: =Daily_Composite!J357 -> 0.09 | MQ8: =Daily_Composite!J358 -> 0.51 | MR8: =Daily_Composite!J359 -> 0.124 | MS8: =Daily_Composite!J360 -> 0.131 | MT8: =Daily_Composite!J361 -> 0.177 | MU8: =Daily_Composite!J362 -> 0.161 | MV8: =Daily_Composite!J363 -> 0.162 | MW8: =Daily_Composite!J364 -> 0.222 | MX8: =Daily_Composite!J365 -> 0.274 | MY8: =Daily_Composite!J366 -> -0.015 | MZ8: =Daily_Composite!J367 -> 0.575 | NA8: =Daily_Composite!J368 -> 0.2 | NB8: =Daily_Composite!J369 -> 0.192
A9: Banking & financial | B9: =Daily_Composite!K5 -> -0.289 | C9: =Daily_Composite!K6 -> 0.163 | D9: =Daily_Composite!K7 -> -0.035 | E9: =Daily_Composite!K8 -> -0.115 | F9: =Daily_Composite!K9 -> -0.415 | G9: =Daily_Composite!K10 -> -0.126 | H9: =Daily_Composite!K11 -> 0.174 | I9: =Daily_Composite!K12 -> -0.035 | J9: =Daily_Composite!K13 -> 0.12 | K9: =Daily_Composite!K14 -> 0.027 | L9: =Daily_Composite!K15 -> -0.079 | M9: =Daily_Composite!K16 -> -0.121 | N9: =Daily_Composite!K17 -> -0.173 | O9: =Daily_Composite!K18 -> -0.289 | P9: =Daily_Composite!K19 -> 0.076 | Q9: =Daily_Composite!K20 -> 0.096 | R9: =Daily_Composite!K21 -> 0.391 | S9: =Daily_Composite!K22 -> 0.337 | T9: =Daily_Composite!K23 -> 0.637 | U9: =Daily_Composite!K24 -> 0.24 | V9: =Daily_Composite!K25 -> 0.259 | W9: =Daily_Composite!K26 -> 0.108 | X9: =Daily_Composite!K27 -> 0.074 | Y9: =Daily_Composite!K28 -> 0.593 | Z9: =Daily_Composite!K29 -> 0.248 | AA9: =Daily_Composite!K30 -> 0.395 | AB9: =Daily_Composite!K31 -> 0.079 | AC9: =Daily_Composite!K32 -> 0.339 | AD9: =Daily_Composite!K33 -> 0.352 | AE9: =Daily_Composite!K34 -> 0.364 | AF9: =Daily_Composite!K35 -> 0.34 | AG9: =Daily_Composite!K36 -> 0.455 | AH9: =Daily_Composite!K37 -> 0.612 | AI9: =Daily_Composite!K38 -> 0.604 | AJ9: =Daily_Composite!K39 -> 0.314 | AK9: =Daily_Composite!K40 -> 0.616 | AL9: =Daily_Composite!K41 -> 0.305 | AM9: =Daily_Composite!K42 -> 0.267 | AN9: =Daily_Composite!K43 -> 0.239 | AO9: =Daily_Composite!K44 -> -0.042 | AP9: =Daily_Composite!K45 -> 0.094 | AQ9: =Daily_Composite!K46 -> 0.588 | AR9: =Daily_Composite!K47 -> 0.173 | AS9: =Daily_Composite!K48 -> 0.085 | AT9: =Daily_Composite!K49 -> 0.533 | AU9: =Daily_Composite!K50 -> 0.497 | AV9: =Daily_Composite!K51 -> 0.261 | AW9: =Daily_Composite!K52 -> 0.093 | AX9: =Daily_Composite!K53 -> 0.077 | AY9: =Daily_Composite!K54 -> 0.131 | AZ9: =Daily_Composite!K55 -> 0.132 | BA9: =Daily_Composite!K56 -> 0.456 | BB9: =Daily_Composite!K57 -> -0.061 | BC9: =Daily_Composite!K58 -> -0.311 | BD9: =Daily_Composite!K59 -> -0.045 | BE9: =Daily_Composite!K60 -> -0.283 | BF9: =Daily_Composite!K61 -> 0.075 | BG9: =Daily_Composite!K62 -> 0.047 | BH9: =Daily_Composite!K63 -> -0.036 | BI9: =Daily_Composite!K64 -> 0.267 | BJ9: =Daily_Composite!K65 -> -0.034 | BK9: =Daily_Composite!K66 -> 0.247 | BL9: =Daily_Composite!K67 -> -0.044 | BM9: =Daily_Composite!K68 -> 0.278 | BN9: =Daily_Composite!K69 -> 0.077 | BO9: =Daily_Composite!K70 -> 0.067 | BP9: =Daily_Composite!K71 -> -0.026 | BQ9: =Daily_Composite!K72 -> -0.037 | BR9: =Daily_Composite!K73 -> 0.283 | BS9: =Daily_Composite!K74 -> -0.219 | BT9: =Daily_Composite!K75 -> 0.064 | BU9: =Daily_Composite!K76 -> 0.156 | BV9: =Daily_Composite!K77 -> 0.008 | BW9: =Daily_Composite!K78 -> 0.082 | BX9: =Daily_Composite!K79 -> -0.128 | BY9: =Daily_Composite!K80 -> -0.167 | BZ9: =Daily_Composite!K81 -> 0.016 | CA9: =Daily_Composite!K82 -> -0.009 | CB9: =Daily_Composite!K83 -> 0.496 | CC9: =Daily_Composite!K84 -> -0.023 | CD9: =Daily_Composite!K85 -> 0.488 | CE9: =Daily_Composite!K86 -> -0.031 | CF9: =Daily_Composite!K87 -> 0.447 | CG9: =Daily_Composite!K88 -> -0.175 | CH9: =Daily_Composite!K89 -> -0.084 | CI9: =Daily_Composite!K90 -> 0.096 | CJ9: =Daily_Composite!K91 -> 0.232 | CK9: =Daily_Composite!K92 -> 0.004 | CL9: =Daily_Composite!K93 -> -0.128 | CM9: =Daily_Composite!K94 -> 0.004 | CN9: =Daily_Composite!K95 -> -0.168 | CO9: =Daily_Composite!K96 -> -0.221 | CP9: =Daily_Composite!K97 -> -0.252 | CQ9: =Daily_Composite!K98 -> -0.427 | CR9: =Daily_Composite!K99 -> -0.412 | CS9: =Daily_Composite!K100 -> -0.448 | CT9: =Daily_Composite!K101 -> -0.24 | CU9: =Daily_Composite!K102 -> -0.461 | CV9: =Daily_Composite!K103 -> -0.393 | CW9: =Daily_Composite!K104 -> -0.466 | CX9: =Daily_Composite!K105 -> -0.498 | CY9: =Daily_Composite!K106 -> -0.293 | CZ9: =Daily_Composite!K107 -> -0.328 | DA9: =Daily_Composite!K108 -> -0.119 | DB9: =Daily_Composite!K109 -> -0.126 | DC9: =Daily_Composite!K110 -> -0.144 | DD9: =Daily_Composite!K111 -> 0.142 | DE9: =Daily_Composite!K112 -> -0.294 | DF9: =Daily_Composite!K113 -> -0.029 | DG9: =Daily_Composite!K114 -> -0.069 | DH9: =Daily_Composite!K115 -> -0.343 | DI9: =Daily_Composite!K116 -> -0.346 | DJ9: =Daily_Composite!K117 -> -0.425 | DK9: =Daily_Composite!K118 -> -0.435 | DL9: =Daily_Composite!K119 -> -0.472 | DM9: =Daily_Composite!K120 -> -0.136 | DN9: =Daily_Composite!K121 -> -0.396 | DO9: =Daily_Composite!K122 -> -0.304 | DP9: =Daily_Composite!K123 -> -0.306 | DQ9: =Daily_Composite!K124 -> -0.272 | DR9: =Daily_Composite!K125 -> -0.288 | DS9: =Daily_Composite!K126 -> -0.296 | DT9: =Daily_Composite!K127 -> -0.39 | DU9: =Daily_Composite!K128 -> -0.071 | DV9: =Daily_Composite!K129 -> -0.096 | DW9: =Daily_Composite!K130 -> 0.492 | DX9: =Daily_Composite!K131 -> -0.117 | DY9: =Daily_Composite!K132 -> 0.11 | DZ9: =Daily_Composite!K133 -> -0.091 | EA9: =Daily_Composite!K134 -> -0.1 | EB9: =Daily_Composite!K135 -> -0.063 | EC9: =Daily_Composite!K136 -> -0.013 | ED9: =Daily_Composite!K137 -> -0.321 | EE9: =Daily_Composite!K138 -> 0.082 | EF9: =Daily_Composite!K139 -> 0.239 | EG9: =Daily_Composite!K140 -> -0.056 | EH9: =Daily_Composite!K141 -> -0.142 | EI9: =Daily_Composite!K142 -> -0.061 | EJ9: =Daily_Composite!K143 -> -0.278 | EK9: =Daily_Composite!K144 -> -0.479 | EL9: =Daily_Composite!K145 -> -0.377 | EM9: =Daily_Composite!K146 -> -0.444 | EN9: =Daily_Composite!K147 -> -0.167 | EO9: =Daily_Composite!K148 -> -0.374 | EP9: =Daily_Composite!K149 -> -0.111 | EQ9: =Daily_Composite!K150 -> -0.266 | ER9: =Daily_Composite!K151 -> -0.066 | ES9: =Daily_Composite!K152 -> -0.022 | ET9: =Daily_Composite!K153 -> -0.147 | EU9: =Daily_Composite!K154 -> -0.143 | EV9: =Daily_Composite!K155 -> 0.101 | EW9: =Daily_Composite!K156 -> 0.107 | EX9: =Daily_Composite!K157 -> 0.369 | EY9: =Daily_Composite!K158 -> -0.006 | EZ9: =Daily_Composite!K159 -> 0.172 | FA9: =Daily_Composite!K160 -> -0.075 | FB9: =Daily_Composite!K161 -> -0.035 | FC9: =Daily_Composite!K162 -> -0.049 | FD9: =Daily_Composite!K163 -> -0.075 | FE9: =Daily_Composite!K164 -> -0.065 | FF9: =Daily_Composite!K165 -> 0.476 | FG9: =Daily_Composite!K166 -> 0.11 | FH9: =Daily_Composite!K167 -> 0.173 | FI9: =Daily_Composite!K168 -> 0.054 | FJ9: =Daily_Composite!K169 -> 0.16 | FK9: =Daily_Composite!K170 -> 0.175 | FL9: =Daily_Composite!K171 -> 0.145 | FM9: =Daily_Composite!K172 -> 0.114 | FN9: =Daily_Composite!K173 -> 0.129 | FO9: =Daily_Composite!K174 -> -0.072 | FP9: =Daily_Composite!K175 -> -0.103 | FQ9: =Daily_Composite!K176 -> 0.002 | FR9: =Daily_Composite!K177 -> 0.39 | FS9: =Daily_Composite!K178 -> -0.116 | FT9: =Daily_Composite!K179 -> -0.254 | FU9: =Daily_Composite!K180 -> -0.278 | FV9: =Daily_Composite!K181 -> -0.162 | FW9: =Daily_Composite!K182 -> -0.451 | FX9: =Daily_Composite!K183 -> -0.341 | FY9: =Daily_Composite!K184 -> -0.404 | FZ9: =Daily_Composite!K185 -> -0.038 | GA9: =Daily_Composite!K186 -> 0.049 | GB9: =Daily_Composite!K187 -> -0.12 | GC9: =Daily_Composite!K188 -> -0.39 | GD9: =Daily_Composite!K189 -> -0.036 | GE9: =Daily_Composite!K190 -> -0.07 | GF9: =Daily_Composite!K191 -> -0.219 | GG9: =Daily_Composite!K192 -> -0.524 | GH9: =Daily_Composite!K193 -> -0.25 | GI9: =Daily_Composite!K194 -> -0.148 | GJ9: =Daily_Composite!K195 -> -0.039 | GK9: =Daily_Composite!K196 -> 0.308 | GL9: =Daily_Composite!K197 -> -0.325 | GM9: =Daily_Composite!K198 -> -0.284 | GN9: =Daily_Composite!K199 -> -0.021 | GO9: =Daily_Composite!K200 -> -0.266 | GP9: =Daily_Composite!K201 -> -0.391 | GQ9: =Daily_Composite!K202 -> -0.21 | GR9: =Daily_Composite!K203 -> 0.265 | GS9: =Daily_Composite!K204 -> -0.296 | GT9: =Daily_Composite!K205 -> -0.235 | GU9: =Daily_Composite!K206 -> -0.314 | GV9: =Daily_Composite!K207 -> -0.261 | GW9: =Daily_Composite!K208 -> -0.285 | GX9: =Daily_Composite!K209 -> -0.506 | GY9: =Daily_Composite!K210 -> -0.494 | GZ9: =Daily_Composite!K211 -> -0.338 | HA9: =Daily_Composite!K212 -> 0.059 | HB9: =Daily_Composite!K213 -> -0.463 | HC9: =Daily_Composite!K214 -> -0.639 | HD9: =Daily_Composite!K215 -> -0.108 | HE9: =Daily_Composite!K216 -> -0.082 | HF9: =Daily_Composite!K217 -> -0.15 | HG9: =Daily_Composite!K218 -> -0.372 | HH9: =Daily_Composite!K219 -> -0.545 | HI9: =Daily_Composite!K220 -> -0.166 | HJ9: =Daily_Composite!K221 -> -0.147 | HK9: =Daily_Composite!K222 -> -0.237 | HL9: =Daily_Composite!K223 -> -0.613 | HM9: =Daily_Composite!K224 -> -0.326 | HN9: =Daily_Composite!K225 -> -0.624 | HO9: =Daily_Composite!K226 -> -0.615 | HP9: =Daily_Composite!K227 -> -0.576 | HQ9: =Daily_Composite!K228 -> -0.659 | HR9: =Daily_Composite!K229 -> -0.343 | HS9: =Daily_Composite!K230 -> 0.094 | HT9: =Daily_Composite!K231 -> -0.498 | HU9: =Daily_Composite!K232 -> -0.544 | HV9: =Daily_Composite!K233 -> -0.44 | HW9: =Daily_Composite!K234 -> -0.441 | HX9: =Daily_Composite!K235 -> -0.429 | HY9: =Daily_Composite!K236 -> -0.343 | HZ9: =Daily_Composite!K237 -> -0.216 | IA9: =Daily_Composite!K238 -> -0.223 | IB9: =Daily_Composite!K239 -> 0.309 | IC9: =Daily_Composite!K240 -> 0.283 | ID9: =Daily_Composite!K241 -> 0.224 | IE9: =Daily_Composite!K242 -> -0.028 | IF9: =Daily_Composite!K243 -> 0.103 | IG9: =Daily_Composite!K244 -> 0.112 | IH9: =Daily_Composite!K245 -> -0.083 | II9: =Daily_Composite!K246 -> -0.024 | IJ9: =Daily_Composite!K247 -> 0.622 | IK9: =Daily_Composite!K248 -> 0.494 | IL9: =Daily_Composite!K249 -> 0.633 | IM9: =Daily_Composite!K250 -> 0.22 | IN9: =Daily_Composite!K251 -> 0.624 | IO9: =Daily_Composite!K252 -> 0.325 | IP9: =Daily_Composite!K253 -> 0.413 | IQ9: =Daily_Composite!K254 -> 0.248 | IR9: =Daily_Composite!K255 -> 0.473 | IS9: =Daily_Composite!K256 -> 0.241 | IT9: =Daily_Composite!K257 -> 0.593 | IU9: =Daily_Composite!K258 -> 0.395 | IV9: =Daily_Composite!K259 -> 0.595 | IW9: =Daily_Composite!K260 -> 0.21 | IX9: =Daily_Composite!K261 -> 0.227 | IY9: =Daily_Composite!K262 -> 0.25 | IZ9: =Daily_Composite!K263 -> 0.176 | JA9: =Daily_Composite!K264 -> 0.288 | JB9: =Daily_Composite!K265 -> 0.264 | JC9: =Daily_Composite!K266 -> 0.59 | JD9: =Daily_Composite!K267 -> 0.393 | JE9: =Daily_Composite!K268 -> 0.527 | JF9: =Daily_Composite!K269 -> 0.303 | JG9: =Daily_Composite!K270 -> 0.281 | JH9: =Daily_Composite!K271 -> 0.262 | JI9: =Daily_Composite!K272 -> 0.356 | JJ9: =Daily_Composite!K273 -> 0.273 | JK9: =Daily_Composite!K274 -> 0.303 | JL9: =Daily_Composite!K275 -> 0.008 | JM9: =Daily_Composite!K276 -> 0.346 | JN9: =Daily_Composite!K277 -> 0.081 | JO9: =Daily_Composite!K278 -> -0.342 | JP9: =Daily_Composite!K279 -> -0.033 | JQ9: =Daily_Composite!K280 -> -0.245 | JR9: =Daily_Composite!K281 -> 0.021 | JS9: =Daily_Composite!K282 -> 0.268 | JT9: =Daily_Composite!K283 -> 0.271 | JU9: =Daily_Composite!K284 -> 0.013 | JV9: =Daily_Composite!K285 -> 0.525 | JW9: =Daily_Composite!K286 -> 0.564 | JX9: =Daily_Composite!K287 -> 0.293 | JY9: =Daily_Composite!K288 -> 0.233 | JZ9: =Daily_Composite!K289 -> 0.262 | KA9: =Daily_Composite!K290 -> 0.258 | KB9: =Daily_Composite!K291 -> 0.303 | KC9: =Daily_Composite!K292 -> -0.056 | KD9: =Daily_Composite!K293 -> 0.509 | KE9: =Daily_Composite!K294 -> 0.229 | KF9: =Daily_Composite!K295 -> 0.369 | KG9: =Daily_Composite!K296 -> -0.163 | KH9: =Daily_Composite!K297 -> -0.421 | KI9: =Daily_Composite!K298 -> -0.304 | KJ9: =Daily_Composite!K299 -> -0.159 | KK9: =Daily_Composite!K300 -> -0.124 | KL9: =Daily_Composite!K301 -> 0.002 | KM9: =Daily_Composite!K302 -> -0.029 | KN9: =Daily_Composite!K303 -> 0.381 | KO9: =Daily_Composite!K304 -> -0.213 | KP9: =Daily_Composite!K305 -> -0.068 | KQ9: =Daily_Composite!K306 -> 0.194 | KR9: =Daily_Composite!K307 -> -0.209 | KS9: =Daily_Composite!K308 -> -0.258 | KT9: =Daily_Composite!K309 -> -0.129 | KU9: =Daily_Composite!K310 -> -0.379 | KV9: =Daily_Composite!K311 -> -0.162 | KW9: =Daily_Composite!K312 -> 0.23 | KX9: =Daily_Composite!K313 -> 0.189 | KY9: =Daily_Composite!K314 -> -0.357 | KZ9: =Daily_Composite!K315 -> -0.11 | LA9: =Daily_Composite!K316 -> -0.087 | LB9: =Daily_Composite!K317 -> -0.158 | LC9: =Daily_Composite!K318 -> -0.099 | LD9: =Daily_Composite!K319 -> 0.253 | LE9: =Daily_Composite!K320 -> 0.307 | LF9: =Daily_Composite!K321 -> 0.101 | LG9: =Daily_Composite!K322 -> 0.141 | LH9: =Daily_Composite!K323 -> 0.647 | LI9: =Daily_Composite!K324 -> 0.195 | LJ9: =Daily_Composite!K325 -> 0.179 | LK9: =Daily_Composite!K326 -> 0.159 | LL9: =Daily_Composite!K327 -> 0.331 | LM9: =Daily_Composite!K328 -> 0.613 | LN9: =Daily_Composite!K329 -> 0.349 | LO9: =Daily_Composite!K330 -> 0.002 | LP9: =Daily_Composite!K331 -> -0.012 | LQ9: =Daily_Composite!K332 -> -0.168 | LR9: =Daily_Composite!K333 -> 0.189 | LS9: =Daily_Composite!K334 -> -0.292 | LT9: =Daily_Composite!K335 -> -0.491 | LU9: =Daily_Composite!K336 -> -0.45 | LV9: =Daily_Composite!K337 -> -0.418 | LW9: =Daily_Composite!K338 -> -0.245 | LX9: =Daily_Composite!K339 -> -0.244 | LY9: =Daily_Composite!K340 -> -0.261 | LZ9: =Daily_Composite!K341 -> -0.211 | MA9: =Daily_Composite!K342 -> -0.294 | MB9: =Daily_Composite!K343 -> -0.366 | MC9: =Daily_Composite!K344 -> -0.31 | MD9: =Daily_Composite!K345 -> -0.24 | ME9: =Daily_Composite!K346 -> -0.23 | MF9: =Daily_Composite!K347 -> 0.335 | MG9: =Daily_Composite!K348 -> 0.6 | MH9: =Daily_Composite!K349 -> 0.572 | MI9: =Daily_Composite!K350 -> 0.714 | MJ9: =Daily_Composite!K351 -> 0.741 | MK9: =Daily_Composite!K352 -> 0.641 | ML9: =Daily_Composite!K353 -> 0.63 | MM9: =Daily_Composite!K354 -> 0.662 | MN9: =Daily_Composite!K355 -> 0.38 | MO9: =Daily_Composite!K356 -> 0.716 | MP9: =Daily_Composite!K357 -> 0.665 | MQ9: =Daily_Composite!K358 -> 0.665 | MR9: =Daily_Composite!K359 -> 0.228 | MS9: =Daily_Composite!K360 -> 0.564 | MT9: =Daily_Composite!K361 -> 0.33 | MU9: =Daily_Composite!K362 -> 0.272 | MV9: =Daily_Composite!K363 -> -0.077 | MW9: =Daily_Composite!K364 -> -0.05 | MX9: =Daily_Composite!K365 -> 0.006 | MY9: =Daily_Composite!K366 -> 0.157 | MZ9: =Daily_Composite!K367 -> 0.531 | NA9: =Daily_Composite!K368 -> 0.09 | NB9: =Daily_Composite!K369 -> 0.133
A10: Capital goods | B10: =Daily_Composite!L5 -> 0.054 | C10: =Daily_Composite!L6 -> -0.125 | D10: =Daily_Composite!L7 -> 0.129 | E10: =Daily_Composite!L8 -> -0.022 | F10: =Daily_Composite!L9 -> -0.06 | G10: =Daily_Composite!L10 -> -0.233 | H10: =Daily_Composite!L11 -> -0.227 | I10: =Daily_Composite!L12 -> -0.165 | J10: =Daily_Composite!L13 -> -0.206 | K10: =Daily_Composite!L14 -> -0.244 | L10: =Daily_Composite!L15 -> -0.201 | M10: =Daily_Composite!L16 -> -0.201 | N10: =Daily_Composite!L17 -> -0.202 | O10: =Daily_Composite!L18 -> -0.202 | P10: =Daily_Composite!L19 -> -0.202 | Q10: =Daily_Composite!L20 -> -0.181 | R10: =Daily_Composite!L21 -> 0.433 | S10: =Daily_Composite!L22 -> 0.228 | T10: =Daily_Composite!L23 -> 0.198 | U10: =Daily_Composite!L24 -> 0.198 | V10: =Daily_Composite!L25 -> 0.198 | W10: =Daily_Composite!L26 -> -0.012 | X10: =Daily_Composite!L27 -> 0.252 | Y10: =Daily_Composite!L28 -> 0.236 | Z10: =Daily_Composite!L29 -> 0.144 | AA10: =Daily_Composite!L30 -> 0.128 | AB10: =Daily_Composite!L31 -> 0.511 | AC10: =Daily_Composite!L32 -> 0.015 | AD10: =Daily_Composite!L33 -> 0.107 | AE10: =Daily_Composite!L34 -> 0.118 | AF10: =Daily_Composite!L35 -> 0.645 | AG10: =Daily_Composite!L36 -> 0.184 | AH10: =Daily_Composite!L37 -> 0.156 | AI10: =Daily_Composite!L38 -> 0.169 | AJ10: =Daily_Composite!L39 -> 0.18 | AK10: =Daily_Composite!L40 -> 0.166 | AL10: =Daily_Composite!L41 -> 0.151 | AM10: =Daily_Composite!L42 -> -0.046 | AN10: =Daily_Composite!L43 -> 0.497 | AO10: =Daily_Composite!L44 -> 0.113 | AP10: =Daily_Composite!L45 -> 0.123 | AQ10: =Daily_Composite!L46 -> 0.414 | AR10: =Daily_Composite!L47 -> 0.406 | AS10: =Daily_Composite!L48 -> 0.437 | AT10: =Daily_Composite!L49 -> 0.068 | AU10: =Daily_Composite!L50 -> 0.063 | AV10: =Daily_Composite!L51 -> 0.013 | AW10: =Daily_Composite!L52 -> 0.019 | AX10: =Daily_Composite!L53 -> 0.451 | AY10: =Daily_Composite!L54 -> 0.006 | AZ10: =Daily_Composite!L55 -> -0.056 | BA10: =Daily_Composite!L56 -> 0.023 | BB10: =Daily_Composite!L57 -> 0.06 | BC10: =Daily_Composite!L58 -> 0.057 | BD10: =Daily_Composite!L59 -> 0.355 | BE10: =Daily_Composite!L60 -> 0.21 | BF10: =Daily_Composite!L61 -> 0.067 | BG10: =Daily_Composite!L62 -> 0.498 | BH10: =Daily_Composite!L63 -> 0.071 | BI10: =Daily_Composite!L64 -> -0.005 | BJ10: =Daily_Composite!L65 -> 0.066 | BK10: =Daily_Composite!L66 -> 0.062 | BL10: =Daily_Composite!L67 -> 0.069 | BM10: =Daily_Composite!L68 -> 0.067 | BN10: =Daily_Composite!L69 -> 0.051 | BO10: =Daily_Composite!L70 -> 0.024 | BP10: =Daily_Composite!L71 -> 0.238 | BQ10: =Daily_Composite!L72 -> 0.032 | BR10: =Daily_Composite!L73 -> 0.035 | BS10: =Daily_Composite!L74 -> 0.278 | BT10: =Daily_Composite!L75 -> 0.345 | BU10: =Daily_Composite!L76 -> 0.024 | BV10: =Daily_Composite!L77 -> -0.025 | BW10: =Daily_Composite!L78 -> -0.004 | BX10: =Daily_Composite!L79 -> -0.011 | BY10: =Daily_Composite!L80 -> -0.011 | BZ10: =Daily_Composite!L81 -> 0.428 | CA10: =Daily_Composite!L82 -> -0.013 | CB10: =Daily_Composite!L83 -> 0.154 | CC10: =Daily_Composite!L84 -> 0.043 | CD10: =Daily_Composite!L85 -> 0.044 | CE10: =Daily_Composite!L86 -> 0.414 | CF10: =Daily_Composite!L87 -> 0.424 | CG10: =Daily_Composite!L88 -> 0.013 | CH10: =Daily_Composite!L89 -> -0.018 | CI10: =Daily_Composite!L90 -> 0.423 | CJ10: =Daily_Composite!L91 -> 0.134 | CK10: =Daily_Composite!L92 -> 0.108 | CL10: =Daily_Composite!L93 -> 0.019 | CM10: =Daily_Composite!L94 -> 0.023 | CN10: =Daily_Composite!L95 -> 0.042 | CO10: =Daily_Composite!L96 -> 0.01 | CP10: =Daily_Composite!L97 -> 0.016 | CQ10: =Daily_Composite!L98 -> -0.403 | CR10: =Daily_Composite!L99 -> -0.032 | CS10: =Daily_Composite!L100 -> -0.031 | CT10: =Daily_Composite!L101 -> -0.183 | CU10: =Daily_Composite!L102 -> -0.205 | CV10: =Daily_Composite!L103 -> -0.172 | CW10: =Daily_Composite!L104 -> -0.107 | CX10: =Daily_Composite!L105 -> -0.141 | CY10: =Daily_Composite!L106 -> -0.19 | CZ10: =Daily_Composite!L107 -> -0.222 | DA10: =Daily_Composite!L108 -> -0.151 | DB10: =Daily_Composite!L109 -> -0.063 | DC10: =Daily_Composite!L110 -> -0.055 | DD10: =Daily_Composite!L111 -> -0.157 | DE10: =Daily_Composite!L112 -> -0.097 | DF10: =Daily_Composite!L113 -> 0.125 | DG10: =Daily_Composite!L114 -> 0.013 | DH10: =Daily_Composite!L115 -> 0.103 | DI10: =Daily_Composite!L116 -> 0.103 | DJ10: =Daily_Composite!L117 -> -0.023 | DK10: =Daily_Composite!L118 -> -0.026 | DL10: =Daily_Composite!L119 -> -0.04 | DM10: =Daily_Composite!L120 -> 0.065 | DN10: =Daily_Composite!L121 -> 0.062 | DO10: =Daily_Composite!L122 -> 0.18 | DP10: =Daily_Composite!L123 -> 0.064 | DQ10: =Daily_Composite!L124 -> 0.048 | DR10: =Daily_Composite!L125 -> 0.484 | DS10: =Daily_Composite!L126 -> 0.024 | DT10: =Daily_Composite!L127 -> 0.04 | DU10: =Daily_Composite!L128 -> 0.418 | DV10: =Daily_Composite!L129 -> 0.39 | DW10: =Daily_Composite!L130 -> 0.466 | DX10: =Daily_Composite!L131 -> -0.042 | DY10: =Daily_Composite!L132 -> 0.241 | DZ10: =Daily_Composite!L133 -> 0.03 | EA10: =Daily_Composite!L134 -> 0.044 | EB10: =Daily_Composite!L135 -> 0.458 | EC10: =Daily_Composite!L136 -> 0.321 | ED10: =Daily_Composite!L137 -> 0.323 | EE10: =Daily_Composite!L138 -> 0.308 | EF10: =Daily_Composite!L139 -> 0.314 | EG10: =Daily_Composite!L140 -> 0.417 | EH10: =Daily_Composite!L141 -> 0.125 | EI10: =Daily_Composite!L142 -> 0.124 | EJ10: =Daily_Composite!L143 -> 0.04 | EK10: =Daily_Composite!L144 -> -0.399 | EL10: =Daily_Composite!L145 -> 0.023 | EM10: =Daily_Composite!L146 -> 0.022 | EN10: =Daily_Composite!L147 -> -0.066 | EO10: =Daily_Composite!L148 -> -0.09 | EP10: =Daily_Composite!L149 -> 0.101 | EQ10: =Daily_Composite!L150 -> 0.09 | ER10: =Daily_Composite!L151 -> -0.013 | ES10: =Daily_Composite!L152 -> -0.021 | ET10: =Daily_Composite!L153 -> -0.4 | EU10: =Daily_Composite!L154 -> -0.07 | EV10: =Daily_Composite!L155 -> -0.074 | EW10: =Daily_Composite!L156 -> 0.106 | EX10: =Daily_Composite!L157 -> 0.289 | EY10: =Daily_Composite!L158 -> 0.309 | EZ10: =Daily_Composite!L159 -> 0.294 | FA10: =Daily_Composite!L160 -> 0.307 | FB10: =Daily_Composite!L161 -> 0.326 | FC10: =Daily_Composite!L162 -> 0.522 | FD10: =Daily_Composite!L163 -> 0.059 | FE10: =Daily_Composite!L164 -> 0.201 | FF10: =Daily_Composite!L165 -> 0.233 | FG10: =Daily_Composite!L166 -> 0.022 | FH10: =Daily_Composite!L167 -> 0.052 | FI10: =Daily_Composite!L168 -> 0.033 | FJ10: =Daily_Composite!L169 -> 0.067 | FK10: =Daily_Composite!L170 -> 0.07 | FL10: =Daily_Composite!L171 -> 0.074 | FM10: =Daily_Composite!L172 -> 0.15 | FN10: =Daily_Composite!L173 -> 0.008 | FO10: =Daily_Composite!L174 -> -0.017 | FP10: =Daily_Composite!L175 -> 0.069 | FQ10: =Daily_Composite!L176 -> -0.032 | FR10: =Daily_Composite!L177 -> -0.096 | FS10: =Daily_Composite!L178 -> -0.121 | FT10: =Daily_Composite!L179 -> -0.126 | FU10: =Daily_Composite!L180 -> -0.595 | FV10: =Daily_Composite!L181 -> -0.177 | FW10: =Daily_Composite!L182 -> -0.201 | FX10: =Daily_Composite!L183 -> -0.451 | FY10: =Daily_Composite!L184 -> -0.34 | FZ10: =Daily_Composite!L185 -> -0.212 | GA10: =Daily_Composite!L186 -> -0.236 | GB10: =Daily_Composite!L187 -> -0.224 | GC10: =Daily_Composite!L188 -> -0.225 | GD10: =Daily_Composite!L189 -> 0.061 | GE10: =Daily_Composite!L190 -> 0.262 | GF10: =Daily_Composite!L191 -> 0.148 | GG10: =Daily_Composite!L192 -> 0.142 | GH10: =Daily_Composite!L193 -> -0.367 | GI10: =Daily_Composite!L194 -> -0.38 | GJ10: =Daily_Composite!L195 -> 0.231 | GK10: =Daily_Composite!L196 -> 0.041 | GL10: =Daily_Composite!L197 -> 0.112 | GM10: =Daily_Composite!L198 -> 0.09 | GN10: =Daily_Composite!L199 -> -0.192 | GO10: =Daily_Composite!L200 -> -0.15 | GP10: =Daily_Composite!L201 -> -0.129 | GQ10: =Daily_Composite!L202 -> -0.236 | GR10: =Daily_Composite!L203 -> -0.122 | GS10: =Daily_Composite!L204 -> 0.036 | GT10: =Daily_Composite!L205 -> 0.03 | GU10: =Daily_Composite!L206 -> -0.243 | GV10: =Daily_Composite!L207 -> -0.22 | GW10: =Daily_Composite!L208 -> -0.024 | GX10: =Daily_Composite!L209 -> -0.026 | GY10: =Daily_Composite!L210 -> 0.072 | GZ10: =Daily_Composite!L211 -> -0.109 | HA10: =Daily_Composite!L212 -> -0.084 | HB10: =Daily_Composite!L213 -> 0.007 | HC10: =Daily_Composite!L214 -> -0.036 | HD10: =Daily_Composite!L215 -> -0.041 | HE10: =Daily_Composite!L216 -> -0.046 | HF10: =Daily_Composite!L217 -> -0.052 | HG10: =Daily_Composite!L218 -> 0.027 | HH10: =Daily_Composite!L219 -> -0.008 | HI10: =Daily_Composite!L220 -> -0.412 | HJ10: =Daily_Composite!L221 -> -0.427 | HK10: =Daily_Composite!L222 -> -0.147 | HL10: =Daily_Composite!L223 -> -0.004 | HM10: =Daily_Composite!L224 -> -0.448 | HN10: =Daily_Composite!L225 -> -0.153 | HO10: =Daily_Composite!L226 -> -0.155 | HP10: =Daily_Composite!L227 -> -0.155 | HQ10: =Daily_Composite!L228 -> -0.155 | HR10: =Daily_Composite!L229 -> -0.164 | HS10: =Daily_Composite!L230 -> -0.217 | HT10: =Daily_Composite!L231 -> -0.19 | HU10: =Daily_Composite!L232 -> -0.155 | HV10: =Daily_Composite!L233 -> -0.2 | HW10: =Daily_Composite!L234 -> -0.2 | HX10: =Daily_Composite!L235 -> -0.285 | HY10: =Daily_Composite!L236 -> -0.267 | HZ10: =Daily_Composite!L237 -> -0.248 | IA10: =Daily_Composite!L238 -> -0.166 | IB10: =Daily_Composite!L239 -> -0.197 | IC10: =Daily_Composite!L240 -> -0.261 | ID10: =Daily_Composite!L241 -> -0.141 | IE10: =Daily_Composite!L242 -> -0.15 | IF10: =Daily_Composite!L243 -> -0.2 | IG10: =Daily_Composite!L244 -> -0.2 | IH10: =Daily_Composite!L245 -> 0.225 | II10: =Daily_Composite!L246 -> -0.166 | IJ10: =Daily_Composite!L247 -> -0.18 | IK10: =Daily_Composite!L248 -> -0.178 | IL10: =Daily_Composite!L249 -> -0.182 | IM10: =Daily_Composite!L250 -> -0.076 | IN10: =Daily_Composite!L251 -> 0.158 | IO10: =Daily_Composite!L252 -> -0.162 | IP10: =Daily_Composite!L253 -> -0.18 | IQ10: =Daily_Composite!L254 -> 0.161 | IR10: =Daily_Composite!L255 -> -0.18 | IS10: =Daily_Composite!L256 -> -0.061 | IT10: =Daily_Composite!L257 -> -0.07 | IU10: =Daily_Composite!L258 -> -0.038 | IV10: =Daily_Composite!L259 -> -0.038 | IW10: =Daily_Composite!L260 -> -0.004 | IX10: =Daily_Composite!L261 -> -0.141 | IY10: =Daily_Composite!L262 -> -0.49 | IZ10: =Daily_Composite!L263 -> -0.036 | JA10: =Daily_Composite!L264 -> -0.038 | JB10: =Daily_Composite!L265 -> -0.257 | JC10: =Daily_Composite!L266 -> -0.441 | JD10: =Daily_Composite!L267 -> -0.036 | JE10: =Daily_Composite!L268 -> -0.043 | JF10: =Daily_Composite!L269 -> -0.059 | JG10: =Daily_Composite!L270 -> -0.144 | JH10: =Daily_Composite!L271 -> -0.258 | JI10: =Daily_Composite!L272 -> -0.516 | JJ10: =Daily_Composite!L273 -> -0.134 | JK10: =Daily_Composite!L274 -> -0.128 | JL10: =Daily_Composite!L275 -> -0.1 | JM10: =Daily_Composite!L276 -> -0.103 | JN10: =Daily_Composite!L277 -> -0.107 | JO10: =Daily_Composite!L278 -> -0.111 | JP10: =Daily_Composite!L279 -> -0.146 | JQ10: =Daily_Composite!L280 -> -0.284 | JR10: =Daily_Composite!L281 -> -0.617 | JS10: =Daily_Composite!L282 -> -0.131 | JT10: =Daily_Composite!L283 -> -0.148 | JU10: =Daily_Composite!L284 -> -0.144 | JV10: =Daily_Composite!L285 -> -0.14 | JW10: =Daily_Composite!L286 -> -0.134 | JX10: =Daily_Composite!L287 -> -0.129 | JY10: =Daily_Composite!L288 -> -0.165 | JZ10: =Daily_Composite!L289 -> 0.017 | KA10: =Daily_Composite!L290 -> -0.356 | KB10: =Daily_Composite!L291 -> -0.354 | KC10: =Daily_Composite!L292 -> -0.557 | KD10: =Daily_Composite!L293 -> -0.553 | KE10: =Daily_Composite!L294 -> -0.35 | KF10: =Daily_Composite!L295 -> -0.348 | KG10: =Daily_Composite!L296 -> -0.328 | KH10: =Daily_Composite!L297 -> -0.345 | KI10: =Daily_Composite!L298 -> -0.238 | KJ10: =Daily_Composite!L299 -> -0.225 | KK10: =Daily_Composite!L300 -> -0.307 | KL10: =Daily_Composite!L301 -> -0.305 | KM10: =Daily_Composite!L302 -> -0.181 | KN10: =Daily_Composite!L303 -> -0.135 | KO10: =Daily_Composite!L304 -> -0.168 | KP10: =Daily_Composite!L305 -> -0.465 | KQ10: =Daily_Composite!L306 -> -0.296 | KR10: =Daily_Composite!L307 -> -0.217 | KS10: =Daily_Composite!L308 -> -0.53 | KT10: =Daily_Composite!L309 -> -0.318 | KU10: =Daily_Composite!L310 -> -0.275 | KV10: =Daily_Composite!L311 -> -0.207 | KW10: =Daily_Composite!L312 -> -0.206 | KX10: =Daily_Composite!L313 -> -0.202 | KY10: =Daily_Composite!L314 -> -0.198 | KZ10: =Daily_Composite!L315 -> -0.194 | LA10: =Daily_Composite!L316 -> -0.189 | LB10: =Daily_Composite!L317 -> -0.115 | LC10: =Daily_Composite!L318 -> -0.152 | LD10: =Daily_Composite!L319 -> -0.488 | LE10: =Daily_Composite!L320 -> -0.482 | LF10: =Daily_Composite!L321 -> -0.473 | LG10: =Daily_Composite!L322 -> -0.13 | LH10: =Daily_Composite!L323 -> -0.127 | LI10: =Daily_Composite!L324 -> -0.163 | LJ10: =Daily_Composite!L325 -> -0.206 | LK10: =Daily_Composite!L326 -> -0.589 | LL10: =Daily_Composite!L327 -> 0.003 | LM10: =Daily_Composite!L328 -> 0.025 | LN10: =Daily_Composite!L329 -> -0.121 | LO10: =Daily_Composite!L330 -> -0.176 | LP10: =Daily_Composite!L331 -> -0.117 | LQ10: =Daily_Composite!L332 -> 0.282 | LR10: =Daily_Composite!L333 -> 0.292 | LS10: =Daily_Composite!L334 -> -0.093 | LT10: =Daily_Composite!L335 -> -0.259 | LU10: =Daily_Composite!L336 -> -0.59 | LV10: =Daily_Composite!L337 -> -0.112 | LW10: =Daily_Composite!L338 -> -0.335 | LX10: =Daily_Composite!L339 -> -0.428 | LY10: =Daily_Composite!L340 -> -0.42 | LZ10: =Daily_Composite!L341 -> -0.243 | MA10: =Daily_Composite!L342 -> -0.239 | MB10: =Daily_Composite!L343 -> -0.235 | MC10: =Daily_Composite!L344 -> -0.564 | MD10: =Daily_Composite!L345 -> -0.017 | ME10: =Daily_Composite!L346 -> 0.023 | MF10: =Daily_Composite!L347 -> -0.503 | MG10: =Daily_Composite!L348 -> -0.491 | MH10: =Daily_Composite!L349 -> -0.195 | MI10: =Daily_Composite!L350 -> -0.181 | MJ10: =Daily_Composite!L351 -> 0.021 | MK10: =Daily_Composite!L352 -> -0.056 | ML10: =Daily_Composite!L353 -> -0.056 | MM10: =Daily_Composite!L354 -> 0.022 | MN10: =Daily_Composite!L355 -> -0.045 | MO10: =Daily_Composite!L356 -> 0.099 | MP10: =Daily_Composite!L357 -> -0.013 | MQ10: =Daily_Composite!L358 -> -0.136 | MR10: =Daily_Composite!L359 -> -0.275 | MS10: =Daily_Composite!L360 -> -0.143 | MT10: =Daily_Composite!L361 -> 0.073 | MU10: =Daily_Composite!L362 -> -0.024 | MV10: =Daily_Composite!L363 -> -0.029 | MW10: =Daily_Composite!L364 -> -0.16 | MX10: =Daily_Composite!L365 -> -0.186 | MY10: =Daily_Composite!L366 -> -0.053 | MZ10: =Daily_Composite!L367 -> -0.212 | NA10: =Daily_Composite!L368 -> -0.128 | NB10: =Daily_Composite!L369 -> -0.04
A11: Cement | B11: =Daily_Composite!M5 -> 0.031 | C11: =Daily_Composite!M6 -> 0.006 | D11: =Daily_Composite!M7 -> 0.067 | E11: =Daily_Composite!M8 -> -0.027 | F11: =Daily_Composite!M9 -> 0.041 | G11: =Daily_Composite!M10 -> -0.311 | H11: =Daily_Composite!M11 -> -0.087 | I11: =Daily_Composite!M12 -> -0.037 | J11: =Daily_Composite!M13 -> -0.037 | K11: =Daily_Composite!M14 -> -0.067 | L11: =Daily_Composite!M15 -> -0.044 | M11: =Daily_Composite!M16 -> -0.138 | N11: =Daily_Composite!M17 -> -0.331 | O11: =Daily_Composite!M18 -> -0.017 | P11: =Daily_Composite!M19 -> 0.073 | Q11: =Daily_Composite!M20 -> -0.047 | R11: =Daily_Composite!M21 -> 0.402 | S11: =Daily_Composite!M22 -> 0.009 | T11: =Daily_Composite!M23 -> -0.065 | U11: =Daily_Composite!M24 -> -0.022 | V11: =Daily_Composite!M25 -> -0.016 | W11: =Daily_Composite!M26 -> -0.161 | X11: =Daily_Composite!M27 -> -0.421 | Y11: =Daily_Composite!M28 -> -0.275 | Z11: =Daily_Composite!M29 -> -0.404 | AA11: =Daily_Composite!M30 -> -0.035 | AB11: =Daily_Composite!M31 -> 0.122 | AC11: =Daily_Composite!M32 -> -0.202 | AD11: =Daily_Composite!M33 -> -0.122 | AE11: =Daily_Composite!M34 -> -0.101 | AF11: =Daily_Composite!M35 -> 0.355 | AG11: =Daily_Composite!M36 -> 0.295 | AH11: =Daily_Composite!M37 -> 0.073 | AI11: =Daily_Composite!M38 -> 0.075 | AJ11: =Daily_Composite!M39 -> 0.032 | AK11: =Daily_Composite!M40 -> -0.016 | AL11: =Daily_Composite!M41 -> -0.029 | AM11: =Daily_Composite!M42 -> 0.005 | AN11: =Daily_Composite!M43 -> 0.198 | AO11: =Daily_Composite!M44 -> -0.217 | AP11: =Daily_Composite!M45 -> 0.096 | AQ11: =Daily_Composite!M46 -> 0.101 | AR11: =Daily_Composite!M47 -> -0.406 | AS11: =Daily_Composite!M48 -> 0.094 | AT11: =Daily_Composite!M49 -> -0.056 | AU11: =Daily_Composite!M50 -> -0.05 | AV11: =Daily_Composite!M51 -> -0.146 | AW11: =Daily_Composite!M52 -> -0.181 | AX11: =Daily_Composite!M53 -> 0.091 | AY11: =Daily_Composite!M54 -> -0.295 | AZ11: =Daily_Composite!M55 -> -0.348 | BA11: =Daily_Composite!M56 -> -0.234 | BB11: =Daily_Composite!M57 -> -0.488 | BC11: =Daily_Composite!M58 -> -0.208 | BD11: =Daily_Composite!M59 -> 0.127 | BE11: =Daily_Composite!M60 -> -0.138 | BF11: =Daily_Composite!M61 -> -0.075 | BG11: =Daily_Composite!M62 -> 0.298 | BH11: =Daily_Composite!M63 -> -0.166 | BI11: =Daily_Composite!M64 -> -0.184 | BJ11: =Daily_Composite!M65 -> -0.488 | BK11: =Daily_Composite!M66 -> -0.222 | BL11: =Daily_Composite!M67 -> -0.162 | BM11: =Daily_Composite!M68 -> -0.185 | BN11: =Daily_Composite!M69 -> -0.242 | BO11: =Daily_Composite!M70 -> -0.264 | BP11: =Daily_Composite!M71 -> -0.116 | BQ11: =Daily_Composite!M72 -> -0.214 | BR11: =Daily_Composite!M73 -> -0.211 | BS11: =Daily_Composite!M74 -> -0.493 | BT11: =Daily_Composite!M75 -> -0.152 | BU11: =Daily_Composite!M76 -> -0.198 | BV11: =Daily_Composite!M77 -> -0.23 | BW11: =Daily_Composite!M78 -> -0.187 | BX11: =Daily_Composite!M79 -> -0.14 | BY11: =Daily_Composite!M80 -> -0.023 | BZ11: =Daily_Composite!M81 -> 0.309 | CA11: =Daily_Composite!M82 -> 0.14 | CB11: =Daily_Composite!M83 -> -0.199 | CC11: =Daily_Composite!M84 -> -0.536 | CD11: =Daily_Composite!M85 -> -0.265 | CE11: =Daily_Composite!M86 -> 0.144 | CF11: =Daily_Composite!M87 -> 0.154 | CG11: =Daily_Composite!M88 -> -0.185 | CH11: =Daily_Composite!M89 -> -0.221 | CI11: =Daily_Composite!M90 -> 0.079 | CJ11: =Daily_Composite!M91 -> -0.113 | CK11: =Daily_Composite!M92 -> -0.484 | CL11: =Daily_Composite!M93 -> -0.401 | CM11: =Daily_Composite!M94 -> -0.458 | CN11: =Daily_Composite!M95 -> -0.516 | CO11: =Daily_Composite!M96 -> -0.521 | CP11: =Daily_Composite!M97 -> -0.536 | CQ11: =Daily_Composite!M98 -> -0.76 | CR11: =Daily_Composite!M99 -> -0.772 | CS11: =Daily_Composite!M100 -> -0.549 | CT11: =Daily_Composite!M101 -> -0.76 | CU11: =Daily_Composite!M102 -> -0.608 | CV11: =Daily_Composite!M103 -> -0.499 | CW11: =Daily_Composite!M104 -> -0.477 | CX11: =Daily_Composite!M105 -> -0.481 | CY11: =Daily_Composite!M106 -> -0.766 | CZ11: =Daily_Composite!M107 -> -0.767 | DA11: =Daily_Composite!M108 -> -0.721 | DB11: =Daily_Composite!M109 -> -0.777 | DC11: =Daily_Composite!M110 -> -0.729 | DD11: =Daily_Composite!M111 -> -0.767 | DE11: =Daily_Composite!M112 -> -0.338 | DF11: =Daily_Composite!M113 -> -0.396 | DG11: =Daily_Composite!M114 -> -0.488 | DH11: =Daily_Composite!M115 -> -0.484 | DI11: =Daily_Composite!M116 -> -0.466 | DJ11: =Daily_Composite!M117 -> -0.605 | DK11: =Daily_Composite!M118 -> -0.684 | DL11: =Daily_Composite!M119 -> -0.268 | DM11: =Daily_Composite!M120 -> -0.642 | DN11: =Daily_Composite!M121 -> -0.134 | DO11: =Daily_Composite!M122 -> -0.081 | DP11: =Daily_Composite!M123 -> -0.076 | DQ11: =Daily_Composite!M124 -> -0.06 | DR11: =Daily_Composite!M125 -> 0.243 | DS11: =Daily_Composite!M126 -> 0.464 | DT11: =Daily_Composite!M127 -> 0.079 | DU11: =Daily_Composite!M128 -> 0.131 | DV11: =Daily_Composite!M129 -> -0.239 | DW11: =Daily_Composite!M130 -> 0.357 | DX11: =Daily_Composite!M131 -> 0.062 | DY11: =Daily_Composite!M132 -> -0.078 | DZ11: =Daily_Composite!M133 -> -0.023 | EA11: =Daily_Composite!M134 -> -0.035 | EB11: =Daily_Composite!M135 -> 0.23 | EC11: =Daily_Composite!M136 -> 0.244 | ED11: =Daily_Composite!M137 -> -0.257 | EE11: =Daily_Composite!M138 -> -0.554 | EF11: =Daily_Composite!M139 -> -0.245 | EG11: =Daily_Composite!M140 -> 0.094 | EH11: =Daily_Composite!M141 -> -0.077 | EI11: =Daily_Composite!M142 -> -0.057 | EJ11: =Daily_Composite!M143 -> -0.148 | EK11: =Daily_Composite!M144 -> -0.555 | EL11: =Daily_Composite!M145 -> -0.355 | EM11: =Daily_Composite!M146 -> -0.211 | EN11: =Daily_Composite!M147 -> -0.614 | EO11: =Daily_Composite!M148 -> -0.232 | EP11: =Daily_Composite!M149 -> -0.184 | EQ11: =Daily_Composite!M150 -> -0.195 | ER11: =Daily_Composite!M151 -> -0.326 | ES11: =Daily_Composite!M152 -> -0.338 | ET11: =Daily_Composite!M153 -> -0.654 | EU11: =Daily_Composite!M154 -> -0.65 | EV11: =Daily_Composite!M155 -> -0.387 | EW11: =Daily_Composite!M156 -> -0.576 | EX11: =Daily_Composite!M157 -> -0.309 | EY11: =Daily_Composite!M158 -> -0.166 | EZ11: =Daily_Composite!M159 -> -0.157 | FA11: =Daily_Composite!M160 -> -0.088 | FB11: =Daily_Composite!M161 -> -0.456 | FC11: =Daily_Composite!M162 -> -0.178 | FD11: =Daily_Composite!M163 -> -0.509 | FE11: =Daily_Composite!M164 -> -0.555 | FF11: =Daily_Composite!M165 -> -0.114 | FG11: =Daily_Composite!M166 -> -0.547 | FH11: =Daily_Composite!M167 -> -0.058 | FI11: =Daily_Composite!M168 -> -0.29 | FJ11: =Daily_Composite!M169 -> -0.265 | FK11: =Daily_Composite!M170 -> -0.223 | FL11: =Daily_Composite!M171 -> -0.269 | FM11: =Daily_Composite!M172 -> -0.171 | FN11: =Daily_Composite!M173 -> -0.019 | FO11: =Daily_Composite!M174 -> -0.364 | FP11: =Daily_Composite!M175 -> 0.066 | FQ11: =Daily_Composite!M176 -> 0.06 | FR11: =Daily_Composite!M177 -> 0.059 | FS11: =Daily_Composite!M178 -> -0.054 | FT11: =Daily_Composite!M179 -> -0.065 | FU11: =Daily_Composite!M180 -> -0.569 | FV11: =Daily_Composite!M181 -> -0.519 | FW11: =Daily_Composite!M182 -> -0.218 | FX11: =Daily_Composite!M183 -> -0.326 | FY11: =Daily_Composite!M184 -> -0.346 | FZ11: =Daily_Composite!M185 -> -0.213 | GA11: =Daily_Composite!M186 -> -0.214 | GB11: =Daily_Composite!M187 -> -0.226 | GC11: =Daily_Composite!M188 -> -0.565 | GD11: =Daily_Composite!M189 -> -0.589 | GE11: =Daily_Composite!M190 -> -0.131 | GF11: =Daily_Composite!M191 -> -0.597 | GG11: =Daily_Composite!M192 -> -0.375 | GH11: =Daily_Composite!M193 -> -0.489 | GI11: =Daily_Composite!M194 -> -0.22 | GJ11: =Daily_Composite!M195 -> -0.092 | GK11: =Daily_Composite!M196 -> -0.244 | GL11: =Daily_Composite!M197 -> -0.305 | GM11: =Daily_Composite!M198 -> -0.389 | GN11: =Daily_Composite!M199 -> -0.489 | GO11: =Daily_Composite!M200 -> -0.658 | GP11: =Daily_Composite!M201 -> -0.26 | GQ11: =Daily_Composite!M202 -> -0.62 | GR11: =Daily_Composite!M203 -> -0.248 | GS11: =Daily_Composite!M204 -> -0.169 | GT11: =Daily_Composite!M205 -> -0.175 | GU11: =Daily_Composite!M206 -> -0.274 | GV11: =Daily_Composite!M207 -> -0.448 | GW11: =Daily_Composite!M208 -> -0.49 | GX11: =Daily_Composite!M209 -> -0.197 | GY11: =Daily_Composite!M210 -> -0.221 | GZ11: =Daily_Composite!M211 -> -0.467 | HA11: =Daily_Composite!M212 -> -0.465 | HB11: =Daily_Composite!M213 -> -0.221 | HC11: =Daily_Composite!M214 -> -0.251 | HD11: =Daily_Composite!M215 -> -0.644 | HE11: =Daily_Composite!M216 -> -0.658 | HF11: =Daily_Composite!M217 -> -0.666 | HG11: =Daily_Composite!M218 -> -0.726 | HH11: =Daily_Composite!M219 -> -0.568 | HI11: =Daily_Composite!M220 -> -0.713 | HJ11: =Daily_Composite!M221 -> -0.716 | HK11: =Daily_Composite!M222 -> -0.282 | HL11: =Daily_Composite!M223 -> -0.275 | HM11: =Daily_Composite!M224 -> -0.511 | HN11: =Daily_Composite!M225 -> -0.365 | HO11: =Daily_Composite!M226 -> -0.357 | HP11: =Daily_Composite!M227 -> -0.641 | HQ11: =Daily_Composite!M228 -> -0.209 | HR11: =Daily_Composite!M229 -> -0.383 | HS11: =Daily_Composite!M230 -> -0.219 | HT11: =Daily_Composite!M231 -> -0.096 | HU11: =Daily_Composite!M232 -> -0.065 | HV11: =Daily_Composite!M233 -> -0.188 | HW11: =Daily_Composite!M234 -> -0.188 | HX11: =Daily_Composite!M235 -> -0.327 | HY11: =Daily_Composite!M236 -> -0.476 | HZ11: =Daily_Composite!M237 -> -0.275 | IA11: =Daily_Composite!M238 -> -0.098 | IB11: =Daily_Composite!M239 -> -0.153 | IC11: =Daily_Composite!M240 -> -0.213 | ID11: =Daily_Composite!M241 -> -0.11 | IE11: =Daily_Composite!M242 -> -0.387 | IF11: =Daily_Composite!M243 -> -0.442 | IG11: =Daily_Composite!M244 -> -0.467 | IH11: =Daily_Composite!M245 -> 0.109 | II11: =Daily_Composite!M246 -> -0.135 | IJ11: =Daily_Composite!M247 -> -0.023 | IK11: =Daily_Composite!M248 -> 0.062 | IL11: =Daily_Composite!M249 -> -0.057 | IM11: =Daily_Composite!M250 -> 0.065 | IN11: =Daily_Composite!M251 -> 0.197 | IO11: =Daily_Composite!M252 -> 0.082 | IP11: =Daily_Composite!M253 -> -0.082 | IQ11: =Daily_Composite!M254 -> 0.141 | IR11: =Daily_Composite!M255 -> -0.15 | IS11: =Daily_Composite!M256 -> -0.654 | IT11: =Daily_Composite!M257 -> -0.273 | IU11: =Daily_Composite!M258 -> -0.249 | IV11: =Daily_Composite!M259 -> -0.265 | IW11: =Daily_Composite!M260 -> -0.12 | IX11: =Daily_Composite!M261 -> -0.158 | IY11: =Daily_Composite!M262 -> -0.595 | IZ11: =Daily_Composite!M263 -> -0.152 | JA11: =Daily_Composite!M264 -> -0.281 | JB11: =Daily_Composite!M265 -> -0.502 | JC11: =Daily_Composite!M266 -> -0.528 | JD11: =Daily_Composite!M267 -> -0.313 | JE11: =Daily_Composite!M268 -> -0.293 | JF11: =Daily_Composite!M269 -> -0.31 | JG11: =Daily_Composite!M270 -> -0.639 | JH11: =Daily_Composite!M271 -> -0.682 | JI11: =Daily_Composite!M272 -> -0.721 | JJ11: =Daily_Composite!M273 -> -0.601 | JK11: =Daily_Composite!M274 -> -0.608 | JL11: =Daily_Composite!M275 -> -0.49 | JM11: =Daily_Composite!M276 -> -0.183 | JN11: =Daily_Composite!M277 -> -0.266 | JO11: =Daily_Composite!M278 -> -0.229 | JP11: =Daily_Composite!M279 -> -0.34 | JQ11: =Daily_Composite!M280 -> -0.239 | JR11: =Daily_Composite!M281 -> -0.572 | JS11: =Daily_Composite!M282 -> 0.107 | JT11: =Daily_Composite!M283 -> -0.242 | JU11: =Daily_Composite!M284 -> -0.578 | JV11: =Daily_Composite!M285 -> -0.264 | JW11: =Daily_Composite!M286 -> -0.227 | JX11: =Daily_Composite!M287 -> -0.243 | JY11: =Daily_Composite!M288 -> -0.116 | JZ11: =Daily_Composite!M289 -> -0.022 | KA11: =Daily_Composite!M290 -> 0.103 | KB11: =Daily_Composite!M291 -> -0.265 | KC11: =Daily_Composite!M292 -> -0.594 | KD11: =Daily_Composite!M293 -> -0.332 | KE11: =Daily_Composite!M294 -> -0.265 | KF11: =Daily_Composite!M295 -> -0.195 | KG11: =Daily_Composite!M296 -> -0.098 | KH11: =Daily_Composite!M297 -> -0.509 | KI11: =Daily_Composite!M298 -> -0.574 | KJ11: =Daily_Composite!M299 -> -0.572 | KK11: =Daily_Composite!M300 -> -0.224 | KL11: =Daily_Composite!M301 -> -0.528 | KM11: =Daily_Composite!M302 -> -0.326 | KN11: =Daily_Composite!M303 -> -0.212 | KO11: =Daily_Composite!M304 -> -0.282 | KP11: =Daily_Composite!M305 -> -0.384 | KQ11: =Daily_Composite!M306 -> -0.262 | KR11: =Daily_Composite!M307 -> -0.425 | KS11: =Daily_Composite!M308 -> -0.562 | KT11: =Daily_Composite!M309 -> -0.019 | KU11: =Daily_Composite!M310 -> -0.234 | KV11: =Daily_Composite!M311 -> -0.653 | KW11: =Daily_Composite!M312 -> -0.263 | KX11: =Daily_Composite!M313 -> -0.259 | KY11: =Daily_Composite!M314 -> -0.22 | KZ11: =Daily_Composite!M315 -> -0.242 | LA11: =Daily_Composite!M316 -> -0.237 | LB11: =Daily_Composite!M317 -> -0.212 | LC11: =Daily_Composite!M318 -> 0.086 | LD11: =Daily_Composite!M319 -> -0.383 | LE11: =Daily_Composite!M320 -> -0.561 | LF11: =Daily_Composite!M321 -> -0.099 | LG11: =Daily_Composite!M322 -> 0.062 | LH11: =Daily_Composite!M323 -> 0.076 | LI11: =Daily_Composite!M324 -> -0.343 | LJ11: =Daily_Composite!M325 -> -0.35 | LK11: =Daily_Composite!M326 -> -0.569 | LL11: =Daily_Composite!M327 -> 0.28 | LM11: =Daily_Composite!M328 -> -0.076 | LN11: =Daily_Composite!M329 -> 0.095 | LO11: =Daily_Composite!M330 -> -0.341 | LP11: =Daily_Composite!M331 -> 0.121 | LQ11: =Daily_Composite!M332 -> 0.251 | LR11: =Daily_Composite!M333 -> 0.266 | LS11: =Daily_Composite!M334 -> 0.064 | LT11: =Daily_Composite!M335 -> 0.059 | LU11: =Daily_Composite!M336 -> -0.39 | LV11: =Daily_Composite!M337 -> 0.341 | LW11: =Daily_Composite!M338 -> 0.168 | LX11: =Daily_Composite!M339 -> -0.002 | LY11: =Daily_Composite!M340 -> 0.119 | LZ11: =Daily_Composite!M341 -> 0.145 | MA11: =Daily_Composite!M342 -> 0.093 | MB11: =Daily_Composite!M343 -> 0.104 | MC11: =Daily_Composite!M344 -> -0.455 | MD11: =Daily_Composite!M345 -> -0.013 | ME11: =Daily_Composite!M346 -> 0.133 | MF11: =Daily_Composite!M347 -> 0.35 | MG11: =Daily_Composite!M348 -> 0.048 | MH11: =Daily_Composite!M349 -> 0.186 | MI11: =Daily_Composite!M350 -> 0.254 | MJ11: =Daily_Composite!M351 -> 0.324 | MK11: =Daily_Composite!M352 -> 0.213 | ML11: =Daily_Composite!M353 -> 0.207 | MM11: =Daily_Composite!M354 -> 0.268 | MN11: =Daily_Composite!M355 -> 0.197 | MO11: =Daily_Composite!M356 -> 0.142 | MP11: =Daily_Composite!M357 -> 0.532 | MQ11: =Daily_Composite!M358 -> 0.027 | MR11: =Daily_Composite!M359 -> -0.015 | MS11: =Daily_Composite!M360 -> 0.057 | MT11: =Daily_Composite!M361 -> 0.098 | MU11: =Daily_Composite!M362 -> 0.07 | MV11: =Daily_Composite!M363 -> -0.132 | MW11: =Daily_Composite!M364 -> 0.011 | MX11: =Daily_Composite!M365 -> -0.112 | MY11: =Daily_Composite!M366 -> 0.36 | MZ11: =Daily_Composite!M367 -> -0.161 | NA11: =Daily_Composite!M368 -> -0.143 | NB11: =Daily_Composite!M369 -> -0.165
A12: Crude oil & gas | B12: =Daily_Composite!N5 -> 0.067 | C12: =Daily_Composite!N6 -> -0.135 | D12: =Daily_Composite!N7 -> -0.105 | E12: =Daily_Composite!N8 -> 0.057 | F12: =Daily_Composite!N9 -> -0.023 | G12: =Daily_Composite!N10 -> -0.305 | H12: =Daily_Composite!N11 -> -0.075 | I12: =Daily_Composite!N12 -> -0.5 | J12: =Daily_Composite!N13 -> -0.116 | K12: =Daily_Composite!N14 -> -0.183 | L12: =Daily_Composite!N15 -> -0.551 | M12: =Daily_Composite!N16 -> -0.316 | N12: =Daily_Composite!N17 -> -0.086 | O12: =Daily_Composite!N18 -> -0.068 | P12: =Daily_Composite!N19 -> -0.111 | Q12: =Daily_Composite!N20 -> -0.25 | R12: =Daily_Composite!N21 -> 0.305 | S12: =Daily_Composite!N22 -> -0.411 | T12: =Daily_Composite!N23 -> -0.102 | U12: =Daily_Composite!N24 -> -0.111 | V12: =Daily_Composite!N25 -> -0.101 | W12: =Daily_Composite!N26 -> -0.268 | X12: =Daily_Composite!N27 -> -0.269 | Y12: =Daily_Composite!N28 -> -0.275 | Z12: =Daily_Composite!N29 -> -0.431 | AA12: =Daily_Composite!N30 -> -0.188 | AB12: =Daily_Composite!N31 -> -0.379 | AC12: =Daily_Composite!N32 -> -0.225 | AD12: =Daily_Composite!N33 -> -0.175 | AE12: =Daily_Composite!N34 -> -0.154 | AF12: =Daily_Composite!N35 -> 0.212 | AG12: =Daily_Composite!N36 -> -0.056 | AH12: =Daily_Composite!N37 -> -0.134 | AI12: =Daily_Composite!N38 -> -0.243 | AJ12: =Daily_Composite!N39 -> 0.099 | AK12: =Daily_Composite!N40 -> -0.036 | AL12: =Daily_Composite!N41 -> -0.065 | AM12: =Daily_Composite!N42 -> -0.492 | AN12: =Daily_Composite!N43 -> 0.177 | AO12: =Daily_Composite!N44 -> -0.187 | AP12: =Daily_Composite!N45 -> -0.107 | AQ12: =Daily_Composite!N46 -> 0.174 | AR12: =Daily_Composite!N47 -> -0.411 | AS12: =Daily_Composite!N48 -> 0.109 | AT12: =Daily_Composite!N49 -> -0.459 | AU12: =Daily_Composite!N50 -> -0.123 | AV12: =Daily_Composite!N51 -> -0.317 | AW12: =Daily_Composite!N52 -> -0.522 | AX12: =Daily_Composite!N53 -> -0.148 | AY12: =Daily_Composite!N54 -> -0.363 | AZ12: =Daily_Composite!N55 -> -0.39 | BA12: =Daily_Composite!N56 -> -0.335 | BB12: =Daily_Composite!N57 -> -0.566 | BC12: =Daily_Composite!N58 -> -0.15 | BD12: =Daily_Composite!N59 -> 0.185 | BE12: =Daily_Composite!N60 -> -0.212 | BF12: =Daily_Composite!N61 -> -0.562 | BG12: =Daily_Composite!N62 -> 0.154 | BH12: =Daily_Composite!N63 -> -0.272 | BI12: =Daily_Composite!N64 -> -0.256 | BJ12: =Daily_Composite!N65 -> -0.605 | BK12: =Daily_Composite!N66 -> -0.528 | BL12: =Daily_Composite!N67 -> -0.038 | BM12: =Daily_Composite!N68 -> -0.246 | BN12: =Daily_Composite!N69 -> -0.354 | BO12: =Daily_Composite!N70 -> -0.606 | BP12: =Daily_Composite!N71 -> -0.247 | BQ12: =Daily_Composite!N72 -> -0.32 | BR12: =Daily_Composite!N73 -> -0.317 | BS12: =Daily_Composite!N74 -> -0.604 | BT12: =Daily_Composite!N75 -> -0.292 | BU12: =Daily_Composite!N76 -> -0.441 | BV12: =Daily_Composite!N77 -> -0.314 | BW12: =Daily_Composite!N78 -> -0.269 | BX12: =Daily_Composite!N79 -> -0.512 | BY12: =Daily_Composite!N80 -> -0.492 | BZ12: =Daily_Composite!N81 -> 0.251 | CA12: =Daily_Composite!N82 -> -0.213 | CB12: =Daily_Composite!N83 -> -0.319 | CC12: =Daily_Composite!N84 -> -0.663 | CD12: =Daily_Composite!N85 -> -0.254 | CE12: =Daily_Composite!N86 -> 0.08 | CF12: =Daily_Composite!N87 -> 0.076 | CG12: =Daily_Composite!N88 -> -0.462 | CH12: =Daily_Composite!N89 -> -0.692 | CI12: =Daily_Composite!N90 -> -0.013 | CJ12: =Daily_Composite!N91 -> -0.345 | CK12: =Daily_Composite!N92 -> -0.46 | CL12: =Daily_Composite!N93 -> -0.597 | CM12: =Daily_Composite!N94 -> 0.079 | CN12: =Daily_Composite!N95 -> -0.597 | CO12: =Daily_Composite!N96 -> -0.555 | CP12: =Daily_Composite!N97 -> -0.786 | CQ12: =Daily_Composite!N98 -> -0.803 | CR12: =Daily_Composite!N99 -> -0.715 | CS12: =Daily_Composite!N100 -> -0.628 | CT12: =Daily_Composite!N101 -> -0.795 | CU12: =Daily_Composite!N102 -> -0.541 | CV12: =Daily_Composite!N103 -> -0.824 | CW12: =Daily_Composite!N104 -> -0.822 | CX12: =Daily_Composite!N105 -> -0.584 | CY12: =Daily_Composite!N106 -> -0.811 | CZ12: =Daily_Composite!N107 -> -0.675 | DA12: =Daily_Composite!N108 -> -0.817 | DB12: =Daily_Composite!N109 -> -0.82 | DC12: =Daily_Composite!N110 -> -0.827 | DD12: =Daily_Composite!N111 -> -0.829 | DE12: =Daily_Composite!N112 -> -0.502 | DF12: =Daily_Composite!N113 -> -0.826 | DG12: =Daily_Composite!N114 -> -0.741 | DH12: =Daily_Composite!N115 -> -0.78 | DI12: =Daily_Composite!N116 -> -0.86 | DJ12: =Daily_Composite!N117 -> -0.791 | DK12: =Daily_Composite!N118 -> -0.586 | DL12: =Daily_Composite!N119 -> -0.62 | DM12: =Daily_Composite!N120 -> -0.744 | DN12: =Daily_Composite!N121 -> -0.563 | DO12: =Daily_Composite!N122 -> -0.467 | DP12: =Daily_Composite!N123 -> -0.41 | DQ12: =Daily_Composite!N124 -> -0.59 | DR12: =Daily_Composite!N125 -> -0.042 | DS12: =Daily_Composite!N126 -> -0.223 | DT12: =Daily_Composite!N127 -> -0.251 | DU12: =Daily_Composite!N128 -> -0.147 | DV12: =Daily_Composite!N129 -> -0.468 | DW12: =Daily_Composite!N130 -> -0.087 | DX12: =Daily_Composite!N131 -> 0.213 | DY12: =Daily_Composite!N132 -> -0.191 | DZ12: =Daily_Composite!N133 -> -0.154 | EA12: =Daily_Composite!N134 -> -0.43 | EB12: =Daily_Composite!N135 -> 0.16 | EC12: =Daily_Composite!N136 -> -0.258 | ED12: =Daily_Composite!N137 -> -0.274 | EE12: =Daily_Composite!N138 -> -0.59 | EF12: =Daily_Composite!N139 -> -0.407 | EG12: =Daily_Composite!N140 -> 0.216 | EH12: =Daily_Composite!N141 -> -0.177 | EI12: =Daily_Composite!N142 -> -0.159 | EJ12: =Daily_Composite!N143 -> -0.683 | EK12: =Daily_Composite!N144 -> -0.686 | EL12: =Daily_Composite!N145 -> -0.334 | EM12: =Daily_Composite!N146 -> -0.289 | EN12: =Daily_Composite!N147 -> -0.629 | EO12: =Daily_Composite!N148 -> -0.382 | EP12: =Daily_Composite!N149 -> -0.027 | EQ12: =Daily_Composite!N150 -> -0.235 | ER12: =Daily_Composite!N151 -> -0.375 | ES12: =Daily_Composite!N152 -> -0.636 | ET12: =Daily_Composite!N153 -> -0.669 | EU12: =Daily_Composite!N154 -> -0.476 | EV12: =Daily_Composite!N155 -> -0.431 | EW12: =Daily_Composite!N156 -> -0.554 | EX12: =Daily_Composite!N157 -> -0.172 | EY12: =Daily_Composite!N158 -> -0.486 | EZ12: =Daily_Composite!N159 -> -0.152 | FA12: =Daily_Composite!N160 -> -0.09 | FB12: =Daily_Composite!N161 -> -0.251 | FC12: =Daily_Composite!N162 -> 0.03 | FD12: =Daily_Composite!N163 -> -0.547 | FE12: =Daily_Composite!N164 -> -0.499 | FF12: =Daily_Composite!N165 -> -0.019 | FG12: =Daily_Composite!N166 -> -0.576 | FH12: =Daily_Composite!N167 -> -0.038 | FI12: =Daily_Composite!N168 -> -0.534 | FJ12: =Daily_Composite!N169 -> -0.164 | FK12: =Daily_Composite!N170 -> -0.433 | FL12: =Daily_Composite!N171 -> -0.668 | FM12: =Daily_Composite!N172 -> -0.105 | FN12: =Daily_Composite!N173 -> -0.12 | FO12: =Daily_Composite!N174 -> -0.403 | FP12: =Daily_Composite!N175 -> -0.006 | FQ12: =Daily_Composite!N176 -> -0.095 | FR12: =Daily_Composite!N177 -> -0.046 | FS12: =Daily_Composite!N178 -> -0.19 | FT12: =Daily_Composite!N179 -> -0.707 | FU12: =Daily_Composite!N180 -> -0.699 | FV12: =Daily_Composite!N181 -> -0.158 | FW12: =Daily_Composite!N182 -> -0.195 | FX12: =Daily_Composite!N183 -> -0.456 | FY12: =Daily_Composite!N184 -> -0.503 | FZ12: =Daily_Composite!N185 -> -0.518 | GA12: =Daily_Composite!N186 -> -0.231 | GB12: =Daily_Composite!N187 -> -0.26 | GC12: =Daily_Composite!N188 -> -0.645 | GD12: =Daily_Composite!N189 -> -0.709 | GE12: =Daily_Composite!N190 -> -0.293 | GF12: =Daily_Composite!N191 -> -0.564 | GG12: =Daily_Composite!N192 -> -0.53 | GH12: =Daily_Composite!N193 -> -0.576 | GI12: =Daily_Composite!N194 -> -0.413 | GJ12: =Daily_Composite!N195 -> 0.096 | GK12: =Daily_Composite!N196 -> -0.249 | GL12: =Daily_Composite!N197 -> -0.444 | GM12: =Daily_Composite!N198 -> -0.696 | GN12: =Daily_Composite!N199 -> -0.486 | GO12: =Daily_Composite!N200 -> -0.364 | GP12: =Daily_Composite!N201 -> -0.395 | GQ12: =Daily_Composite!N202 -> -0.581 | GR12: =Daily_Composite!N203 -> -0.523 | GS12: =Daily_Composite!N204 -> -0.385 | GT12: =Daily_Composite!N205 -> -0.225 | GU12: =Daily_Composite!N206 -> -0.604 | GV12: =Daily_Composite!N207 -> -0.477 | GW12: =Daily_Composite!N208 -> -0.367 | GX12: =Daily_Composite!N209 -> -0.252 | GY12: =Daily_Composite!N210 -> -0.113 | GZ12: =Daily_Composite!N211 -> -0.409 | HA12: =Daily_Composite!N212 -> -0.395 | HB12: =Daily_Composite!N213 -> -0.63 | HC12: =Daily_Composite!N214 -> -0.299 | HD12: =Daily_Composite!N215 -> -0.59 | HE12: =Daily_Composite!N216 -> -0.487 | HF12: =Daily_Composite!N217 -> -0.612 | HG12: =Daily_Composite!N218 -> -0.558 | HH12: =Daily_Composite!N219 -> -0.528 | HI12: =Daily_Composite!N220 -> -0.659 | HJ12: =Daily_Composite!N221 -> -0.684 | HK12: =Daily_Composite!N222 -> -0.554 | HL12: =Daily_Composite!N223 -> -0.575 | HM12: =Daily_Composite!N224 -> -0.667 | HN12: =Daily_Composite!N225 -> -0.623 | HO12: =Daily_Composite!N226 -> -0.503 | HP12: =Daily_Composite!N227 -> -0.507 | HQ12: =Daily_Composite!N228 -> -0.453 | HR12: =Daily_Composite!N229 -> -0.358 | HS12: =Daily_Composite!N230 -> -0.392 | HT12: =Daily_Composite!N231 -> -0.624 | HU12: =Daily_Composite!N232 -> -0.404 | HV12: =Daily_Composite!N233 -> -0.449 | HW12: =Daily_Composite!N234 -> -0.569 | HX12: =Daily_Composite!N235 -> -0.517 | HY12: =Daily_Composite!N236 -> -0.534 | HZ12: =Daily_Composite!N237 -> -0.494 | IA12: =Daily_Composite!N238 -> -0.364 | IB12: =Daily_Composite!N239 -> -0.36 | IC12: =Daily_Composite!N240 -> -0.563 | ID12: =Daily_Composite!N241 -> -0.374 | IE12: =Daily_Composite!N242 -> -0.59 | IF12: =Daily_Composite!N243 -> -0.633 | IG12: =Daily_Composite!N244 -> -0.581 | IH12: =Daily_Composite!N245 -> -0.136 | II12: =Daily_Composite!N246 -> -0.446 | IJ12: =Daily_Composite!N247 -> -0.341 | IK12: =Daily_Composite!N248 -> -0.18 | IL12: =Daily_Composite!N249 -> -0.064 | IM12: =Daily_Composite!N250 -> -0.27 | IN12: =Daily_Composite!N251 -> -0.088 | IO12: =Daily_Composite!N252 -> -0.388 | IP12: =Daily_Composite!N253 -> -0.612 | IQ12: =Daily_Composite!N254 -> -0.157 | IR12: =Daily_Composite!N255 -> -0.385 | IS12: =Daily_Composite!N256 -> -0.7 | IT12: =Daily_Composite!N257 -> -0.592 | IU12: =Daily_Composite!N258 -> -0.078 | IV12: =Daily_Composite!N259 -> -0.117 | IW12: =Daily_Composite!N260 -> -0.276 | IX12: =Daily_Composite!N261 -> -0.339 | IY12: =Daily_Composite!N262 -> -0.639 | IZ12: =Daily_Composite!N263 -> -0.453 | JA12: =Daily_Composite!N264 -> -0.314 | JB12: =Daily_Composite!N265 -> -0.572 | JC12: =Daily_Composite!N266 -> -0.655 | JD12: =Daily_Composite!N267 -> -0.281 | JE12: =Daily_Composite!N268 -> -0.319 | JF12: =Daily_Composite!N269 -> -0.413 | JG12: =Daily_Composite!N270 -> -0.788 | JH12: =Daily_Composite!N271 -> -0.856 | JI12: =Daily_Composite!N272 -> -0.732 | JJ12: =Daily_Composite!N273 -> -0.567 | JK12: =Daily_Composite!N274 -> -0.652 | JL12: =Daily_Composite!N275 -> -0.548 | JM12: =Daily_Composite!N276 -> -0.149 | JN12: =Daily_Composite!N277 -> -0.284 | JO12: =Daily_Composite!N278 -> -0.244 | JP12: =Daily_Composite!N279 -> -0.593 | JQ12: =Daily_Composite!N280 -> -0.519 | JR12: =Daily_Composite!N281 -> -0.754 | JS12: =Daily_Composite!N282 -> -0.484 | JT12: =Daily_Composite!N283 -> -0.394 | JU12: =Daily_Composite!N284 -> -0.725 | JV12: =Daily_Composite!N285 -> -0.585 | JW12: =Daily_Composite!N286 -> -0.17 | JX12: =Daily_Composite!N287 -> -0.219 | JY12: =Daily_Composite!N288 -> -0.233 | JZ12: =Daily_Composite!N289 -> -0.131 | KA12: =Daily_Composite!N290 -> -0.539 | KB12: =Daily_Composite!N291 -> -0.442 | KC12: =Daily_Composite!N292 -> -0.731 | KD12: =Daily_Composite!N293 -> -0.51 | KE12: =Daily_Composite!N294 -> 0.054 | KF12: =Daily_Composite!N295 -> 0.131 | KG12: =Daily_Composite!N296 -> -0.151 | KH12: =Daily_Composite!N297 -> -0.644 | KI12: =Daily_Composite!N298 -> -0.708 | KJ12: =Daily_Composite!N299 -> -0.605 | KK12: =Daily_Composite!N300 -> -0.497 | KL12: =Daily_Composite!N301 -> -0.509 | KM12: =Daily_Composite!N302 -> -0.304 | KN12: =Daily_Composite!N303 -> -0.003 | KO12: =Daily_Composite!N304 -> -0.229 | KP12: =Daily_Composite!N305 -> -0.328 | KQ12: =Daily_Composite!N306 -> -0.246 | KR12: =Daily_Composite!N307 -> -0.451 | KS12: =Daily_Composite!N308 -> -0.605 | KT12: =Daily_Composite!N309 -> -0.408 | KU12: =Daily_Composite!N310 -> -0.271 | KV12: =Daily_Composite!N311 -> -0.679 | KW12: =Daily_Composite!N312 -> -0.607 | KX12: =Daily_Composite!N313 -> -0.224 | KY12: =Daily_Composite!N314 -> -0.182 | KZ12: =Daily_Composite!N315 -> -0.274 | LA12: =Daily_Composite!N316 -> -0.528 | LB12: =Daily_Composite!N317 -> -0.37 | LC12: =Daily_Composite!N318 -> -0.363 | LD12: =Daily_Composite!N319 -> -0.411 | LE12: =Daily_Composite!N320 -> -0.586 | LF12: =Daily_Composite!N321 -> -0.257 | LG12: =Daily_Composite!N322 -> 0.059 | LH12: =Daily_Composite!N323 -> 0.061 | LI12: =Daily_Composite!N324 -> -0.463 | LJ12: =Daily_Composite!N325 -> -0.605 | LK12: =Daily_Composite!N326 -> -0.62 | LL12: =Daily_Composite!N327 -> -0.064 | LM12: =Daily_Composite!N328 -> -0.048 | LN12: =Daily_Composite!N329 -> -0.125 | LO12: =Daily_Composite!N330 -> -0.55 | LP12: =Daily_Composite!N331 -> 0.091 | LQ12: =Daily_Composite!N332 -> 0.224 | LR12: =Daily_Composite!N333 -> 0.259 | LS12: =Daily_Composite!N334 -> 0.017 | LT12: =Daily_Composite!N335 -> -0.22 | LU12: =Daily_Composite!N336 -> -0.525 | LV12: =Daily_Composite!N337 -> 0.035 | LW12: =Daily_Composite!N338 -> -0.271 | LX12: =Daily_Composite!N339 -> -0.376 | LY12: =Daily_Composite!N340 -> 0.028 | LZ12: =Daily_Composite!N341 -> 0.075 | MA12: =Daily_Composite!N342 -> 0.002 | MB12: =Daily_Composite!N343 -> -0.321 | MC12: =Daily_Composite!N344 -> -0.529 | MD12: =Daily_Composite!N345 -> -0.048 | ME12: =Daily_Composite!N346 -> 0.071 | MF12: =Daily_Composite!N347 -> 0.273 | MG12: =Daily_Composite!N348 -> -0.172 | MH12: =Daily_Composite!N349 -> 0.138 | MI12: =Daily_Composite!N350 -> 0.23 | MJ12: =Daily_Composite!N351 -> 0.277 | MK12: =Daily_Composite!N352 -> -0.376 | ML12: =Daily_Composite!N353 -> -0.248 | MM12: =Daily_Composite!N354 -> 0.188 | MN12: =Daily_Composite!N355 -> -0.068 | MO12: =Daily_Composite!N356 -> 0.025 | MP12: =Daily_Composite!N357 -> 0.483 | MQ12: =Daily_Composite!N358 -> 0.303 | MR12: =Daily_Composite!N359 -> -0.254 | MS12: =Daily_Composite!N360 -> -0.183 | MT12: =Daily_Composite!N361 -> -0.17 | MU12: =Daily_Composite!N362 -> -0.139 | MV12: =Daily_Composite!N363 -> -0.146 | MW12: =Daily_Composite!N364 -> -0.15 | MX12: =Daily_Composite!N365 -> -0.202 | MY12: =Daily_Composite!N366 -> 0.19 | MZ12: =Daily_Composite!N367 -> -0.46 | NA12: =Daily_Composite!N368 -> -0.125 | NB12: =Daily_Composite!N369 -> -0.21
A13: Eatable oil | B13: =Daily_Composite!O5 -> 0.073 | C13: =Daily_Composite!O6 -> 0.016 | D13: =Daily_Composite!O7 -> -0.006 | E13: =Daily_Composite!O8 -> 0.039 | F13: =Daily_Composite!O9 -> -0.424 | G13: =Daily_Composite!O10 -> -0.162 | H13: =Daily_Composite!O11 -> -0.12 | I13: =Daily_Composite!O12 -> -0.038 | J13: =Daily_Composite!O13 -> -0.087 | K13: =Daily_Composite!O14 -> -0.185 | L13: =Daily_Composite!O15 -> -0.526 | M13: =Daily_Composite!O16 -> -0.258 | N13: =Daily_Composite!O17 -> -0.213 | O13: =Daily_Composite!O18 -> -0.519 | P13: =Daily_Composite!O19 -> -0.215 | Q13: =Daily_Composite!O20 -> -0.197 | R13: =Daily_Composite!O21 -> -0.101 | S13: =Daily_Composite!O22 -> -0.105 | T13: =Daily_Composite!O23 -> -0.215 | U13: =Daily_Composite!O24 -> -0.21 | V13: =Daily_Composite!O25 -> -0.208 | W13: =Daily_Composite!O26 -> -0.191 | X13: =Daily_Composite!O27 -> -0.14 | Y13: =Daily_Composite!O28 -> 0.411 | Z13: =Daily_Composite!O29 -> -0.127 | AA13: =Daily_Composite!O30 -> -0.345 | AB13: =Daily_Composite!O31 -> -0.015 | AC13: =Daily_Composite!O32 -> -0.049 | AD13: =Daily_Composite!O33 -> -0.129 | AE13: =Daily_Composite!O34 -> -0.131 | AF13: =Daily_Composite!O35 -> -0.148 | AG13: =Daily_Composite!O36 -> -0.125 | AH13: =Daily_Composite!O37 -> 0.394 | AI13: =Daily_Composite!O38 -> -0.047 | AJ13: =Daily_Composite!O39 -> 0 | AK13: =Daily_Composite!O40 -> -0.066 | AL13: =Daily_Composite!O41 -> -0.088 | AM13: =Daily_Composite!O42 -> -0.178 | AN13: =Daily_Composite!O43 -> -0.082 | AO13: =Daily_Composite!O44 -> -0.086 | AP13: =Daily_Composite!O45 -> -0.051 | AQ13: =Daily_Composite!O46 -> 0.473 | AR13: =Daily_Composite!O47 -> -0.035 | AS13: =Daily_Composite!O48 -> -0.019 | AT13: =Daily_Composite!O49 -> 0.39 | AU13: =Daily_Composite!O50 -> 0.327 | AV13: =Daily_Composite!O51 -> 0.05 | AW13: =Daily_Composite!O52 -> 0.013 | AX13: =Daily_Composite!O53 -> -0.104 | AY13: =Daily_Composite!O54 -> 0.05 | AZ13: =Daily_Composite!O55 -> 0.132 | BA13: =Daily_Composite!O56 -> 0.465 | BB13: =Daily_Composite!O57 -> 0.174 | BC13: =Daily_Composite!O58 -> 0.338 | BD13: =Daily_Composite!O59 -> 0.034 | BE13: =Daily_Composite!O60 -> -0.009 | BF13: =Daily_Composite!O61 -> -0.185 | BG13: =Daily_Composite!O62 -> -0.074 | BH13: =Daily_Composite!O63 -> -0.027 | BI13: =Daily_Composite!O64 -> 0.307 | BJ13: =Daily_Composite!O65 -> -0.239 | BK13: =Daily_Composite!O66 -> -0.139 | BL13: =Daily_Composite!O67 -> -0.007 | BM13: =Daily_Composite!O68 -> -0.018 | BN13: =Daily_Composite!O69 -> -0.106 | BO13: =Daily_Composite!O70 -> -0.265 | BP13: =Daily_Composite!O71 -> -0.126 | BQ13: =Daily_Composite!O72 -> -0.138 | BR13: =Daily_Composite!O73 -> 0.207 | BS13: =Daily_Composite!O74 -> -0.141 | BT13: =Daily_Composite!O75 -> -0.087 | BU13: =Daily_Composite!O76 -> 0.243 | BV13: =Daily_Composite!O77 -> 0.231 | BW13: =Daily_Composite!O78 -> 0.202 | BX13: =Daily_Composite!O79 -> -0.127 | BY13: =Daily_Composite!O80 -> -0.144 | BZ13: =Daily_Composite!O81 -> 0.024 | CA13: =Daily_Composite!O82 -> 0.01 | CB13: =Daily_Composite!O83 -> 0.382 | CC13: =Daily_Composite!O84 -> -0.215 | CD13: =Daily_Composite!O85 -> 0.168 | CE13: =Daily_Composite!O86 -> -0.147 | CF13: =Daily_Composite!O87 -> -0.12 | CG13: =Daily_Composite!O88 -> -0.174 | CH13: =Daily_Composite!O89 -> -0.441 | CI13: =Daily_Composite!O90 -> -0.242 | CJ13: =Daily_Composite!O91 -> -0.279 | CK13: =Daily_Composite!O92 -> -0.081 | CL13: =Daily_Composite!O93 -> -0.512 | CM13: =Daily_Composite!O94 -> -0.284 | CN13: =Daily_Composite!O95 -> -0.412 | CO13: =Daily_Composite!O96 -> -0.343 | CP13: =Daily_Composite!O97 -> -0.623 | CQ13: =Daily_Composite!O98 -> -0.329 | CR13: =Daily_Composite!O99 -> -0.373 | CS13: =Daily_Composite!O100 -> -0.629 | CT13: =Daily_Composite!O101 -> -0.297 | CU13: =Daily_Composite!O102 -> -0.345 | CV13: =Daily_Composite!O103 -> -0.483 | CW13: =Daily_Composite!O104 -> -0.525 | CX13: =Daily_Composite!O105 -> -0.605 | CY13: =Daily_Composite!O106 -> -0.195 | CZ13: =Daily_Composite!O107 -> 0.07 | DA13: =Daily_Composite!O108 -> -0.278 | DB13: =Daily_Composite!O109 -> -0.278 | DC13: =Daily_Composite!O110 -> -0.029 | DD13: =Daily_Composite!O111 -> -0.059 | DE13: =Daily_Composite!O112 -> 0.009 | DF13: =Daily_Composite!O113 -> -0.223 | DG13: =Daily_Composite!O114 -> -0.261 | DH13: =Daily_Composite!O115 -> -0.317 | DI13: =Daily_Composite!O116 -> -0.508 | DJ13: =Daily_Composite!O117 -> -0.303 | DK13: =Daily_Composite!O118 -> -0.264 | DL13: =Daily_Composite!O119 -> -0.55 | DM13: =Daily_Composite!O120 -> -0.286 | DN13: =Daily_Composite!O121 -> -0.21 | DO13: =Daily_Composite!O122 -> -0.204 | DP13: =Daily_Composite!O123 -> -0.206 | DQ13: =Daily_Composite!O124 -> -0.464 | DR13: =Daily_Composite!O125 -> -0.276 | DS13: =Daily_Composite!O126 -> -0.186 | DT13: =Daily_Composite!O127 -> -0.486 | DU13: =Daily_Composite!O128 -> -0.258 | DV13: =Daily_Composite!O129 -> -0.292 | DW13: =Daily_Composite!O130 -> -0.273 | DX13: =Daily_Composite!O131 -> -0.542 | DY13: =Daily_Composite!O132 -> -0.595 | DZ13: =Daily_Composite!O133 -> -0.336 | EA13: =Daily_Composite!O134 -> -0.634 | EB13: =Daily_Composite!O135 -> -0.308 | EC13: =Daily_Composite!O136 -> -0.298 | ED13: =Daily_Composite!O137 -> -0.666 | EE13: =Daily_Composite!O138 -> -0.518 | EF13: =Daily_Composite!O139 -> -0.519 | EG13: =Daily_Composite!O140 -> -0.244 | EH13: =Daily_Composite!O141 -> -0.236 | EI13: =Daily_Composite!O142 -> -0.216 | EJ13: =Daily_Composite!O143 -> -0.538 | EK13: =Daily_Composite!O144 -> -0.331 | EL13: =Daily_Composite!O145 -> -0.212 | EM13: =Daily_Composite!O146 -> -0.449 | EN13: =Daily_Composite!O147 -> -0.064 | EO13: =Daily_Composite!O148 -> -0.228 | EP13: =Daily_Composite!O149 -> -0.128 | EQ13: =Daily_Composite!O150 -> -0.135 | ER13: =Daily_Composite!O151 -> -0.147 | ES13: =Daily_Composite!O152 -> -0.24 | ET13: =Daily_Composite!O153 -> -0.104 | EU13: =Daily_Composite!O154 -> -0.072 | EV13: =Daily_Composite!O155 -> 0.276 | EW13: =Daily_Composite!O156 -> -0.03 | EX13: =Daily_Composite!O157 -> -0.016 | EY13: =Daily_Composite!O158 -> 0.006 | EZ13: =Daily_Composite!O159 -> -0.184 | FA13: =Daily_Composite!O160 -> -0.149 | FB13: =Daily_Composite!O161 -> 0.384 | FC13: =Daily_Composite!O162 -> 0.111 | FD13: =Daily_Composite!O163 -> 0.085 | FE13: =Daily_Composite!O164 -> 0.087 | FF13: =Daily_Composite!O165 -> 0.515 | FG13: =Daily_Composite!O166 -> 0.36 | FH13: =Daily_Composite!O167 -> 0.418 | FI13: =Daily_Composite!O168 -> 0.027 | FJ13: =Daily_Composite!O169 -> -0.01 | FK13: =Daily_Composite!O170 -> -0.11 | FL13: =Daily_Composite!O171 -> -0.258 | FM13: =Daily_Composite!O172 -> -0.108 | FN13: =Daily_Composite!O173 -> -0.008 | FO13: =Daily_Composite!O174 -> -0.017 | FP13: =Daily_Composite!O175 -> 0.043 | FQ13: =Daily_Composite!O176 -> -0.216 | FR13: =Daily_Composite!O177 -> -0.205 | FS13: =Daily_Composite!O178 -> -0.251 | FT13: =Daily_Composite!O179 -> -0.56 | FU13: =Daily_Composite!O180 -> -0.251 | FV13: =Daily_Composite!O181 -> -0.146 | FW13: =Daily_Composite!O182 -> 0.001 | FX13: =Daily_Composite!O183 -> -0.146 | FY13: =Daily_Composite!O184 -> -0.125 | FZ13: =Daily_Composite!O185 -> 0.171 | GA13: =Daily_Composite!O186 -> -0.299 | GB13: =Daily_Composite!O187 -> -0.478 | GC13: =Daily_Composite!O188 -> -0.18 | GD13: =Daily_Composite!O189 -> -0.257 | GE13: =Daily_Composite!O190 -> -0.208 | GF13: =Daily_Composite!O191 -> -0.299 | GG13: =Daily_Composite!O192 -> -0.628 | GH13: =Daily_Composite!O193 -> -0.48 | GI13: =Daily_Composite!O194 -> -0.416 | GJ13: =Daily_Composite!O195 -> -0.189 | GK13: =Daily_Composite!O196 -> -0.205 | GL13: =Daily_Composite!O197 -> -0.235 | GM13: =Daily_Composite!O198 -> -0.493 | GN13: =Daily_Composite!O199 -> -0.201 | GO13: =Daily_Composite!O200 -> -0.173 | GP13: =Daily_Composite!O201 -> -0.485 | GQ13: =Daily_Composite!O202 -> -0.119 | GR13: =Daily_Composite!O203 -> -0.28 | GS13: =Daily_Composite!O204 -> -0.192 | GT13: =Daily_Composite!O205 -> -0.168 | GU13: =Daily_Composite!O206 -> -0.416 | GV13: =Daily_Composite!O207 -> -0.216 | GW13: =Daily_Composite!O208 -> -0.192 | GX13: =Daily_Composite!O209 -> -0.539 | GY13: =Daily_Composite!O210 -> -0.306 | GZ13: =Daily_Composite!O211 -> -0.213 | HA13: =Daily_Composite!O212 -> -0.153 | HB13: =Daily_Composite!O213 -> -0.484 | HC13: =Daily_Composite!O214 -> -0.599 | HD13: =Daily_Composite!O215 -> -0.197 | HE13: =Daily_Composite!O216 -> -0.127 | HF13: =Daily_Composite!O217 -> -0.188 | HG13: =Daily_Composite!O218 -> -0.324 | HH13: =Daily_Composite!O219 -> -0.562 | HI13: =Daily_Composite!O220 -> -0.245 | HJ13: =Daily_Composite!O221 -> -0.204 | HK13: =Daily_Composite!O222 -> -0.184 | HL13: =Daily_Composite!O223 -> -0.205 | HM13: =Daily_Composite!O224 -> -0.211 | HN13: =Daily_Composite!O225 -> -0.379 | HO13: =Daily_Composite!O226 -> -0.15 | HP13: =Daily_Composite!O227 -> -0.181 | HQ13: =Daily_Composite!O228 -> -0.555 | HR13: =Daily_Composite!O229 -> -0.17 | HS13: =Daily_Composite!O230 -> -0.184 | HT13: =Daily_Composite!O231 -> -0.202 | HU13: =Daily_Composite!O232 -> -0.162 | HV13: =Daily_Composite!O233 -> -0.194 | HW13: =Daily_Composite!O234 -> -0.373 | HX13: =Daily_Composite!O235 -> -0.165 | HY13: =Daily_Composite!O236 -> -0.197 | HZ13: =Daily_Composite!O237 -> -0.564 | IA13: =Daily_Composite!O238 -> -0.141 | IB13: =Daily_Composite!O239 -> -0.134 | IC13: =Daily_Composite!O240 -> 0.079 | ID13: =Daily_Composite!O241 -> 0.163 | IE13: =Daily_Composite!O242 -> -0.172 | IF13: =Daily_Composite!O243 -> -0.309 | IG13: =Daily_Composite!O244 -> -0.14 | IH13: =Daily_Composite!O245 -> -0.125 | II13: =Daily_Composite!O246 -> -0.142 | IJ13: =Daily_Composite!O247 -> 0.372 | IK13: =Daily_Composite!O248 -> 0.236 | IL13: =Daily_Composite!O249 -> 0.342 | IM13: =Daily_Composite!O250 -> 0.018 | IN13: =Daily_Composite!O251 -> -0.046 | IO13: =Daily_Composite!O252 -> -0.059 | IP13: =Daily_Composite!O253 -> -0.073 | IQ13: =Daily_Composite!O254 -> -0.035 | IR13: =Daily_Composite!O255 -> 0.22 | IS13: =Daily_Composite!O256 -> -0.264 | IT13: =Daily_Composite!O257 -> -0.291 | IU13: =Daily_Composite!O258 -> -0.067 | IV13: =Daily_Composite!O259 -> -0.054 | IW13: =Daily_Composite!O260 -> -0.155 | IX13: =Daily_Composite!O261 -> -0.186 | IY13: =Daily_Composite!O262 -> -0.157 | IZ13: =Daily_Composite!O263 -> -0.125 | JA13: =Daily_Composite!O264 -> -0.148 | JB13: =Daily_Composite!O265 -> -0.084 | JC13: =Daily_Composite!O266 -> -0.092 | JD13: =Daily_Composite!O267 -> 0.156 | JE13: =Daily_Composite!O268 -> 0.023 | JF13: =Daily_Composite!O269 -> -0.044 | JG13: =Daily_Composite!O270 -> -0.104 | JH13: =Daily_Composite!O271 -> -0.221 | JI13: =Daily_Composite!O272 -> 0.016 | JJ13: =Daily_Composite!O273 -> 0.005 | JK13: =Daily_Composite!O274 -> 0.345 | JL13: =Daily_Composite!O275 -> 0.233 | JM13: =Daily_Composite!O276 -> 0.291 | JN13: =Daily_Composite!O277 -> -0.074 | JO13: =Daily_Composite!O278 -> -0.086 | JP13: =Daily_Composite!O279 -> -0.102 | JQ13: =Daily_Composite!O280 -> -0.096 | JR13: =Daily_Composite!O281 -> -0.063 | JS13: =Daily_Composite!O282 -> -0.075 | JT13: =Daily_Composite!O283 -> -0.143 | JU13: =Daily_Composite!O284 -> -0.192 | JV13: =Daily_Composite!O285 -> -0.264 | JW13: =Daily_Composite!O286 -> 0.003 | JX13: =Daily_Composite!O287 -> -0.012 | JY13: =Daily_Composite!O288 -> -0.097 | JZ13: =Daily_Composite!O289 -> -0.118 | KA13: =Daily_Composite!O290 -> -0.187 | KB13: =Daily_Composite!O291 -> -0.263 | KC13: =Daily_Composite!O292 -> -0.12 | KD13: =Daily_Composite!O293 -> -0.126 | KE13: =Daily_Composite!O294 -> 0.056 | KF13: =Daily_Composite!O295 -> 0.199 | KG13: =Daily_Composite!O296 -> 0.14 | KH13: =Daily_Composite!O297 -> -0.223 | KI13: =Daily_Composite!O298 -> -0.464 | KJ13: =Daily_Composite!O299 -> -0.18 | KK13: =Daily_Composite!O300 -> -0.044 | KL13: =Daily_Composite!O301 -> 0.014 | KM13: =Daily_Composite!O302 -> -0.193 | KN13: =Daily_Composite!O303 -> 0.045 | KO13: =Daily_Composite!O304 -> -0.119 | KP13: =Daily_Composite!O305 -> -0.077 | KQ13: =Daily_Composite!O306 -> -0.129 | KR13: =Daily_Composite!O307 -> -0.154 | KS13: =Daily_Composite!O308 -> -0.152 | KT13: =Daily_Composite!O309 -> -0.129 | KU13: =Daily_Composite!O310 -> -0.539 | KV13: =Daily_Composite!O311 -> -0.36 | KW13: =Daily_Composite!O312 -> -0.35 | KX13: =Daily_Composite!O313 -> 0.001 | KY13: =Daily_Composite!O314 -> 0.002 | KZ13: =Daily_Composite!O315 -> -0.102 | LA13: =Daily_Composite!O316 -> -0.174 | LB13: =Daily_Composite!O317 -> -0.176 | LC13: =Daily_Composite!O318 -> -0.153 | LD13: =Daily_Composite!O319 -> -0.016 | LE13: =Daily_Composite!O320 -> -0.073 | LF13: =Daily_Composite!O321 -> -0.159 | LG13: =Daily_Composite!O322 -> 0.231 | LH13: =Daily_Composite!O323 -> 0.376 | LI13: =Daily_Composite!O324 -> -0.084 | LJ13: =Daily_Composite!O325 -> -0.084 | LK13: =Daily_Composite!O326 -> -0.114 | LL13: =Daily_Composite!O327 -> 0.022 | LM13: =Daily_Composite!O328 -> 0.418 | LN13: =Daily_Composite!O329 -> 0.034 | LO13: =Daily_Composite!O330 -> -0.259 | LP13: =Daily_Composite!O331 -> -0.1 | LQ13: =Daily_Composite!O332 -> -0.053 | LR13: =Daily_Composite!O333 -> -0.038 | LS13: =Daily_Composite!O334 -> -0.064 | LT13: =Daily_Composite!O335 -> -0.155 | LU13: =Daily_Composite!O336 -> -0.086 | LV13: =Daily_Composite!O337 -> -0.053 | LW13: =Daily_Composite!O338 -> -0.186 | LX13: =Daily_Composite!O339 -> -0.225 | LY13: =Daily_Composite!O340 -> -0.033 | LZ13: =Daily_Composite!O341 -> 0.053 | MA13: =Daily_Composite!O342 -> 0.004 | MB13: =Daily_Composite!O343 -> -0.076 | MC13: =Daily_Composite!O344 -> 0.023 | MD13: =Daily_Composite!O345 -> 0.003 | ME13: =Daily_Composite!O346 -> 0.079 | MF13: =Daily_Composite!O347 -> -0.008 | MG13: =Daily_Composite!O348 -> -0.063 | MH13: =Daily_Composite!O349 -> -0.008 | MI13: =Daily_Composite!O350 -> 0.341 | MJ13: =Daily_Composite!O351 -> 0.29 | MK13: =Daily_Composite!O352 -> -0.252 | ML13: =Daily_Composite!O353 -> -0.163 | MM13: =Daily_Composite!O354 -> 0.018 | MN13: =Daily_Composite!O355 -> 0.039 | MO13: =Daily_Composite!O356 -> 0.445 | MP13: =Daily_Composite!O357 -> 0.346 | MQ13: =Daily_Composite!O358 -> 0.314 | MR13: =Daily_Composite!O359 -> -0.02 | MS13: =Daily_Composite!O360 -> 0.019 | MT13: =Daily_Composite!O361 -> -0.011 | MU13: =Daily_Composite!O362 -> -0.004 | MV13: =Daily_Composite!O363 -> 0.036 | MW13: =Daily_Composite!O364 -> 0.029 | MX13: =Daily_Composite!O365 -> 0.02 | MY13: =Daily_Composite!O366 -> -0.073 | MZ13: =Daily_Composite!O367 -> -0.234 | NA13: =Daily_Composite!O368 -> 0.055 | NB13: =Daily_Composite!O369 -> 0.092
A14: Educational | B14: =Daily_Composite!P5 -> -0.171 | C14: =Daily_Composite!P6 -> -0.142 | D14: =Daily_Composite!P7 -> -0.146 | E14: =Daily_Composite!P8 -> 0.218 | F14: =Daily_Composite!P9 -> -0.015 | G14: =Daily_Composite!P10 -> -0.109 | H14: =Daily_Composite!P11 -> 0.403 | I14: =Daily_Composite!P12 -> -0.101 | J14: =Daily_Composite!P13 -> -0.098 | K14: =Daily_Composite!P14 -> 0.319 | L14: =Daily_Composite!P15 -> 0.165 | M14: =Daily_Composite!P16 -> 0.147 | N14: =Daily_Composite!P17 -> -0.146 | O14: =Daily_Composite!P18 -> -0.156 | P14: =Daily_Composite!P19 -> -0.074 | Q14: =Daily_Composite!P20 -> 0.053 | R14: =Daily_Composite!P21 -> 0.237 | S14: =Daily_Composite!P22 -> -0.158 | T14: =Daily_Composite!P23 -> 0.039 | U14: =Daily_Composite!P24 -> 0.025 | V14: =Daily_Composite!P25 -> 0.038 | W14: =Daily_Composite!P26 -> 0.01 | X14: =Daily_Composite!P27 -> -0.017 | Y14: =Daily_Composite!P28 -> 0.01 | Z14: =Daily_Composite!P29 -> 0.01 | AA14: =Daily_Composite!P30 -> 0.372 | AB14: =Daily_Composite!P31 -> -0.042 | AC14: =Daily_Composite!P32 -> 0.015 | AD14: =Daily_Composite!P33 -> 0.038 | AE14: =Daily_Composite!P34 -> 0.038 | AF14: =Daily_Composite!P35 -> 0.23 | AG14: =Daily_Composite!P36 -> 0.035 | AH14: =Daily_Composite!P37 -> 0.019 | AI14: =Daily_Composite!P38 -> 0.398 | AJ14: =Daily_Composite!P39 -> 0.034 | AK14: =Daily_Composite!P40 -> 0.052 | AL14: =Daily_Composite!P41 -> 0.072 | AM14: =Daily_Composite!P42 -> 0.069 | AN14: =Daily_Composite!P43 -> 0.087 | AO14: =Daily_Composite!P44 -> 0.116 | AP14: =Daily_Composite!P45 -> 0.116 | AQ14: =Daily_Composite!P46 -> 0.078 | AR14: =Daily_Composite!P47 -> 0.083 | AS14: =Daily_Composite!P48 -> -0.188 | AT14: =Daily_Composite!P49 -> 0.101 | AU14: =Daily_Composite!P50 -> 0.077 | AV14: =Daily_Composite!P51 -> 0.049 | AW14: =Daily_Composite!P52 -> 0.049 | AX14: =Daily_Composite!P53 -> 0.052 | AY14: =Daily_Composite!P54 -> 0.029 | AZ14: =Daily_Composite!P55 -> -0.21 | BA14: =Daily_Composite!P56 -> -0.211 | BB14: =Daily_Composite!P57 -> -0.204 | BC14: =Daily_Composite!P58 -> -0.497 | BD14: =Daily_Composite!P59 -> -0.212 | BE14: =Daily_Composite!P60 -> -0.214 | BF14: =Daily_Composite!P61 -> -0.279 | BG14: =Daily_Composite!P62 -> -0.278 | BH14: =Daily_Composite!P63 -> 0.037 | BI14: =Daily_Composite!P64 -> 0.118 | BJ14: =Daily_Composite!P65 -> -0.157 | BK14: =Daily_Composite!P66 -> 0.266 | BL14: =Daily_Composite!P67 -> -0.197 | BM14: =Daily_Composite!P68 -> -0.175 | BN14: =Daily_Composite!P69 -> 0.178 | BO14: =Daily_Composite!P70 -> 0.164 | BP14: =Daily_Composite!P71 -> -0.18 | BQ14: =Daily_Composite!P72 -> -0.167 | BR14: =Daily_Composite!P73 -> -0.165 | BS14: =Daily_Composite!P74 -> -0.162 | BT14: =Daily_Composite!P75 -> 0.349 | BU14: =Daily_Composite!P76 -> -0.161 | BV14: =Daily_Composite!P77 -> -0.164 | BW14: =Daily_Composite!P78 -> -0.164 | BX14: =Daily_Composite!P79 -> -0.127 | BY14: =Daily_Composite!P80 -> -0.182 | BZ14: =Daily_Composite!P81 -> -0.16 | CA14: =Daily_Composite!P82 -> -0.156 | CB14: =Daily_Composite!P83 -> 0.035 | CC14: =Daily_Composite!P84 -> 0.038 | CD14: =Daily_Composite!P85 -> 0.511 | CE14: =Daily_Composite!P86 -> 0.075 | CF14: =Daily_Composite!P87 -> 0.075 | CG14: =Daily_Composite!P88 -> 0.059 | CH14: =Daily_Composite!P89 -> 0.05 | CI14: =Daily_Composite!P90 -> 0.386 | CJ14: =Daily_Composite!P91 -> 0.424 | CK14: =Daily_Composite!P92 -> 0.044 | CL14: =Daily_Composite!P93 -> 0.225 | CM14: =Daily_Composite!P94 -> 0.074 | CN14: =Daily_Composite!P95 -> 0.074 | CO14: =Daily_Composite!P96 -> 0.422 | CP14: =Daily_Composite!P97 -> 0.419 | CQ14: =Daily_Composite!P98 -> -0.012 | CR14: =Daily_Composite!P99 -> 0.031 | CS14: =Daily_Composite!P100 -> 0.008 | CT14: =Daily_Composite!P101 -> 0.008 | CU14: =Daily_Composite!P102 -> -0.41 | CV14: =Daily_Composite!P103 -> 0.008 | CW14: =Daily_Composite!P104 -> 0.01 | CX14: =Daily_Composite!P105 -> 0.012 | CY14: =Daily_Composite!P106 -> 0.042 | CZ14: =Daily_Composite!P107 -> 0.016 | DA14: =Daily_Composite!P108 -> 0 | DB14: =Daily_Composite!P109 -> -0.013 | DC14: =Daily_Composite!P110 -> -0.006 | DD14: =Daily_Composite!P111 -> 0.012 | DE14: =Daily_Composite!P112 -> -0.402 | DF14: =Daily_Composite!P113 -> 0.053 | DG14: =Daily_Composite!P114 -> 0.058 | DH14: =Daily_Composite!P115 -> -0.117 | DI14: =Daily_Composite!P116 -> -0.135 | DJ14: =Daily_Composite!P117 -> -0.143 | DK14: =Daily_Composite!P118 -> -0.256 | DL14: =Daily_Composite!P119 -> -0.121 | DM14: =Daily_Composite!P120 -> -0.123 | DN14: =Daily_Composite!P121 -> -0.351 | DO14: =Daily_Composite!P122 -> -0.141 | DP14: =Daily_Composite!P123 -> -0.139 | DQ14: =Daily_Composite!P124 -> -0.139 | DR14: =Daily_Composite!P125 -> -0.059 | DS14: =Daily_Composite!P126 -> -0.136 | DT14: =Daily_Composite!P127 -> -0.135 | DU14: =Daily_Composite!P128 -> -0.127 | DV14: =Daily_Composite!P129 -> -0.131 | DW14: =Daily_Composite!P130 -> 0.574 | DX14: =Daily_Composite!P131 -> -0.125 | DY14: =Daily_Composite!P132 -> 0.016 | DZ14: =Daily_Composite!P133 -> -0.005 | EA14: =Daily_Composite!P134 -> -0.008 | EB14: =Daily_Composite!P135 -> -0.014 | EC14: =Daily_Composite!P136 -> -0.032 | ED14: =Daily_Composite!P137 -> -0.021 | EE14: =Daily_Composite!P138 -> 0.035 | EF14: =Daily_Composite!P139 -> 0.494 | EG14: =Daily_Composite!P140 -> 0.084 | EH14: =Daily_Composite!P141 -> 0.094 | EI14: =Daily_Composite!P142 -> 0.097 | EJ14: =Daily_Composite!P143 -> 0.095 | EK14: =Daily_Composite!P144 -> 0.056 | EL14: =Daily_Composite!P145 -> -0.214 | EM14: =Daily_Composite!P146 -> -0.073 | EN14: =Daily_Composite!P147 -> 0.084 | EO14: =Daily_Composite!P148 -> -0.27 | EP14: =Daily_Composite!P149 -> 0.16 | EQ14: =Daily_Composite!P150 -> 0.174 | ER14: =Daily_Composite!P151 -> 0.199 | ES14: =Daily_Composite!P152 -> 0.195 | ET14: =Daily_Composite!P153 -> 0.128 | EU14: =Daily_Composite!P154 -> 0.104 | EV14: =Daily_Composite!P155 -> 0.132 | EW14: =Daily_Composite!P156 -> 0.135 | EX14: =Daily_Composite!P157 -> 0.269 | EY14: =Daily_Composite!P158 -> 0.133 | EZ14: =Daily_Composite!P159 -> 0.131 | FA14: =Daily_Composite!P160 -> 0.168 | FB14: =Daily_Composite!P161 -> 0.208 | FC14: =Daily_Composite!P162 -> 0.248 | FD14: =Daily_Composite!P163 -> 0.262 | FE14: =Daily_Composite!P164 -> 0.28 | FF14: =Daily_Composite!P165 -> 0.29 | FG14: =Daily_Composite!P166 -> 0.327 | FH14: =Daily_Composite!P167 -> 0.576 | FI14: =Daily_Composite!P168 -> 0.361 | FJ14: =Daily_Composite!P169 -> 0.319 | FK14: =Daily_Composite!P170 -> 0.276 | FL14: =Daily_Composite!P171 -> 0.255 | FM14: =Daily_Composite!P172 -> 0.628 | FN14: =Daily_Composite!P173 -> 0.583 | FO14: =Daily_Composite!P174 -> 0.187 | FP14: =Daily_Composite!P175 -> 0.241 | FQ14: =Daily_Composite!P176 -> 0.139 | FR14: =Daily_Composite!P177 -> 0.136 | FS14: =Daily_Composite!P178 -> 0.274 | FT14: =Daily_Composite!P179 -> 0.104 | FU14: =Daily_Composite!P180 -> 0.025 | FV14: =Daily_Composite!P181 -> 0.097 | FW14: =Daily_Composite!P182 -> 0.082 | FX14: =Daily_Composite!P183 -> 0.111 | FY14: =Daily_Composite!P184 -> -0.025 | FZ14: =Daily_Composite!P185 -> 0.099 | GA14: =Daily_Composite!P186 -> 0.115 | GB14: =Daily_Composite!P187 -> 0.136 | GC14: =Daily_Composite!P188 -> 0.136 | GD14: =Daily_Composite!P189 -> 0.135 | GE14: =Daily_Composite!P190 -> 0.133 | GF14: =Daily_Composite!P191 -> 0.131 | GG14: =Daily_Composite!P192 -> 0.104 | GH14: =Daily_Composite!P193 -> 0.129 | GI14: =Daily_Composite!P194 -> 0.364 | GJ14: =Daily_Composite!P195 -> 0.091 | GK14: =Daily_Composite!P196 -> 0.075 | GL14: =Daily_Composite!P197 -> 0.03 | GM14: =Daily_Composite!P198 -> 0.032 | GN14: =Daily_Composite!P199 -> 0.364 | GO14: =Daily_Composite!P200 -> 0.374 | GP14: =Daily_Composite!P201 -> 0.057 | GQ14: =Daily_Composite!P202 -> 0.051 | GR14: =Daily_Composite!P203 -> 0.524 | GS14: =Daily_Composite!P204 -> 0.038 | GT14: =Daily_Composite!P205 -> 0.059 | GU14: =Daily_Composite!P206 -> 0.4 | GV14: =Daily_Composite!P207 -> 0.399 | GW14: =Daily_Composite!P208 -> 0.046 | GX14: =Daily_Composite!P209 -> 0.044 | GY14: =Daily_Composite!P210 -> 0.011 | GZ14: =Daily_Composite!P211 -> -0.002 | HA14: =Daily_Composite!P212 -> 0.435 | HB14: =Daily_Composite!P213 -> 0.009 | HC14: =Daily_Composite!P214 -> -0.029 | HD14: =Daily_Composite!P215 -> -0.006 | HE14: =Daily_Composite!P216 -> -0.01 | HF14: =Daily_Composite!P217 -> -0.032 | HG14: =Daily_Composite!P218 -> -0.044 | HH14: =Daily_Composite!P219 -> -0.028 | HI14: =Daily_Composite!P220 -> -0.028 | HJ14: =Daily_Composite!P221 -> -0.028 | HK14: =Daily_Composite!P222 -> -0.035 | HL14: =Daily_Composite!P223 -> -0.042 | HM14: =Daily_Composite!P224 -> -0.049 | HN14: =Daily_Composite!P225 -> -0.054 | HO14: =Daily_Composite!P226 -> -0.057 | HP14: =Daily_Composite!P227 -> -0.169 | HQ14: =Daily_Composite!P228 -> -0.107 | HR14: =Daily_Composite!P229 -> -0.068 | HS14: =Daily_Composite!P230 -> 0.337 | HT14: =Daily_Composite!P231 -> -0.042 | HU14: =Daily_Composite!P232 -> -0.005 | HV14: =Daily_Composite!P233 -> 0.236 | HW14: =Daily_Composite!P234 -> 0.236 | HX14: =Daily_Composite!P235 -> 0.014 | HY14: =Daily_Composite!P236 -> 0.063 | HZ14: =Daily_Composite!P237 -> 0.16 | IA14: =Daily_Composite!P238 -> 0.062 | IB14: =Daily_Composite!P239 -> 0.576 | IC14: =Daily_Composite!P240 -> 0.117 | ID14: =Daily_Composite!P241 -> 0.119 | IE14: =Daily_Composite!P242 -> 0.155 | IF14: =Daily_Composite!P243 -> 0.145 | IG14: =Daily_Composite!P244 -> 0.151 | IH14: =Daily_Composite!P245 -> 0.118 | II14: =Daily_Composite!P246 -> 0.142 | IJ14: =Daily_Composite!P247 -> 0.138 | IK14: =Daily_Composite!P248 -> 0.116 | IL14: =Daily_Composite!P249 -> 0.58 | IM14: =Daily_Composite!P250 -> 0.142 | IN14: =Daily_Composite!P251 -> 0.151 | IO14: =Daily_Composite!P252 -> 0.152 | IP14: =Daily_Composite!P253 -> 0.153 | IQ14: =Daily_Composite!P254 -> 0.486 | IR14: =Daily_Composite!P255 -> 0.48 | IS14: =Daily_Composite!P256 -> 0.154 | IT14: =Daily_Composite!P257 -> 0.593 | IU14: =Daily_Composite!P258 -> 0.156 | IV14: =Daily_Composite!P259 -> 0.157 | IW14: =Daily_Composite!P260 -> 0.497 | IX14: =Daily_Composite!P261 -> 0.498 | IY14: =Daily_Composite!P262 -> 0.123 | IZ14: =Daily_Composite!P263 -> 0.153 | JA14: =Daily_Composite!P264 -> 0.107 | JB14: =Daily_Composite!P265 -> 0.063 | JC14: =Daily_Composite!P266 -> 0.455 | JD14: =Daily_Composite!P267 -> -0.064 | JE14: =Daily_Composite!P268 -> -0.041 | JF14: =Daily_Composite!P269 -> -0.054 | JG14: =Daily_Composite!P270 -> -0.096 | JH14: =Daily_Composite!P271 -> -0.097 | JI14: =Daily_Composite!P272 -> -0.094 | JJ14: =Daily_Composite!P273 -> -0.121 | JK14: =Daily_Composite!P274 -> -0.139 | JL14: =Daily_Composite!P275 -> -0.118 | JM14: =Daily_Composite!P276 -> 0.275 | JN14: =Daily_Composite!P277 -> -0.118 | JO14: =Daily_Composite!P278 -> -0.114 | JP14: =Daily_Composite!P279 -> -0.109 | JQ14: =Daily_Composite!P280 -> -0.058 | JR14: =Daily_Composite!P281 -> -0.006 | JS14: =Daily_Composite!P282 -> 0.429 | JT14: =Daily_Composite!P283 -> 0.413 | JU14: =Daily_Composite!P284 -> 0.075 | JV14: =Daily_Composite!P285 -> 0.573 | JW14: =Daily_Composite!P286 -> 0.183 | JX14: =Daily_Composite!P287 -> 0.183 | JY14: =Daily_Composite!P288 -> 0.522 | JZ14: =Daily_Composite!P289 -> 0.53 | KA14: =Daily_Composite!P290 -> 0.171 | KB14: =Daily_Composite!P291 -> 0.208 | KC14: =Daily_Composite!P292 -> 0.21 | KD14: =Daily_Composite!P293 -> 0.623 | KE14: =Daily_Composite!P294 -> 0.165 | KF14: =Daily_Composite!P295 -> 0.119 | KG14: =Daily_Composite!P296 -> 0.026 | KH14: =Daily_Composite!P297 -> -0.073 | KI14: =Daily_Composite!P298 -> -0.019 | KJ14: =Daily_Composite!P299 -> -0.048 | KK14: =Daily_Composite!P300 -> 0.03 | KL14: =Daily_Composite!P301 -> 0.035 | KM14: =Daily_Composite!P302 -> 0.043 | KN14: =Daily_Composite!P303 -> 0.387 | KO14: =Daily_Composite!P304 -> 0.009 | KP14: =Daily_Composite!P305 -> 0.038 | KQ14: =Daily_Composite!P306 -> 0.043 | KR14: =Daily_Composite!P307 -> 0.011 | KS14: =Daily_Composite!P308 -> 0.002 | KT14: =Daily_Composite!P309 -> 0.326 | KU14: =Daily_Composite!P310 -> 0.328 | KV14: =Daily_Composite!P311 -> -0.046 | KW14: =Daily_Composite!P312 -> 0.373 | KX14: =Daily_Composite!P313 -> 0.005 | KY14: =Daily_Composite!P314 -> 0.007 | KZ14: =Daily_Composite!P315 -> -0.141 | LA14: =Daily_Composite!P316 -> -0.11 | LB14: =Daily_Composite!P317 -> 0.013 | LC14: =Daily_Composite!P318 -> 0.013 | LD14: =Daily_Composite!P319 -> 0.013 | LE14: =Daily_Composite!P320 -> 0.015 | LF14: =Daily_Composite!P321 -> 0.293 | LG14: =Daily_Composite!P322 -> -0.078 | LH14: =Daily_Composite!P323 -> -0.046 | LI14: =Daily_Composite!P324 -> -0.044 | LJ14: =Daily_Composite!P325 -> -0.072 | LK14: =Daily_Composite!P326 -> -0.064 | LL14: =Daily_Composite!P327 -> 0.069 | LM14: =Daily_Composite!P328 -> 0.135 | LN14: =Daily_Composite!P329 -> 0.04 | LO14: =Daily_Composite!P330 -> 0.046 | LP14: =Daily_Composite!P331 -> 0.433 | LQ14: =Daily_Composite!P332 -> 0.074 | LR14: =Daily_Composite!P333 -> 0.11 | LS14: =Daily_Composite!P334 -> 0.073 | LT14: =Daily_Composite!P335 -> -0.04 | LU14: =Daily_Composite!P336 -> -0.172 | LV14: =Daily_Composite!P337 -> 0.042 | LW14: =Daily_Composite!P338 -> -0.047 | LX14: =Daily_Composite!P339 -> -0.026 | LY14: =Daily_Composite!P340 -> -0.048 | LZ14: =Daily_Composite!P341 -> -0.019 | MA14: =Daily_Composite!P342 -> 0.068 | MB14: =Daily_Composite!P343 -> 0.094 | MC14: =Daily_Composite!P344 -> 0.123 | MD14: =Daily_Composite!P345 -> 0.096 | ME14: =Daily_Composite!P346 -> 0.132 | MF14: =Daily_Composite!P347 -> 0.15 | MG14: =Daily_Composite!P348 -> 0.589 | MH14: =Daily_Composite!P349 -> 0.185 | MI14: =Daily_Composite!P350 -> 0.203 | MJ14: =Daily_Composite!P351 -> 0.245 | MK14: =Daily_Composite!P352 -> 0.252 | ML14: =Daily_Composite!P353 -> 0.226 | MM14: =Daily_Composite!P354 -> 0.325 | MN14: =Daily_Composite!P355 -> 0.268 | MO14: =Daily_Composite!P356 -> 0.241 | MP14: =Daily_Composite!P357 -> 0.198 | MQ14: =Daily_Composite!P358 -> 0.551 | MR14: =Daily_Composite!P359 -> 0.088 | MS14: =Daily_Composite!P360 -> 0.093 | MT14: =Daily_Composite!P361 -> 0.073 | MU14: =Daily_Composite!P362 -> 0.085 | MV14: =Daily_Composite!P363 -> 0.213 | MW14: =Daily_Composite!P364 -> 0.374 | MX14: =Daily_Composite!P365 -> 0.375 | MY14: =Daily_Composite!P366 -> 0.003 | MZ14: =Daily_Composite!P367 -> 0.526 | NA14: =Daily_Composite!P368 -> -0.07 | NB14: =Daily_Composite!P369 -> -0.019
A15: Essential oils & perfumeries | B15: =Daily_Composite!Q5 -> -0.377 | C15: =Daily_Composite!Q6 -> 0.028 | D15: =Daily_Composite!Q7 -> -0.241 | E15: =Daily_Composite!Q8 -> -0.195 | F15: =Daily_Composite!Q9 -> -0.114 | G15: =Daily_Composite!Q10 -> 0.059 | H15: =Daily_Composite!Q11 -> 0.342 | I15: =Daily_Composite!Q12 -> 0.107 | J15: =Daily_Composite!Q13 -> 0.215 | K15: =Daily_Composite!Q14 -> 0.136 | L15: =Daily_Composite!Q15 -> -0.18 | M15: =Daily_Composite!Q16 -> 0.137 | N15: =Daily_Composite!Q17 -> 0.388 | O15: =Daily_Composite!Q18 -> 0.398 | P15: =Daily_Composite!Q19 -> 0.248 | Q15: =Daily_Composite!Q20 -> 0.168 | R15: =Daily_Composite!Q21 -> 0.37 | S15: =Daily_Composite!Q22 -> 0.198 | T15: =Daily_Composite!Q23 -> 0.586 | U15: =Daily_Composite!Q24 -> 0.156 | V15: =Daily_Composite!Q25 -> 0.177 | W15: =Daily_Composite!Q26 -> 0.105 | X15: =Daily_Composite!Q27 -> 0.12 | Y15: =Daily_Composite!Q28 -> 0.177 | Z15: =Daily_Composite!Q29 -> 0.139 | AA15: =Daily_Composite!Q30 -> 0.371 | AB15: =Daily_Composite!Q31 -> 0.177 | AC15: =Daily_Composite!Q32 -> 0.435 | AD15: =Daily_Composite!Q33 -> 0.404 | AE15: =Daily_Composite!Q34 -> 0.423 | AF15: =Daily_Composite!Q35 -> 0.073 | AG15: =Daily_Composite!Q36 -> 0.178 | AH15: =Daily_Composite!Q37 -> 0.031 | AI15: =Daily_Composite!Q38 -> 0.305 | AJ15: =Daily_Composite!Q39 -> 0.18 | AK15: =Daily_Composite!Q40 -> 0.527 | AL15: =Daily_Composite!Q41 -> 0.11 | AM15: =Daily_Composite!Q42 -> -0.404 | AN15: =Daily_Composite!Q43 -> -0.066 | AO15: =Daily_Composite!Q44 -> -0.24 | AP15: =Daily_Composite!Q45 -> -0.158 | AQ15: =Daily_Composite!Q46 -> 0.017 | AR15: =Daily_Composite!Q47 -> -0.006 | AS15: =Daily_Composite!Q48 -> -0.222 | AT15: =Daily_Composite!Q49 -> 0.025 | AU15: =Daily_Composite!Q50 -> 0.022 | AV15: =Daily_Composite!Q51 -> 0.008 | AW15: =Daily_Composite!Q52 -> -0.247 | AX15: =Daily_Composite!Q53 -> -0.006 | AY15: =Daily_Composite!Q54 -> 0.055 | AZ15: =Daily_Composite!Q55 -> -0.009 | BA15: =Daily_Composite!Q56 -> -0.028 | BB15: =Daily_Composite!Q57 -> -0.017 | BC15: =Daily_Composite!Q58 -> -0.38 | BD15: =Daily_Composite!Q59 -> 0.045 | BE15: =Daily_Composite!Q60 -> -0.395 | BF15: =Daily_Composite!Q61 -> -0.368 | BG15: =Daily_Composite!Q62 -> 0.006 | BH15: =Daily_Composite!Q63 -> -0.075 | BI15: =Daily_Composite!Q64 -> -0.109 | BJ15: =Daily_Composite!Q65 -> -0.199 | BK15: =Daily_Composite!Q66 -> -0.15 | BL15: =Daily_Composite!Q67 -> 0.067 | BM15: =Daily_Composite!Q68 -> 0.056 | BN15: =Daily_Composite!Q69 -> -0.096 | BO15: =Daily_Composite!Q70 -> -0.5 | BP15: =Daily_Composite!Q71 -> -0.355 | BQ15: =Daily_Composite!Q72 -> -0.319 | BR15: =Daily_Composite!Q73 -> -0.304 | BS15: =Daily_Composite!Q74 -> -0.174 | BT15: =Daily_Composite!Q75 -> 0.043 | BU15: =Daily_Composite!Q76 -> -0.096 | BV15: =Daily_Composite!Q77 -> -0.271 | BW15: =Daily_Composite!Q78 -> -0.03 | BX15: =Daily_Composite!Q79 -> -0.286 | BY15: =Daily_Composite!Q80 -> -0.374 | BZ15: =Daily_Composite!Q81 -> -0.006 | CA15: =Daily_Composite!Q82 -> -0.007 | CB15: =Daily_Composite!Q83 -> -0.033 | CC15: =Daily_Composite!Q84 -> -0.101 | CD15: =Daily_Composite!Q85 -> 0.294 | CE15: =Daily_Composite!Q86 -> 0.023 | CF15: =Daily_Composite!Q87 -> 0.301 | CG15: =Daily_Composite!Q88 -> -0.443 | CH15: =Daily_Composite!Q89 -> -0.519 | CI15: =Daily_Composite!Q90 -> -0.042 | CJ15: =Daily_Composite!Q91 -> 0.03 | CK15: =Daily_Composite!Q92 -> -0.022 | CL15: =Daily_Composite!Q93 -> -0.159 | CM15: =Daily_Composite!Q94 -> 0.039 | CN15: =Daily_Composite!Q95 -> -0.226 | CO15: =Daily_Composite!Q96 -> -0.184 | CP15: =Daily_Composite!Q97 -> -0.413 | CQ15: =Daily_Composite!Q98 -> -0.328 | CR15: =Daily_Composite!Q99 -> -0.231 | CS15: =Daily_Composite!Q100 -> 0.165 | CT15: =Daily_Composite!Q101 -> -0.044 | CU15: =Daily_Composite!Q102 -> -0.371 | CV15: =Daily_Composite!Q103 -> -0.064 | CW15: =Daily_Composite!Q104 -> -0.086 | CX15: =Daily_Composite!Q105 -> -0.292 | CY15: =Daily_Composite!Q106 -> 0.004 | CZ15: =Daily_Composite!Q107 -> 0.273 | DA15: =Daily_Composite!Q108 -> -0.066 | DB15: =Daily_Composite!Q109 -> -0.069 | DC15: =Daily_Composite!Q110 -> -0.065 | DD15: =Daily_Composite!Q111 -> -0.058 | DE15: =Daily_Composite!Q112 -> -0.433 | DF15: =Daily_Composite!Q113 -> -0.004 | DG15: =Daily_Composite!Q114 -> 0.105 | DH15: =Daily_Composite!Q115 -> 0.162 | DI15: =Daily_Composite!Q116 -> -0.317 | DJ15: =Daily_Composite!Q117 -> -0.005 | DK15: =Daily_Composite!Q118 -> -0.171 | DL15: =Daily_Composite!Q119 -> -0.103 | DM15: =Daily_Composite!Q120 -> -0.066 | DN15: =Daily_Composite!Q121 -> -0.412 | DO15: =Daily_Composite!Q122 -> 0 | DP15: =Daily_Composite!Q123 -> -0.018 | DQ15: =Daily_Composite!Q124 -> -0.451 | DR15: =Daily_Composite!Q125 -> -0.098 | DS15: =Daily_Composite!Q126 -> 0.195 | DT15: =Daily_Composite!Q127 -> 0.244 | DU15: =Daily_Composite!Q128 -> 0.051 | DV15: =Daily_Composite!Q129 -> 0.015 | DW15: =Daily_Composite!Q130 -> 0.409 | DX15: =Daily_Composite!Q131 -> 0.002 | DY15: =Daily_Composite!Q132 -> 0.434 | DZ15: =Daily_Composite!Q133 -> -0.02 | EA15: =Daily_Composite!Q134 -> -0.318 | EB15: =Daily_Composite!Q135 -> -0.029 | EC15: =Daily_Composite!Q136 -> 0.05 | ED15: =Daily_Composite!Q137 -> 0.081 | EE15: =Daily_Composite!Q138 -> 0.022 | EF15: =Daily_Composite!Q139 -> 0.256 | EG15: =Daily_Composite!Q140 -> -0.007 | EH15: =Daily_Composite!Q141 -> -0.034 | EI15: =Daily_Composite!Q142 -> -0.053 | EJ15: =Daily_Composite!Q143 -> -0.43 | EK15: =Daily_Composite!Q144 -> -0.345 | EL15: =Daily_Composite!Q145 -> -0.047 | EM15: =Daily_Composite!Q146 -> -0.143 | EN15: =Daily_Composite!Q147 -> -0.062 | EO15: =Daily_Composite!Q148 -> -0.348 | EP15: =Daily_Composite!Q149 -> -0.114 | EQ15: =Daily_Composite!Q150 -> -0.089 | ER15: =Daily_Composite!Q151 -> -0.216 | ES15: =Daily_Composite!Q152 -> -0.414 | ET15: =Daily_Composite!Q153 -> -0.318 | EU15: =Daily_Composite!Q154 -> -0.142 | EV15: =Daily_Composite!Q155 -> -0.148 | EW15: =Daily_Composite!Q156 -> 0.023 | EX15: =Daily_Composite!Q157 -> 0.103 | EY15: =Daily_Composite!Q158 -> -0.188 | EZ15: =Daily_Composite!Q159 -> 0.16 | FA15: =Daily_Composite!Q160 -> -0.195 | FB15: =Daily_Composite!Q161 -> 0.045 | FC15: =Daily_Composite!Q162 -> -0.237 | FD15: =Daily_Composite!Q163 -> -0.232 | FE15: =Daily_Composite!Q164 -> -0.221 | FF15: =Daily_Composite!Q165 -> -0.161 | FG15: =Daily_Composite!Q166 -> -0.172 | FH15: =Daily_Composite!Q167 -> -0.152 | FI15: =Daily_Composite!Q168 -> -0.192 | FJ15: =Daily_Composite!Q169 -> -0.378 | FK15: =Daily_Composite!Q170 -> -0.376 | FL15: =Daily_Composite!Q171 -> -0.53 | FM15: =Daily_Composite!Q172 -> -0.164 | FN15: =Daily_Composite!Q173 -> -0.207 | FO15: =Daily_Composite!Q174 -> -0.211 | FP15: =Daily_Composite!Q175 -> -0.161 | FQ15: =Daily_Composite!Q176 -> -0.128 | FR15: =Daily_Composite!Q177 -> 0.407 | FS15: =Daily_Composite!Q178 -> -0.284 | FT15: =Daily_Composite!Q179 -> -0.513 | FU15: =Daily_Composite!Q180 -> -0.271 | FV15: =Daily_Composite!Q181 -> 0.049 | FW15: =Daily_Composite!Q182 -> -0.216 | FX15: =Daily_Composite!Q183 -> -0.253 | FY15: =Daily_Composite!Q184 -> -0.418 | FZ15: =Daily_Composite!Q185 -> -0.155 | GA15: =Daily_Composite!Q186 -> 0.221 | GB15: =Daily_Composite!Q187 -> 0.213 | GC15: =Daily_Composite!Q188 -> -0.197 | GD15: =Daily_Composite!Q189 -> 0.021 | GE15: =Daily_Composite!Q190 -> 0.032 | GF15: =Daily_Composite!Q191 -> -0.02 | GG15: =Daily_Composite!Q192 -> -0.045 | GH15: =Daily_Composite!Q193 -> 0.015 | GI15: =Daily_Composite!Q194 -> -0.019 | GJ15: =Daily_Composite!Q195 -> -0.024 | GK15: =Daily_Composite!Q196 -> 0.368 | GL15: =Daily_Composite!Q197 -> -0.035 | GM15: =Daily_Composite!Q198 -> -0.481 | GN15: =Daily_Composite!Q199 -> 0.057 | GO15: =Daily_Composite!Q200 -> -0.003 | GP15: =Daily_Composite!Q201 -> -0.029 | GQ15: =Daily_Composite!Q202 -> -0.146 | GR15: =Daily_Composite!Q203 -> 0.237 | GS15: =Daily_Composite!Q204 -> -0.225 | GT15: =Daily_Composite!Q205 -> -0.189 | GU15: =Daily_Composite!Q206 -> -0.596 | GV15: =Daily_Composite!Q207 -> -0.346 | GW15: =Daily_Composite!Q208 -> -0.566 | GX15: =Daily_Composite!Q209 -> -0.553 | GY15: =Daily_Composite!Q210 -> -0.159 | GZ15: =Daily_Composite!Q211 -> -0.189 | HA15: =Daily_Composite!Q212 -> 0.108 | HB15: =Daily_Composite!Q213 -> -0.314 | HC15: =Daily_Composite!Q214 -> -0.58 | HD15: =Daily_Composite!Q215 -> -0.071 | HE15: =Daily_Composite!Q216 -> 0.091 | HF15: =Daily_Composite!Q217 -> -0.107 | HG15: =Daily_Composite!Q218 -> -0.163 | HH15: =Daily_Composite!Q219 -> -0.158 | HI15: =Daily_Composite!Q220 -> -0.091 | HJ15: =Daily_Composite!Q221 -> -0.094 | HK15: =Daily_Composite!Q222 -> -0.417 | HL15: =Daily_Composite!Q223 -> -0.659 | HM15: =Daily_Composite!Q224 -> -0.356 | HN15: =Daily_Composite!Q225 -> -0.744 | HO15: =Daily_Composite!Q226 -> -0.69 | HP15: =Daily_Composite!Q227 -> -0.458 | HQ15: =Daily_Composite!Q228 -> -0.454 | HR15: =Daily_Composite!Q229 -> -0.307 | HS15: =Daily_Composite!Q230 -> 0.032 | HT15: =Daily_Composite!Q231 -> -0.361 | HU15: =Daily_Composite!Q232 -> -0.539 | HV15: =Daily_Composite!Q233 -> -0.375 | HW15: =Daily_Composite!Q234 -> -0.543 | HX15: =Daily_Composite!Q235 -> -0.459 | HY15: =Daily_Composite!Q236 -> -0.312 | HZ15: =Daily_Composite!Q237 -> 0.057 | IA15: =Daily_Composite!Q238 -> -0.075 | IB15: =Daily_Composite!Q239 -> 0.249 | IC15: =Daily_Composite!Q240 -> -0.133 | ID15: =Daily_Composite!Q241 -> 0.079 | IE15: =Daily_Composite!Q242 -> -0.169 | IF15: =Daily_Composite!Q243 -> -0.47 | IG15: =Daily_Composite!Q244 -> -0.26 | IH15: =Daily_Composite!Q245 -> -0.12 | II15: =Daily_Composite!Q246 -> -0.106 | IJ15: =Daily_Composite!Q247 -> -0.181 | IK15: =Daily_Composite!Q248 -> -0.252 | IL15: =Daily_Composite!Q249 -> 0.207 | IM15: =Daily_Composite!Q250 -> -0.189 | IN15: =Daily_Composite!Q251 -> 0.396 | IO15: =Daily_Composite!Q252 -> -0.022 | IP15: =Daily_Composite!Q253 -> -0.194 | IQ15: =Daily_Composite!Q254 -> -0.286 | IR15: =Daily_Composite!Q255 -> -0.291 | IS15: =Daily_Composite!Q256 -> -0.218 | IT15: =Daily_Composite!Q257 -> 0.222 | IU15: =Daily_Composite!Q258 -> 0.005 | IV15: =Daily_Composite!Q259 -> 0.377 | IW15: =Daily_Composite!Q260 -> -0.207 | IX15: =Daily_Composite!Q261 -> -0.208 | IY15: =Daily_Composite!Q262 -> 0.067 | IZ15: =Daily_Composite!Q263 -> -0.232 | JA15: =Daily_Composite!Q264 -> -0.202 | JB15: =Daily_Composite!Q265 -> -0.022 | JC15: =Daily_Composite!Q266 -> 0.31 | JD15: =Daily_Composite!Q267 -> -0.095 | JE15: =Daily_Composite!Q268 -> 0.268 | JF15: =Daily_Composite!Q269 -> -0.121 | JG15: =Daily_Composite!Q270 -> -0.105 | JH15: =Daily_Composite!Q271 -> -0.461 | JI15: =Daily_Composite!Q272 -> -0.111 | JJ15: =Daily_Composite!Q273 -> -0.178 | JK15: =Daily_Composite!Q274 -> -0.354 | JL15: =Daily_Composite!Q275 -> -0.317 | JM15: =Daily_Composite!Q276 -> -0.015 | JN15: =Daily_Composite!Q277 -> -0.344 | JO15: =Daily_Composite!Q278 -> -0.679 | JP15: =Daily_Composite!Q279 -> -0.393 | JQ15: =Daily_Composite!Q280 -> -0.529 | JR15: =Daily_Composite!Q281 -> -0.351 | JS15: =Daily_Composite!Q282 -> -0.278 | JT15: =Daily_Composite!Q283 -> -0.287 | JU15: =Daily_Composite!Q284 -> -0.245 | JV15: =Daily_Composite!Q285 -> 0.163 | JW15: =Daily_Composite!Q286 -> 0.105 | JX15: =Daily_Composite!Q287 -> -0.159 | JY15: =Daily_Composite!Q288 -> -0.295 | JZ15: =Daily_Composite!Q289 -> -0.44 | KA15: =Daily_Composite!Q290 -> -0.13 | KB15: =Daily_Composite!Q291 -> -0.091 | KC15: =Daily_Composite!Q292 -> -0.353 | KD15: =Daily_Composite!Q293 -> 0.11 | KE15: =Daily_Composite!Q294 -> -0.337 | KF15: =Daily_Composite!Q295 -> -0.299 | KG15: =Daily_Composite!Q296 -> -0.344 | KH15: =Daily_Composite!Q297 -> -0.348 | KI15: =Daily_Composite!Q298 -> -0.346 | KJ15: =Daily_Composite!Q299 -> -0.2 | KK15: =Daily_Composite!Q300 -> -0.194 | KL15: =Daily_Composite!Q301 -> -0.173 | KM15: =Daily_Composite!Q302 -> -0.238 | KN15: =Daily_Composite!Q303 -> 0.195 | KO15: =Daily_Composite!Q304 -> -0.273 | KP15: =Daily_Composite!Q305 -> -0.27 | KQ15: =Daily_Composite!Q306 -> 0.163 | KR15: =Daily_Composite!Q307 -> -0.316 | KS15: =Daily_Composite!Q308 -> -0.41 | KT15: =Daily_Composite!Q309 -> -0.313 | KU15: =Daily_Composite!Q310 -> -0.264 | KV15: =Daily_Composite!Q311 -> -0.441 | KW15: =Daily_Composite!Q312 -> -0.155 | KX15: =Daily_Composite!Q313 -> -0.146 | KY15: =Daily_Composite!Q314 -> -0.685 | KZ15: =Daily_Composite!Q315 -> -0.22 | LA15: =Daily_Composite!Q316 -> -0.436 | LB15: =Daily_Composite!Q317 -> -0.518 | LC15: =Daily_Composite!Q318 -> -0.5 | LD15: =Daily_Composite!Q319 -> -0.127 | LE15: =Daily_Composite!Q320 -> -0.018 | LF15: =Daily_Composite!Q321 -> 0.037 | LG15: =Daily_Composite!Q322 -> -0.122 | LH15: =Daily_Composite!Q323 -> 0.566 | LI15: =Daily_Composite!Q324 -> -0.106 | LJ15: =Daily_Composite!Q325 -> -0.301 | LK15: =Daily_Composite!Q326 -> -0.1 | LL15: =Daily_Composite!Q327 -> 0.006 | LM15: =Daily_Composite!Q328 -> 0.011 | LN15: =Daily_Composite!Q329 -> -0.211 | LO15: =Daily_Composite!Q330 -> -0.267 | LP15: =Daily_Composite!Q331 -> -0.154 | LQ15: =Daily_Composite!Q332 -> -0.34 | LR15: =Daily_Composite!Q333 -> -0.074 | LS15: =Daily_Composite!Q334 -> -0.478 | LT15: =Daily_Composite!Q335 -> -0.663 | LU15: =Daily_Composite!Q336 -> -0.487 | LV15: =Daily_Composite!Q337 -> -0.512 | LW15: =Daily_Composite!Q338 -> -0.508 | LX15: =Daily_Composite!Q339 -> -0.531 | LY15: =Daily_Composite!Q340 -> -0.346 | LZ15: =Daily_Composite!Q341 -> -0.525 | MA15: =Daily_Composite!Q342 -> -0.461 | MB15: =Daily_Composite!Q343 -> -0.555 | MC15: =Daily_Composite!Q344 -> -0.419 | MD15: =Daily_Composite!Q345 -> -0.406 | ME15: =Daily_Composite!Q346 -> -0.403 | MF15: =Daily_Composite!Q347 -> -0.015 | MG15: =Daily_Composite!Q348 -> 0.243 | MH15: =Daily_Composite!Q349 -> 0.044 | MI15: =Daily_Composite!Q350 -> 0.504 | MJ15: =Daily_Composite!Q351 -> 0.225 | MK15: =Daily_Composite!Q352 -> -0.229 | ML15: =Daily_Composite!Q353 -> -0.076 | MM15: =Daily_Composite!Q354 -> 0.298 | MN15: =Daily_Composite!Q355 -> 0.126 | MO15: =Daily_Composite!Q356 -> 0.179 | MP15: =Daily_Composite!Q357 -> 0.156 | MQ15: =Daily_Composite!Q358 -> 0.438 | MR15: =Daily_Composite!Q359 -> -0.022 | MS15: =Daily_Composite!Q360 -> 0.345 | MT15: =Daily_Composite!Q361 -> -0.003 | MU15: =Daily_Composite!Q362 -> -0.023 | MV15: =Daily_Composite!Q363 -> -0.214 | MW15: =Daily_Composite!Q364 -> -0.342 | MX15: =Daily_Composite!Q365 -> -0.296 | MY15: =Daily_Composite!Q366 -> -0.244 | MZ15: =Daily_Composite!Q367 -> 0.116 | NA15: =Daily_Composite!Q368 -> -0.116 | NB15: =Daily_Composite!Q369 -> -0.465
A16: Exports | B16: =Daily_Composite!R5 -> -0.117 | C16: =Daily_Composite!R6 -> -0.191 | D16: =Daily_Composite!R7 -> -0.192 | E16: =Daily_Composite!R8 -> -0.209 | F16: =Daily_Composite!R9 -> -0.461 | G16: =Daily_Composite!R10 -> -0.283 | H16: =Daily_Composite!R11 -> -0.294 | I16: =Daily_Composite!R12 -> -0.133 | J16: =Daily_Composite!R13 -> -0.167 | K16: =Daily_Composite!R14 -> -0.261 | L16: =Daily_Composite!R15 -> -0.325 | M16: =Daily_Composite!R16 -> -0.348 | N16: =Daily_Composite!R17 -> -0.322 | O16: =Daily_Composite!R18 -> -0.604 | P16: =Daily_Composite!R19 -> -0.282 | Q16: =Daily_Composite!R20 -> -0.259 | R16: =Daily_Composite!R21 -> -0.294 | S16: =Daily_Composite!R22 -> -0.316 | T16: =Daily_Composite!R23 -> -0.34 | U16: =Daily_Composite!R24 -> -0.261 | V16: =Daily_Composite!R25 -> -0.252 | W16: =Daily_Composite!R26 -> -0.265 | X16: =Daily_Composite!R27 -> -0.255 | Y16: =Daily_Composite!R28 -> 0.117 | Z16: =Daily_Composite!R29 -> -0.233 | AA16: =Daily_Composite!R30 -> -0.323 | AB16: =Daily_Composite!R31 -> -0.203 | AC16: =Daily_Composite!R32 -> -0.22 | AD16: =Daily_Composite!R33 -> -0.244 | AE16: =Daily_Composite!R34 -> -0.244 | AF16: =Daily_Composite!R35 -> -0.215 | AG16: =Daily_Composite!R36 -> 0.001 | AH16: =Daily_Composite!R37 -> 0.429 | AI16: =Daily_Composite!R38 -> 0.027 | AJ16: =Daily_Composite!R39 -> 0.03 | AK16: =Daily_Composite!R40 -> -0.021 | AL16: =Daily_Composite!R41 -> -0.021 | AM16: =Daily_Composite!R42 -> -0.053 | AN16: =Daily_Composite!R43 -> -0.052 | AO16: =Daily_Composite!R44 -> -0.007 | AP16: =Daily_Composite!R45 -> 0.01 | AQ16: =Daily_Composite!R46 -> 0.471 | AR16: =Daily_Composite!R47 -> 0.008 | AS16: =Daily_Composite!R48 -> 0.016 | AT16: =Daily_Composite!R49 -> 0.367 | AU16: =Daily_Composite!R50 -> 0.315 | AV16: =Daily_Composite!R51 -> 0.168 | AW16: =Daily_Composite!R52 -> 0.103 | AX16: =Daily_Composite!R53 -> 0.098 | AY16: =Daily_Composite!R54 -> 0.094 | AZ16: =Daily_Composite!R55 -> 0.015 | BA16: =Daily_Composite!R56 -> 0.486 | BB16: =Daily_Composite!R57 -> 0.161 | BC16: =Daily_Composite!R58 -> 0.138 | BD16: =Daily_Composite!R59 -> -0.116 | BE16: =Daily_Composite!R60 -> -0.134 | BF16: =Daily_Composite!R61 -> -0.084 | BG16: =Daily_Composite!R62 -> -0.073 | BH16: =Daily_Composite!R63 -> -0.237 | BI16: =Daily_Composite!R64 -> 0.107 | BJ16: =Daily_Composite!R65 -> -0.166 | BK16: =Daily_Composite!R66 -> -0.162 | BL16: =Daily_Composite!R67 -> -0.015 | BM16: =Daily_Composite!R68 -> 0.007 | BN16: =Daily_Composite!R69 -> -0.228 | BO16: =Daily_Composite!R70 -> -0.234 | BP16: =Daily_Composite!R71 -> -0.042 | BQ16: =Daily_Composite!R72 -> -0.059 | BR16: =Daily_Composite!R73 -> 0.156 | BS16: =Daily_Composite!R74 -> -0.032 | BT16: =Daily_Composite!R75 -> 0.004 | BU16: =Daily_Composite!R76 -> 0.088 | BV16: =Daily_Composite!R77 -> -0.069 | BW16: =Daily_Composite!R78 -> -0.03 | BX16: =Daily_Composite!R79 -> 0.02 | BY16: =Daily_Composite!R80 -> -0.113 | BZ16: =Daily_Composite!R81 -> -0.074 | CA16: =Daily_Composite!R82 -> -0.071 | CB16: =Daily_Composite!R83 -> 0.434 | CC16: =Daily_Composite!R84 -> 0.206 | CD16: =Daily_Composite!R85 -> 0.394 | CE16: =Daily_Composite!R86 -> 0.173 | CF16: =Daily_Composite!R87 -> 0.098 | CG16: =Daily_Composite!R88 -> 0.123 | CH16: =Daily_Composite!R89 -> 0.116 | CI16: =Daily_Composite!R90 -> 0.113 | CJ16: =Daily_Composite!R91 -> 0.179 | CK16: =Daily_Composite!R92 -> 0.169 | CL16: =Daily_Composite!R93 -> 0.019 | CM16: =Daily_Composite!R94 -> 0.105 | CN16: =Daily_Composite!R95 -> -0.121 | CO16: =Daily_Composite!R96 -> -0.03 | CP16: =Daily_Composite!R97 -> -0.063 | CQ16: =Daily_Composite!R98 -> -0.054 | CR16: =Daily_Composite!R99 -> -0.07 | CS16: =Daily_Composite!R100 -> -0.457 | CT16: =Daily_Composite!R101 -> -0.068 | CU16: =Daily_Composite!R102 -> -0.12 | CV16: =Daily_Composite!R103 -> -0.287 | CW16: =Daily_Composite!R104 -> -0.413 | CX16: =Daily_Composite!R105 -> -0.455 | CY16: =Daily_Composite!R106 -> -0.083 | CZ16: =Daily_Composite!R107 -> -0.126 | DA16: =Daily_Composite!R108 -> -0.238 | DB16: =Daily_Composite!R109 -> -0.24 | DC16: =Daily_Composite!R110 -> -0.238 | DD16: =Daily_Composite!R111 -> 0.094 | DE16: =Daily_Composite!R112 -> 0.117 | DF16: =Daily_Composite!R113 -> -0.182 | DG16: =Daily_Composite!R114 -> -0.204 | DH16: =Daily_Composite!R115 -> -0.224 | DI16: =Daily_Composite!R116 -> -0.22 | DJ16: =Daily_Composite!R117 -> -0.234 | DK16: =Daily_Composite!R118 -> -0.329 | DL16: =Daily_Composite!R119 -> -0.503 | DM16: =Daily_Composite!R120 -> 0 | DN16: =Daily_Composite!R121 -> -0.092 | DO16: =Daily_Composite!R122 -> -0.215 | DP16: =Daily_Composite!R123 -> -0.206 | DQ16: =Daily_Composite!R124 -> -0.275 | DR16: =Daily_Composite!R125 -> -0.267 | DS16: =Daily_Composite!R126 -> -0.16 | DT16: =Daily_Composite!R127 -> -0.45 | DU16: =Daily_Composite!R128 -> -0.204 | DV16: =Daily_Composite!R129 -> -0.281 | DW16: =Daily_Composite!R130 -> -0.325 | DX16: =Daily_Composite!R131 -> -0.495 | DY16: =Daily_Composite!R132 -> -0.556 | DZ16: =Daily_Composite!R133 -> -0.181 | EA16: =Daily_Composite!R134 -> -0.229 | EB16: =Daily_Composite!R135 -> -0.202 | EC16: =Daily_Composite!R136 -> -0.193 | ED16: =Daily_Composite!R137 -> -0.649 | EE16: =Daily_Composite!R138 -> -0.45 | EF16: =Daily_Composite!R139 -> -0.404 | EG16: =Daily_Composite!R140 -> -0.157 | EH16: =Daily_Composite!R141 -> -0.117 | EI16: =Daily_Composite!R142 -> -0.094 | EJ16: =Daily_Composite!R143 -> -0.11 | EK16: =Daily_Composite!R144 -> -0.131 | EL16: =Daily_Composite!R145 -> -0.097 | EM16: =Daily_Composite!R146 -> -0.444 | EN16: =Daily_Composite!R147 -> -0.044 | EO16: =Daily_Composite!R148 -> -0.009 | EP16: =Daily_Composite!R149 -> -0.05 | EQ16: =Daily_Composite!R150 -> -0.033 | ER16: =Daily_Composite!R151 -> -0.167 | ES16: =Daily_Composite!R152 -> -0.139 | ET16: =Daily_Composite!R153 -> -0.039 | EU16: =Daily_Composite!R154 -> 0.105 | EV16: =Daily_Composite!R155 -> 0.265 | EW16: =Daily_Composite!R156 -> 0.116 | EX16: =Daily_Composite!R157 -> 0.145 | EY16: =Daily_Composite!R158 -> 0.211 | EZ16: =Daily_Composite!R159 -> 0.099 | FA16: =Daily_Composite!R160 -> 0.128 | FB16: =Daily_Composite!R161 -> 0.095 | FC16: =Daily_Composite!R162 -> 0.097 | FD16: =Daily_Composite!R163 -> 0.196 | FE16: =Daily_Composite!R164 -> 0.216 | FF16: =Daily_Composite!R165 -> 0.608 | FG16: =Daily_Composite!R166 -> 0.541 | FH16: =Daily_Composite!R167 -> 0.527 | FI16: =Daily_Composite!R168 -> 0.204 | FJ16: =Daily_Composite!R169 -> 0.17 | FK16: =Daily_Composite!R170 -> 0.121 | FL16: =Daily_Composite!R171 -> 0.098 | FM16: =Daily_Composite!R172 -> 0.138 | FN16: =Daily_Composite!R173 -> 0.298 | FO16: =Daily_Composite!R174 -> 0.043 | FP16: =Daily_Composite!R175 -> -0.041 | FQ16: =Daily_Composite!R176 -> -0.023 | FR16: =Daily_Composite!R177 -> -0.009 | FS16: =Daily_Composite!R178 -> -0.108 | FT16: =Daily_Composite!R179 -> -0.12 | FU16: =Daily_Composite!R180 -> -0.138 | FV16: =Daily_Composite!R181 -> -0.021 | FW16: =Daily_Composite!R182 -> -0.336 | FX16: =Daily_Composite!R183 -> -0.065 | FY16: =Daily_Composite!R184 -> -0.119 | FZ16: =Daily_Composite!R185 -> -0.07 | GA16: =Daily_Composite!R186 -> -0.351 | GB16: =Daily_Composite!R187 -> -0.421 | GC16: =Daily_Composite!R188 -> -0.134 | GD16: =Daily_Composite!R189 -> -0.047 | GE16: =Daily_Composite!R190 -> -0.081 | GF16: =Daily_Composite!R191 -> -0.243 | GG16: =Daily_Composite!R192 -> -0.566 | GH16: =Daily_Composite!R193 -> -0.411 | GI16: =Daily_Composite!R194 -> -0.321 | GJ16: =Daily_Composite!R195 -> -0.131 | GK16: =Daily_Composite!R196 -> -0.168 | GL16: =Daily_Composite!R197 -> -0.188 | GM16: =Daily_Composite!R198 -> -0.165 | GN16: =Daily_Composite!R199 -> 0.003 | GO16: =Daily_Composite!R200 -> 0.033 | GP16: =Daily_Composite!R201 -> -0.427 | GQ16: =Daily_Composite!R202 -> -0.015 | GR16: =Daily_Composite!R203 -> -0.001 | GS16: =Daily_Composite!R204 -> -0.139 | GT16: =Daily_Composite!R205 -> -0.115 | GU16: =Daily_Composite!R206 -> -0.256 | GV16: =Daily_Composite!R207 -> -0.176 | GW16: =Daily_Composite!R208 -> -0.051 | GX16: =Daily_Composite!R209 -> -0.473 | GY16: =Daily_Composite!R210 -> -0.465 | GZ16: =Daily_Composite!R211 -> -0.131 | HA16: =Daily_Composite!R212 -> -0.057 | HB16: =Daily_Composite!R213 -> -0.436 | HC16: =Daily_Composite!R214 -> -0.455 | HD16: =Daily_Composite!R215 -> 0.038 | HE16: =Daily_Composite!R216 -> 0.064 | HF16: =Daily_Composite!R217 -> 0.067 | HG16: =Daily_Composite!R218 -> -0.102 | HH16: =Daily_Composite!R219 -> -0.472 | HI16: =Daily_Composite!R220 -> -0.06 | HJ16: =Daily_Composite!R221 -> -0.009 | HK16: =Daily_Composite!R222 -> -0.152 | HL16: =Daily_Composite!R223 -> -0.144 | HM16: =Daily_Composite!R224 -> -0.01 | HN16: =Daily_Composite!R225 -> -0.013 | HO16: =Daily_Composite!R226 -> -0.013 | HP16: =Daily_Composite!R227 -> -0.075 | HQ16: =Daily_Composite!R228 -> -0.443 | HR16: =Daily_Composite!R229 -> 0.121 | HS16: =Daily_Composite!R230 -> 0.007 | HT16: =Daily_Composite!R231 -> -0.029 | HU16: =Daily_Composite!R232 -> -0.028 | HV16: =Daily_Composite!R233 -> 0.081 | HW16: =Daily_Composite!R234 -> -0.003 | HX16: =Daily_Composite!R235 -> -0.028 | HY16: =Daily_Composite!R236 -> -0.034 | HZ16: =Daily_Composite!R237 -> -0.393 | IA16: =Daily_Composite!R238 -> 0.16 | IB16: =Daily_Composite!R239 -> 0.067 | IC16: =Daily_Composite!R240 -> 0.092 | ID16: =Daily_Composite!R241 -> 0.131 | IE16: =Daily_Composite!R242 -> 0.077 | IF16: =Daily_Composite!R243 -> -0.107 | IG16: =Daily_Composite!R244 -> -0.083 | IH16: =Daily_Composite!R245 -> 0.038 | II16: =Daily_Composite!R246 -> 0.072 | IJ16: =Daily_Composite!R247 -> 0.481 | IK16: =Daily_Composite!R248 -> 0.445 | IL16: =Daily_Composite!R249 -> 0.469 | IM16: =Daily_Composite!R250 -> 0.282 | IN16: =Daily_Composite!R251 -> 0.229 | IO16: =Daily_Composite!R252 -> 0.223 | IP16: =Daily_Composite!R253 -> 0.175 | IQ16: =Daily_Composite!R254 -> 0.143 | IR16: =Daily_Composite!R255 -> 0.364 | IS16: =Daily_Composite!R256 -> -0.13 | IT16: =Daily_Composite!R257 -> -0.136 | IU16: =Daily_Composite!R258 -> -0.097 | IV16: =Daily_Composite!R259 -> -0.102 | IW16: =Daily_Composite!R260 -> -0.292 | IX16: =Daily_Composite!R261 -> -0.276 | IY16: =Daily_Composite!R262 -> -0.165 | IZ16: =Daily_Composite!R263 -> -0.138 | JA16: =Daily_Composite!R264 -> -0.115 | JB16: =Daily_Composite!R265 -> -0.084 | JC16: =Daily_Composite!R266 -> -0.062 | JD16: =Daily_Composite!R267 -> 0.077 | JE16: =Daily_Composite!R268 -> -0.095 | JF16: =Daily_Composite!R269 -> -0.09 | JG16: =Daily_Composite!R270 -> -0.061 | JH16: =Daily_Composite!R271 -> -0.094 | JI16: =Daily_Composite!R272 -> -0.094 | JJ16: =Daily_Composite!R273 -> -0.099 | JK16: =Daily_Composite!R274 -> 0.299 | JL16: =Daily_Composite!R275 -> 0.136 | JM16: =Daily_Composite!R276 -> 0.215 | JN16: =Daily_Composite!R277 -> -0.33 | JO16: =Daily_Composite!R278 -> -0.323 | JP16: =Daily_Composite!R279 -> -0.303 | JQ16: =Daily_Composite!R280 -> -0.237 | JR16: =Daily_Composite!R281 -> -0.245 | JS16: =Daily_Composite!R282 -> -0.266 | JT16: =Daily_Composite!R283 -> -0.288 | JU16: =Daily_Composite!R284 -> -0.225 | JV16: =Daily_Composite!R285 -> -0.214 | JW16: =Daily_Composite!R286 -> -0.175 | JX16: =Daily_Composite!R287 -> -0.184 | JY16: =Daily_Composite!R288 -> -0.368 | JZ16: =Daily_Composite!R289 -> -0.237 | KA16: =Daily_Composite!R290 -> -0.228 | KB16: =Daily_Composite!R291 -> -0.285 | KC16: =Daily_Composite!R292 -> -0.281 | KD16: =Daily_Composite!R293 -> -0.252 | KE16: =Daily_Composite!R294 -> -0.27 | KF16: =Daily_Composite!R295 -> -0.1 | KG16: =Daily_Composite!R296 -> -0.323 | KH16: =Daily_Composite!R297 -> -0.362 | KI16: =Daily_Composite!R298 -> -0.314 | KJ16: =Daily_Composite!R299 -> -0.344 | KK16: =Daily_Composite!R300 -> -0.359 | KL16: =Daily_Composite!R301 -> -0.392 | KM16: =Daily_Composite!R302 -> -0.363 | KN16: =Daily_Composite!R303 -> -0.187 | KO16: =Daily_Composite!R304 -> -0.357 | KP16: =Daily_Composite!R305 -> -0.343 | KQ16: =Daily_Composite!R306 -> -0.361 | KR16: =Daily_Composite!R307 -> -0.404 | KS16: =Daily_Composite!R308 -> -0.402 | KT16: =Daily_Composite!R309 -> -0.37 | KU16: =Daily_Composite!R310 -> -0.538 | KV16: =Daily_Composite!R311 -> -0.203 | KW16: =Daily_Composite!R312 -> -0.164 | KX16: =Daily_Composite!R313 -> 0.025 | KY16: =Daily_Composite!R314 -> 0.032 | KZ16: =Daily_Composite!R315 -> 0.05 | LA16: =Daily_Composite!R316 -> 0.055 | LB16: =Daily_Composite!R317 -> 0.039 | LC16: =Daily_Composite!R318 -> 0.045 | LD16: =Daily_Composite!R319 -> 0.229 | LE16: =Daily_Composite!R320 -> 0.078 | LF16: =Daily_Composite!R321 -> -0.153 | LG16: =Daily_Composite!R322 -> 0.244 | LH16: =Daily_Composite!R323 -> 0.377 | LI16: =Daily_Composite!R324 -> -0.054 | LJ16: =Daily_Composite!R325 -> -0.082 | LK16: =Daily_Composite!R326 -> -0.098 | LL16: =Daily_Composite!R327 -> -0.055 | LM16: =Daily_Composite!R328 -> 0.467 | LN16: =Daily_Composite!R329 -> 0.167 | LO16: =Daily_Composite!R330 -> -0.163 | LP16: =Daily_Composite!R331 -> -0.064 | LQ16: =Daily_Composite!R332 -> -0.34 | LR16: =Daily_Composite!R333 -> -0.262 | LS16: =Daily_Composite!R334 -> -0.223 | LT16: =Daily_Composite!R335 -> -0.313 | LU16: =Daily_Composite!R336 -> -0.418 | LV16: =Daily_Composite!R337 -> -0.473 | LW16: =Daily_Composite!R338 -> -0.294 | LX16: =Daily_Composite!R339 -> -0.288 | LY16: =Daily_Composite!R340 -> -0.301 | LZ16: =Daily_Composite!R341 -> -0.261 | MA16: =Daily_Composite!R342 -> -0.421 | MB16: =Daily_Composite!R343 -> -0.422 | MC16: =Daily_Composite!R344 -> -0.389 | MD16: =Daily_Composite!R345 -> -0.262 | ME16: =Daily_Composite!R346 -> -0.199 | MF16: =Daily_Composite!R347 -> -0.216 | MG16: =Daily_Composite!R348 -> -0.213 | MH16: =Daily_Composite!R349 -> -0.083 | MI16: =Daily_Composite!R350 -> 0.192 | MJ16: =Daily_Composite!R351 -> 0.184 | MK16: =Daily_Composite!R352 -> -0.175 | ML16: =Daily_Composite!R353 -> -0.2 | MM16: =Daily_Composite!R354 -> -0.186 | MN16: =Daily_Composite!R355 -> -0.153 | MO16: =Daily_Composite!R356 -> 0.393 | MP16: =Daily_Composite!R357 -> 0.296 | MQ16: =Daily_Composite!R358 -> 0.3 | MR16: =Daily_Composite!R359 -> -0.121 | MS16: =Daily_Composite!R360 -> -0.092 | MT16: =Daily_Composite!R361 -> -0.155 | MU16: =Daily_Composite!R362 -> -0.143 | MV16: =Daily_Composite!R363 -> -0.199 | MW16: =Daily_Composite!R364 -> -0.165 | MX16: =Daily_Composite!R365 -> -0.125 | MY16: =Daily_Composite!R366 -> -0.149 | MZ16: =Daily_Composite!R367 -> -0.149 | NA16: =Daily_Composite!R368 -> -0.02 | NB16: =Daily_Composite!R369 -> -0.003
